Workbook

Sheet Summary – Option 1
A1: SurTrac co-packaging – priority companies and drugs (Option 1 – injectable shipments)
A2: 2x2: unit price (x) × injectable shipments (#) (y); bubble = injectable export value ($'000). Priority 1 = high price AND high volume (top-right); Priority 2 = one of the two high; Priority 3 = both lower; cut-offs = median of eligible pairs (Scoring C3 / E3). Drugs with an ID / IM / SC route on a label in the 7 geographies only (IV-only drugs removed). Companies ranked by number of Priority 1 drugs, then opportunity of Priority 1 + 2; within a company, drugs by tier, then opportunity. Price ≤ $5 listed last as Excluded.
A3: Packaging: strength and fill per unit container (no carton sizes). Avg price: average per unit (per dose for multi-dose vaccine vials) of presentations priced > $5; Excluded rows: average of all priced presentations (all ≤ $5). Volume = India FY24 shipments of the molecule (all dosage forms) × injectable share of registered products in the 7 geographies. Volume is molecule-level (same for every company). Markets: countries where the company (or its group entity) holds an authorisation – a proxy for where it is supplied. Filters, assumptions and limitations: see the tab of that name. Live – linked to Scoring; grey helper column O orders the list.
A4: Company rank | B4: Company | C4: Drug rank | D4: Priority tier | E4: 2x2 quadrant | F4: Drug (API) | G4: Product name | H4: Drug utility | I4: Presentation | J4: Packaging (per unit) | K4: Avg price (USD / unit) | L4: Injectable shipments (#) | M4: Injectable export value ($'000) | N4: Markets where the company holds an authorisation | O4: Helper: sort key
A5: =IF($O5="","",INT($O5/1000)) -> 1 | B5: =IF($O5="","",INDEX(Scoring!$A$29:$A$361,MATCH($O5,Scoring!$AB$29:$AB$361,0))) -> Intas | C5: =IF($O5="","",IF(INDEX(Scoring!$P$29:$P$361,MATCH($O5,Scoring!$AB$29:$AB$361,0))="","–",INDEX(Scoring!$P$29:$P$361,MATCH($O5,Scoring!$AB$29:$AB$361,0)))) -> 1 | D5: =IF($O5="","",INDEX(Scoring!$Q$29:$Q$361,MATCH($O5,Scoring!$AB$29:$AB$361,0))) -> Priority 1 | E5: =IF($O5="","",INDEX(Scoring!$AJ$29:$AJ$361,MATCH($O5,Scoring!$AB$29:$AB$361,0))) -> High price · high volume | F5: =IF($O5="","",INDEX(Scoring!$B$29:$B$361,MATCH($O5,Scoring!$AB$29:$AB$361,0))) -> Azacitidine | G5: =IF($O5="","",INDEX(Scoring!$AG$29:$AG$361,MATCH($O5,Scoring!$AB$29:$AB$361,0))) -> Azacitidine Accord; Azaccord | H5: =IF($O5="","",INDEX(Scoring!$C$29:$C$361,MATCH($O5,Scoring!$AB$29:$AB$361,0))) -> Oncology: myelodysplastic syndromes, acute myeloid leukaemia | I5: =IF($O5="","",INDEX(Scoring!$I$29:$I$361,MATCH($O5,Scoring!$AB$29:$AB$361,0))) -> Vial | J5: =IF($O5="","",INDEX(Scoring!$Z$29:$Z$361,MATCH($O5,Scoring!$AB$29:$AB$361,0))) -> 25 mg/mL vial; 100 mg powder vial | K5: =IF($O5="","",IF(INDEX(Scoring!$D$29:$D$361,MATCH($O5,Scoring!$AB$29:$AB$361,0))="",INDEX(Scoring!$AF$29:$AF$361,MATCH($O5,Scoring!$AB$29:$AB$361,0)),INDEX(Scoring!$D$29:$D$361,MATCH($O5,Scoring!$AB$29:$AB$361,0)))) -> 256.12 | L5: =IF($O5="","",INDEX(Scoring!$M$29:$M$361,MATCH($O5,Scoring!$AB$29:$AB$361,0))) -> 632 | M5: =IF($O5="","",INDEX(Scoring!$F$29:$F$361,MATCH($O5,Scoring!$AB$29:$AB$361,0))) -> 42181.7 | N5: =IF($O5="","",INDEX(Scoring!$AI$29:$AI$361,MATCH($O5,Scoring!$AB$29:$AB$361,0))) -> UK, Australia | EU/EEA: all 30 countries | O5: =IFERROR(SMALL(Scoring!$AB$29:$AB$361,1),"") -> 1001
A6: =IF($O6="","",INT($O6/1000)) -> 1 | B6: =IF($O6="","",INDEX(Scoring!$A$29:$A$361,MATCH($O6,Scoring!$AB$29:$AB$361,0))) -> Intas | C6: =IF($O6="","",IF(INDEX(Scoring!$P$29:$P$361,MATCH($O6,Scoring!$AB$29:$AB$361,0))="","–",INDEX(Scoring!$P$29:$P$361,MATCH($O6,Scoring!$AB$29:$AB$361,0)))) -> 2 | D6: =IF($O6="","",INDEX(Scoring!$Q$29:$Q$361,MATCH($O6,Scoring!$AB$29:$AB$361,0))) -> Priority 1 | E6: =IF($O6="","",INDEX(Scoring!$AJ$29:$AJ$361,MATCH($O6,Scoring!$AB$29:$AB$361,0))) -> High price · high volume | F6: =IF($O6="","",INDEX(Scoring!$B$29:$B$361,MATCH($O6,Scoring!$AB$29:$AB$361,0))) -> Bortezomib | G6: =IF($O6="","",INDEX(Scoring!$AG$29:$AG$361,MATCH($O6,Scoring!$AB$29:$AB$361,0))) -> Bortezomib; Bortezomib Accord; Bortezomib Intas (+1 more) | H6: =IF($O6="","",INDEX(Scoring!$C$29:$C$361,MATCH($O6,Scoring!$AB$29:$AB$361,0))) -> Oncology: multiple myeloma, mantle cell lymphoma | I6: =IF($O6="","",INDEX(Scoring!$I$29:$I$361,MATCH($O6,Scoring!$AB$29:$AB$361,0))) -> Vial, Prefilled syringe | J6: =IF($O6="","",INDEX(Scoring!$Z$29:$Z$361,MATCH($O6,Scoring!$AB$29:$AB$361,0))) -> 2 mg pre-filled syringe; 3.5 mg/1.4 mL vial; 2.5 mg/1 mL vial; 1 mg powder vial (+2 more) | K6: =IF($O6="","",IF(INDEX(Scoring!$D$29:$D$361,MATCH($O6,Scoring!$AB$29:$AB$361,0))="",INDEX(Scoring!$AF$29:$AF$361,MATCH($O6,Scoring!$AB$29:$AB$361,0)),INDEX(Scoring!$D$29:$D$361,MATCH($O6,Scoring!$AB$29:$AB$361,0)))) -> 569.27 | L6: =IF($O6="","",INDEX(Scoring!$M$29:$M$361,MATCH($O6,Scoring!$AB$29:$AB$361,0))) -> 905 | M6: =IF($O6="","",INDEX(Scoring!$F$29:$F$361,MATCH($O6,Scoring!$AB$29:$AB$361,0))) -> 28093.4 | N6: =IF($O6="","",INDEX(Scoring!$AI$29:$AI$361,MATCH($O6,Scoring!$AB$29:$AB$361,0))) -> UK, Australia, South Africa, UK-NI | EU/EEA: all 30 countries | O6: =IFERROR(SMALL(Scoring!$AB$29:$AB$361,2),"") -> 1002
A7: =IF($O7="","",INT($O7/1000)) -> 1 | B7: =IF($O7="","",INDEX(Scoring!$A$29:$A$361,MATCH($O7,Scoring!$AB$29:$AB$361,0))) -> Intas | C7: =IF($O7="","",IF(INDEX(Scoring!$P$29:$P$361,MATCH($O7,Scoring!$AB$29:$AB$361,0))="","–",INDEX(Scoring!$P$29:$P$361,MATCH($O7,Scoring!$AB$29:$AB$361,0)))) -> 3 | D7: =IF($O7="","",INDEX(Scoring!$Q$29:$Q$361,MATCH($O7,Scoring!$AB$29:$AB$361,0))) -> Priority 1 | E7: =IF($O7="","",INDEX(Scoring!$AJ$29:$AJ$361,MATCH($O7,Scoring!$AB$29:$AB$361,0))) -> High price · high volume | F7: =IF($O7="","",INDEX(Scoring!$B$29:$B$361,MATCH($O7,Scoring!$AB$29:$AB$361,0))) -> Pegfilgrastim | G7: =IF($O7="","",INDEX(Scoring!$AG$29:$AG$361,MATCH($O7,Scoring!$AB$29:$AB$361,0))) -> Pelgraz | H7: =IF($O7="","",INDEX(Scoring!$C$29:$C$361,MATCH($O7,Scoring!$AB$29:$AB$361,0))) -> Oncology support: prevents low white cell counts after chemotherapy | I7: =IF($O7="","",INDEX(Scoring!$I$29:$I$361,MATCH($O7,Scoring!$AB$29:$AB$361,0))) -> Prefilled syringe | J7: =IF($O7="","",INDEX(Scoring!$Z$29:$Z$361,MATCH($O7,Scoring!$AB$29:$AB$361,0))) -> 6 mg/0.6 mL pre-filled syringe | K7: =IF($O7="","",IF(INDEX(Scoring!$D$29:$D$361,MATCH($O7,Scoring!$AB$29:$AB$361,0))="",INDEX(Scoring!$AF$29:$AF$361,MATCH($O7,Scoring!$AB$29:$AB$361,0)),INDEX(Scoring!$D$29:$D$361,MATCH($O7,Scoring!$AB$29:$AB$361,0)))) -> 907.38 | L7: =IF($O7="","",INDEX(Scoring!$M$29:$M$361,MATCH($O7,Scoring!$AB$29:$AB$361,0))) -> 155 | M7: =IF($O7="","",INDEX(Scoring!$F$29:$F$361,MATCH($O7,Scoring!$AB$29:$AB$361,0))) -> 22036.1 | N7: =IF($O7="","",INDEX(Scoring!$AI$29:$AI$361,MATCH($O7,Scoring!$AB$29:$AB$361,0))) -> UK | EU/EEA: all 30 countries | O7: =IFERROR(SMALL(Scoring!$AB$29:$AB$361,3),"") -> 1003
A8: =IF($O8="","",INT($O8/1000)) -> 1 | B8: =IF($O8="","",INDEX(Scoring!$A$29:$A$361,MATCH($O8,Scoring!$AB$29:$AB$361,0))) -> Intas | C8: =IF($O8="","",IF(INDEX(Scoring!$P$29:$P$361,MATCH($O8,Scoring!$AB$29:$AB$361,0))="","–",INDEX(Scoring!$P$29:$P$361,MATCH($O8,Scoring!$AB$29:$AB$361,0)))) -> 4 | D8: =IF($O8="","",INDEX(Scoring!$Q$29:$Q$361,MATCH($O8,Scoring!$AB$29:$AB$361,0))) -> Priority 1 | E8: =IF($O8="","",INDEX(Scoring!$AJ$29:$AJ$361,MATCH($O8,Scoring!$AB$29:$AB$361,0))) -> High price · high volume | F8: =IF($O8="","",INDEX(Scoring!$B$29:$B$361,MATCH($O8,Scoring!$AB$29:$AB$361,0))) -> Methotrexate | G8: =IF($O8="","",INDEX(Scoring!$AG$29:$AG$361,MATCH($O8,Scoring!$AB$29:$AB$361,0))) -> Methotrexate; Methotrexate Subcutaneous; Methotrexate Intas | H8: =IF($O8="","",INDEX(Scoring!$C$29:$C$361,MATCH($O8,Scoring!$AB$29:$AB$361,0))) -> Oncology and immunology: leukaemia, lymphoma, bone cancer, rheumatoid arthritis, psoriasis | I8: =IF($O8="","",INDEX(Scoring!$I$29:$I$361,MATCH($O8,Scoring!$AB$29:$AB$361,0))) -> Vial, Prefilled syringe | J8: =IF($O8="","",INDEX(Scoring!$Z$29:$Z$361,MATCH($O8,Scoring!$AB$29:$AB$361,0))) -> 50 mg/2 mL vial; 500 mg/20 mL vial; 1000 mg/40 mL vial; 10 mg/0.2 mL pre-filled syringe (+2 more) | K8: =IF($O8="","",IF(INDEX(Scoring!$D$29:$D$361,MATCH($O8,Scoring!$AB$29:$AB$361,0))="",INDEX(Scoring!$AF$29:$AF$361,MATCH($O8,Scoring!$AB$29:$AB$361,0)),INDEX(Scoring!$D$29:$D$361,MATCH($O8,Scoring!$AB$29:$AB$361,0)))) -> 50.77 | L8: =IF($O8="","",INDEX(Scoring!$M$29:$M$361,MATCH($O8,Scoring!$AB$29:$AB$361,0))) -> 996 | M8: =IF($O8="","",INDEX(Scoring!$F$29:$F$361,MATCH($O8,Scoring!$AB$29:$AB$361,0))) -> 13045.6 | N8: =IF($O8="","",INDEX(Scoring!$AI$29:$AI$361,MATCH($O8,Scoring!$AB$29:$AB$361,0))) -> UK, Canada, Australia, UK-NI | EU/EEA (25): Germany, France, Netherlands, Belgium + 21 more | O8: =IFERROR(SMALL(Scoring!$AB$29:$AB$361,4),"") -> 1004
A9: =IF($O9="","",INT($O9/1000)) -> 1 | B9: =IF($O9="","",INDEX(Scoring!$A$29:$A$361,MATCH($O9,Scoring!$AB$29:$AB$361,0))) -> Intas | C9: =IF($O9="","",IF(INDEX(Scoring!$P$29:$P$361,MATCH($O9,Scoring!$AB$29:$AB$361,0))="","–",INDEX(Scoring!$P$29:$P$361,MATCH($O9,Scoring!$AB$29:$AB$361,0)))) -> 5 | D9: =IF($O9="","",INDEX(Scoring!$Q$29:$Q$361,MATCH($O9,Scoring!$AB$29:$AB$361,0))) -> Priority 1 | E9: =IF($O9="","",INDEX(Scoring!$AJ$29:$AJ$361,MATCH($O9,Scoring!$AB$29:$AB$361,0))) -> High price · high volume | F9: =IF($O9="","",INDEX(Scoring!$B$29:$B$361,MATCH($O9,Scoring!$AB$29:$AB$361,0))) -> Fulvestrant | G9: =IF($O9="","",INDEX(Scoring!$AG$29:$AG$361,MATCH($O9,Scoring!$AB$29:$AB$361,0))) -> Fulvestrant; Fulvestrant Accord; Fulvestrant Intas (+1 more) | H9: =IF($O9="","",INDEX(Scoring!$C$29:$C$361,MATCH($O9,Scoring!$AB$29:$AB$361,0))) -> Oncology: hormone receptor-positive advanced breast cancer | I9: =IF($O9="","",INDEX(Scoring!$I$29:$I$361,MATCH($O9,Scoring!$AB$29:$AB$361,0))) -> Prefilled syringe | J9: =IF($O9="","",INDEX(Scoring!$Z$29:$Z$361,MATCH($O9,Scoring!$AB$29:$AB$361,0))) -> 250 mg/5 mL pre-filled syringe | K9: =IF($O9="","",IF(INDEX(Scoring!$D$29:$D$361,MATCH($O9,Scoring!$AB$29:$AB$361,0))="",INDEX(Scoring!$AF$29:$AF$361,MATCH($O9,Scoring!$AB$29:$AB$361,0)),INDEX(Scoring!$D$29:$D$361,MATCH($O9,Scoring!$AB$29:$AB$361,0)))) -> 246.46 | L9: =IF($O9="","",INDEX(Scoring!$M$29:$M$361,MATCH($O9,Scoring!$AB$29:$AB$361,0))) -> 146 | M9: =IF($O9="","",INDEX(Scoring!$F$29:$F$361,MATCH($O9,Scoring!$AB$29:$AB$361,0))) -> 11366.1 | N9: =IF($O9="","",INDEX(Scoring!$AI$29:$AI$361,MATCH($O9,Scoring!$AB$29:$AB$361,0))) -> US, UK, Australia, South Africa, UK-NI | EU/EEA (25): Germany, France, Netherlands, Belgium + 21 more | O9: =IFERROR(SMALL(Scoring!$AB$29:$AB$361,5),"") -> 1005
A10: =IF($O10="","",INT($O10/1000)) -> 1 | B10: =IF($O10="","",INDEX(Scoring!$A$29:$A$361,MATCH($O10,Scoring!$AB$29:$AB$361,0))) -> Intas | C10: =IF($O10="","",IF(INDEX(Scoring!$P$29:$P$361,MATCH($O10,Scoring!$AB$29:$AB$361,0))="","–",INDEX(Scoring!$P$29:$P$361,MATCH($O10,Scoring!$AB$29:$AB$361,0)))) -> 6 | D10: =IF($O10="","",INDEX(Scoring!$Q$29:$Q$361,MATCH($O10,Scoring!$AB$29:$AB$361,0))) -> Priority 1 | E10: =IF($O10="","",INDEX(Scoring!$AJ$29:$AJ$361,MATCH($O10,Scoring!$AB$29:$AB$361,0))) -> High price · high volume | F10: =IF($O10="","",INDEX(Scoring!$B$29:$B$361,MATCH($O10,Scoring!$AB$29:$AB$361,0))) -> Phenylephrine | G10: =IF($O10="","",INDEX(Scoring!$AG$29:$AG$361,MATCH($O10,Scoring!$AB$29:$AB$361,0))) -> Phenylephrine Accord; Phenylcord | H10: =IF($O10="","",INDEX(Scoring!$C$29:$C$361,MATCH($O10,Scoring!$AB$29:$AB$361,0))) -> Anaesthesia: low blood pressure during anaesthesia | I10: =IF($O10="","",INDEX(Scoring!$I$29:$I$361,MATCH($O10,Scoring!$AB$29:$AB$361,0))) -> Vial | J10: =IF($O10="","",INDEX(Scoring!$Z$29:$Z$361,MATCH($O10,Scoring!$AB$29:$AB$361,0))) -> 10 mg/1 mL vial; 100 mg/10 mL vial | K10: =IF($O10="","",IF(INDEX(Scoring!$D$29:$D$361,MATCH($O10,Scoring!$AB$29:$AB$361,0))="",INDEX(Scoring!$AF$29:$AF$361,MATCH($O10,Scoring!$AB$29:$AB$361,0)),INDEX(Scoring!$D$29:$D$361,MATCH($O10,Scoring!$AB$29:$AB$361,0)))) -> 32.6 | L10: =IF($O10="","",INDEX(Scoring!$M$29:$M$361,MATCH($O10,Scoring!$AB$29:$AB$361,0))) -> 226 | M10: =IF($O10="","",INDEX(Scoring!$F$29:$F$361,MATCH($O10,Scoring!$AB$29:$AB$361,0))) -> 5695.2 | N10: =IF($O10="","",INDEX(Scoring!$AI$29:$AI$361,MATCH($O10,Scoring!$AB$29:$AB$361,0))) -> Australia, South Africa | O10: =IFERROR(SMALL(Scoring!$AB$29:$AB$361,6),"") -> 1006
A11: =IF($O11="","",INT($O11/1000)) -> 1 | B11: =IF($O11="","",INDEX(Scoring!$A$29:$A$361,MATCH($O11,Scoring!$AB$29:$AB$361,0))) -> Intas | C11: =IF($O11="","",IF(INDEX(Scoring!$P$29:$P$361,MATCH($O11,Scoring!$AB$29:$AB$361,0))="","–",INDEX(Scoring!$P$29:$P$361,MATCH($O11,Scoring!$AB$29:$AB$361,0)))) -> 7 | D11: =IF($O11="","",INDEX(Scoring!$Q$29:$Q$361,MATCH($O11,Scoring!$AB$29:$AB$361,0))) -> Priority 1 | E11: =IF($O11="","",INDEX(Scoring!$AJ$29:$AJ$361,MATCH($O11,Scoring!$AB$29:$AB$361,0))) -> High price · high volume | F11: =IF($O11="","",INDEX(Scoring!$B$29:$B$361,MATCH($O11,Scoring!$AB$29:$AB$361,0))) -> Epinephrine (Adrenaline) | G11: =IF($O11="","",INDEX(Scoring!$AG$29:$AG$361,MATCH($O11,Scoring!$AB$29:$AB$361,0))) -> Adrenaline Accord | H11: =IF($O11="","",INDEX(Scoring!$C$29:$C$361,MATCH($O11,Scoring!$AB$29:$AB$361,0))) -> Critical care: anaphylaxis, cardiac arrest, shock | I11: =IF($O11="","",INDEX(Scoring!$I$29:$I$361,MATCH($O11,Scoring!$AB$29:$AB$361,0))) -> Prefilled syringe | J11: =IF($O11="","",INDEX(Scoring!$Z$29:$Z$361,MATCH($O11,Scoring!$AB$29:$AB$361,0))) -> 1 mg/10 mL pre-filled syringe | K11: =IF($O11="","",IF(INDEX(Scoring!$D$29:$D$361,MATCH($O11,Scoring!$AB$29:$AB$361,0))="",INDEX(Scoring!$AF$29:$AF$361,MATCH($O11,Scoring!$AB$29:$AB$361,0)),INDEX(Scoring!$D$29:$D$361,MATCH($O11,Scoring!$AB$29:$AB$361,0)))) -> 28.67 | L11: =IF($O11="","",INDEX(Scoring!$M$29:$M$361,MATCH($O11,Scoring!$AB$29:$AB$361,0))) -> 799 | M11: =IF($O11="","",INDEX(Scoring!$F$29:$F$361,MATCH($O11,Scoring!$AB$29:$AB$361,0))) -> 4049.5 | N11: =IF($O11="","",INDEX(Scoring!$AI$29:$AI$361,MATCH($O11,Scoring!$AB$29:$AB$361,0))) -> EU/EEA (3): France, Netherlands, Portugal | O11: =IFERROR(SMALL(Scoring!$AB$29:$AB$361,7),"") -> 1007
A12: =IF($O12="","",INT($O12/1000)) -> 1 | B12: =IF($O12="","",INDEX(Scoring!$A$29:$A$361,MATCH($O12,Scoring!$AB$29:$AB$361,0))) -> Intas | C12: =IF($O12="","",IF(INDEX(Scoring!$P$29:$P$361,MATCH($O12,Scoring!$AB$29:$AB$361,0))="","–",INDEX(Scoring!$P$29:$P$361,MATCH($O12,Scoring!$AB$29:$AB$361,0)))) -> 8 | D12: =IF($O12="","",INDEX(Scoring!$Q$29:$Q$361,MATCH($O12,Scoring!$AB$29:$AB$361,0))) -> Priority 1 | E12: =IF($O12="","",INDEX(Scoring!$AJ$29:$AJ$361,MATCH($O12,Scoring!$AB$29:$AB$361,0))) -> High price · high volume | F12: =IF($O12="","",INDEX(Scoring!$B$29:$B$361,MATCH($O12,Scoring!$AB$29:$AB$361,0))) -> Bleomycin | G12: =IF($O12="","",INDEX(Scoring!$AG$29:$AG$361,MATCH($O12,Scoring!$AB$29:$AB$361,0))) -> Bleomycin; Bleomicina Accord; Bleomycin Accord | H12: =IF($O12="","",INDEX(Scoring!$C$29:$C$361,MATCH($O12,Scoring!$AB$29:$AB$361,0))) -> Oncology: Hodgkin lymphoma, testicular and squamous cell cancers | I12: =IF($O12="","",INDEX(Scoring!$I$29:$I$361,MATCH($O12,Scoring!$AB$29:$AB$361,0))) -> Vial | J12: =IF($O12="","",INDEX(Scoring!$Z$29:$Z$361,MATCH($O12,Scoring!$AB$29:$AB$361,0))) -> 15000 IU powder vial | K12: =IF($O12="","",IF(INDEX(Scoring!$D$29:$D$361,MATCH($O12,Scoring!$AB$29:$AB$361,0))="",INDEX(Scoring!$AF$29:$AF$361,MATCH($O12,Scoring!$AB$29:$AB$361,0)),INDEX(Scoring!$D$29:$D$361,MATCH($O12,Scoring!$AB$29:$AB$361,0)))) -> 50.27 | L12: =IF($O12="","",INDEX(Scoring!$M$29:$M$361,MATCH($O12,Scoring!$AB$29:$AB$361,0))) -> 441 | M12: =IF($O12="","",INDEX(Scoring!$F$29:$F$361,MATCH($O12,Scoring!$AB$29:$AB$361,0))) -> 3973.7 | N12: =IF($O12="","",INDEX(Scoring!$AI$29:$AI$361,MATCH($O12,Scoring!$AB$29:$AB$361,0))) -> UK, Australia, UK-NI | EU/EEA (14): Germany, France, Netherlands, Belgium + 10 more | O12: =IFERROR(SMALL(Scoring!$AB$29:$AB$361,8),"") -> 1008
A13: =IF($O13="","",INT($O13/1000)) -> 1 | B13: =IF($O13="","",INDEX(Scoring!$A$29:$A$361,MATCH($O13,Scoring!$AB$29:$AB$361,0))) -> Intas | C13: =IF($O13="","",IF(INDEX(Scoring!$P$29:$P$361,MATCH($O13,Scoring!$AB$29:$AB$361,0))="","–",INDEX(Scoring!$P$29:$P$361,MATCH($O13,Scoring!$AB$29:$AB$361,0)))) -> 9 | D13: =IF($O13="","",INDEX(Scoring!$Q$29:$Q$361,MATCH($O13,Scoring!$AB$29:$AB$361,0))) -> Priority 1 | E13: =IF($O13="","",INDEX(Scoring!$AJ$29:$AJ$361,MATCH($O13,Scoring!$AB$29:$AB$361,0))) -> High price · high volume | F13: =IF($O13="","",INDEX(Scoring!$B$29:$B$361,MATCH($O13,Scoring!$AB$29:$AB$361,0))) -> Denosumab | G13: =IF($O13="","",INDEX(Scoring!$AG$29:$AG$361,MATCH($O13,Scoring!$AB$29:$AB$361,0))) -> Jubereq; Dostiva | H13: =IF($O13="","",INDEX(Scoring!$C$29:$C$361,MATCH($O13,Scoring!$AB$29:$AB$361,0))) -> Bone health and oncology: bone metastases, osteoporosis | I13: =IF($O13="","",INDEX(Scoring!$I$29:$I$361,MATCH($O13,Scoring!$AB$29:$AB$361,0))) -> Vial | J13: =IF($O13="","",INDEX(Scoring!$Z$29:$Z$361,MATCH($O13,Scoring!$AB$29:$AB$361,0))) -> 120 mg/1.7 mL vial | K13: =IF($O13="","",IF(INDEX(Scoring!$D$29:$D$361,MATCH($O13,Scoring!$AB$29:$AB$361,0))="",INDEX(Scoring!$AF$29:$AF$361,MATCH($O13,Scoring!$AB$29:$AB$361,0)),INDEX(Scoring!$D$29:$D$361,MATCH($O13,Scoring!$AB$29:$AB$361,0)))) -> 162.77 | L13: =IF($O13="","",INDEX(Scoring!$M$29:$M$361,MATCH($O13,Scoring!$AB$29:$AB$361,0))) -> 314 | M13: =IF($O13="","",INDEX(Scoring!$F$29:$F$361,MATCH($O13,Scoring!$AB$29:$AB$361,0))) -> 3429.5 | N13: =IF($O13="","",INDEX(Scoring!$AI$29:$AI$361,MATCH($O13,Scoring!$AB$29:$AB$361,0))) -> UK, Australia | EU/EEA: all 30 countries | O13: =IFERROR(SMALL(Scoring!$AB$29:$AB$361,9),"") -> 1009
A14: =IF($O14="","",INT($O14/1000)) -> 1 | B14: =IF($O14="","",INDEX(Scoring!$A$29:$A$361,MATCH($O14,Scoring!$AB$29:$AB$361,0))) -> Intas | C14: =IF($O14="","",IF(INDEX(Scoring!$P$29:$P$361,MATCH($O14,Scoring!$AB$29:$AB$361,0))="","–",INDEX(Scoring!$P$29:$P$361,MATCH($O14,Scoring!$AB$29:$AB$361,0)))) -> 10 | D14: =IF($O14="","",INDEX(Scoring!$Q$29:$Q$361,MATCH($O14,Scoring!$AB$29:$AB$361,0))) -> Priority 2 | E14: =IF($O14="","",INDEX(Scoring!$AJ$29:$AJ$361,MATCH($O14,Scoring!$AB$29:$AB$361,0))) -> Lower price · high volume | F14: =IF($O14="","",INDEX(Scoring!$B$29:$B$361,MATCH($O14,Scoring!$AB$29:$AB$361,0))) -> Ceftriaxone | G14: =IF($O14="","",INDEX(Scoring!$AG$29:$AG$361,MATCH($O14,Scoring!$AB$29:$AB$361,0))) -> Ceftriaxone Accord | H14: =IF($O14="","",INDEX(Scoring!$C$29:$C$361,MATCH($O14,Scoring!$AB$29:$AB$361,0))) -> Anti-infective: pneumonia, meningitis, sepsis, gonorrhoea, typhoid | I14: =IF($O14="","",INDEX(Scoring!$I$29:$I$361,MATCH($O14,Scoring!$AB$29:$AB$361,0))) -> Not stated | J14: =IF($O14="","",INDEX(Scoring!$Z$29:$Z$361,MATCH($O14,Scoring!$AB$29:$AB$361,0))) -> 1 g (container not stated) | K14: =IF($O14="","",IF(INDEX(Scoring!$D$29:$D$361,MATCH($O14,Scoring!$AB$29:$AB$361,0))="",INDEX(Scoring!$AF$29:$AF$361,MATCH($O14,Scoring!$AB$29:$AB$361,0)),INDEX(Scoring!$D$29:$D$361,MATCH($O14,Scoring!$AB$29:$AB$361,0)))) -> 5.6 | L14: =IF($O14="","",INDEX(Scoring!$M$29:$M$361,MATCH($O14,Scoring!$AB$29:$AB$361,0))) -> 3110 | M14: =IF($O14="","",INDEX(Scoring!$F$29:$F$361,MATCH($O14,Scoring!$AB$29:$AB$361,0))) -> 93119.2 | N14: =IF($O14="","",INDEX(Scoring!$AI$29:$AI$361,MATCH($O14,Scoring!$AB$29:$AB$361,0))) -> EU/EEA (1): Italy | O14: =IFERROR(SMALL(Scoring!$AB$29:$AB$361,10),"") -> 1010
A15: =IF($O15="","",INT($O15/1000)) -> 1 | B15: =IF($O15="","",INDEX(Scoring!$A$29:$A$361,MATCH($O15,Scoring!$AB$29:$AB$361,0))) -> Intas | C15: =IF($O15="","",IF(INDEX(Scoring!$P$29:$P$361,MATCH($O15,Scoring!$AB$29:$AB$361,0))="","–",INDEX(Scoring!$P$29:$P$361,MATCH($O15,Scoring!$AB$29:$AB$361,0)))) -> 11 | D15: =IF($O15="","",INDEX(Scoring!$Q$29:$Q$361,MATCH($O15,Scoring!$AB$29:$AB$361,0))) -> Priority 2 | E15: =IF($O15="","",INDEX(Scoring!$AJ$29:$AJ$361,MATCH($O15,Scoring!$AB$29:$AB$361,0))) -> Lower price · high volume | F15: =IF($O15="","",INDEX(Scoring!$B$29:$B$361,MATCH($O15,Scoring!$AB$29:$AB$361,0))) -> Ondansetron | G15: =IF($O15="","",INDEX(Scoring!$AG$29:$AG$361,MATCH($O15,Scoring!$AB$29:$AB$361,0))) -> Ondansetron Hydrochloride; Ondansetron; Ondansetron Accord | H15: =IF($O15="","",INDEX(Scoring!$C$29:$C$361,MATCH($O15,Scoring!$AB$29:$AB$361,0))) -> Oncology support: nausea and vomiting from chemotherapy and surgery | I15: =IF($O15="","",INDEX(Scoring!$I$29:$I$361,MATCH($O15,Scoring!$AB$29:$AB$361,0))) -> Vial, Ampoule, Prefilled syringe | J15: =IF($O15="","",INDEX(Scoring!$Z$29:$Z$361,MATCH($O15,Scoring!$AB$29:$AB$361,0))) -> 40 mg/20 mL vial; 8 mg/4 mL pre-filled syringe; 4 mg/2 mL ampoule; 4 mg/2 mL pre-filled syringe | K15: =IF($O15="","",IF(INDEX(Scoring!$D$29:$D$361,MATCH($O15,Scoring!$AB$29:$AB$361,0))="",INDEX(Scoring!$AF$29:$AF$361,MATCH($O15,Scoring!$AB$29:$AB$361,0)),INDEX(Scoring!$D$29:$D$361,MATCH($O15,Scoring!$AB$29:$AB$361,0)))) -> 24.05 | L15: =IF($O15="","",INDEX(Scoring!$M$29:$M$361,MATCH($O15,Scoring!$AB$29:$AB$361,0))) -> 963 | M15: =IF($O15="","",INDEX(Scoring!$F$29:$F$361,MATCH($O15,Scoring!$AB$29:$AB$361,0))) -> 17590.5 | N15: =IF($O15="","",INDEX(Scoring!$AI$29:$AI$361,MATCH($O15,Scoring!$AB$29:$AB$361,0))) -> US, UK, Australia, UK-NI | EU/EEA (23): Germany, France, Netherlands, Belgium + 19 more | O15: =IFERROR(SMALL(Scoring!$AB$29:$AB$361,11),"") -> 1011
A16: =IF($O16="","",INT($O16/1000)) -> 1 | B16: =IF($O16="","",INDEX(Scoring!$A$29:$A$361,MATCH($O16,Scoring!$AB$29:$AB$361,0))) -> Intas | C16: =IF($O16="","",IF(INDEX(Scoring!$P$29:$P$361,MATCH($O16,Scoring!$AB$29:$AB$361,0))="","–",INDEX(Scoring!$P$29:$P$361,MATCH($O16,Scoring!$AB$29:$AB$361,0)))) -> 12 | D16: =IF($O16="","",INDEX(Scoring!$Q$29:$Q$361,MATCH($O16,Scoring!$AB$29:$AB$361,0))) -> Priority 2 | E16: =IF($O16="","",INDEX(Scoring!$AJ$29:$AJ$361,MATCH($O16,Scoring!$AB$29:$AB$361,0))) -> High price · lower volume | F16: =IF($O16="","",INDEX(Scoring!$B$29:$B$361,MATCH($O16,Scoring!$AB$29:$AB$361,0))) -> Plerixafor | G16: =IF($O16="","",INDEX(Scoring!$AG$29:$AG$361,MATCH($O16,Scoring!$AB$29:$AB$361,0))) -> Plerixafor; Plerixafor Accord | H16: =IF($O16="","",INDEX(Scoring!$C$29:$C$361,MATCH($O16,Scoring!$AB$29:$AB$361,0))) -> Oncology support: stem cell mobilisation in myeloma and lymphoma | I16: =IF($O16="","",INDEX(Scoring!$I$29:$I$361,MATCH($O16,Scoring!$AB$29:$AB$361,0))) -> Vial | J16: =IF($O16="","",INDEX(Scoring!$Z$29:$Z$361,MATCH($O16,Scoring!$AB$29:$AB$361,0))) -> 24 mg/1.2 mL vial | K16: =IF($O16="","",IF(INDEX(Scoring!$D$29:$D$361,MATCH($O16,Scoring!$AB$29:$AB$361,0))="",INDEX(Scoring!$AF$29:$AF$361,MATCH($O16,Scoring!$AB$29:$AB$361,0)),INDEX(Scoring!$D$29:$D$361,MATCH($O16,Scoring!$AB$29:$AB$361,0)))) -> 4779 | L16: =IF($O16="","",INDEX(Scoring!$M$29:$M$361,MATCH($O16,Scoring!$AB$29:$AB$361,0))) -> 47 | M16: =IF($O16="","",INDEX(Scoring!$F$29:$F$361,MATCH($O16,Scoring!$AB$29:$AB$361,0))) -> 7904.7 | N16: =IF($O16="","",INDEX(Scoring!$AI$29:$AI$361,MATCH($O16,Scoring!$AB$29:$AB$361,0))) -> UK, Australia | EU/EEA: all 30 countries | O16: =IFERROR(SMALL(Scoring!$AB$29:$AB$361,12),"") -> 1012
A17: =IF($O17="","",INT($O17/1000)) -> 1 | B17: =IF($O17="","",INDEX(Scoring!$A$29:$A$361,MATCH($O17,Scoring!$AB$29:$AB$361,0))) -> Intas | C17: =IF($O17="","",IF(INDEX(Scoring!$P$29:$P$361,MATCH($O17,Scoring!$AB$29:$AB$361,0))="","–",INDEX(Scoring!$P$29:$P$361,MATCH($O17,Scoring!$AB$29:$AB$361,0)))) -> 13 | D17: =IF($O17="","",INDEX(Scoring!$Q$29:$Q$361,MATCH($O17,Scoring!$AB$29:$AB$361,0))) -> Priority 2 | E17: =IF($O17="","",INDEX(Scoring!$AJ$29:$AJ$361,MATCH($O17,Scoring!$AB$29:$AB$361,0))) -> Lower price · high volume | F17: =IF($O17="","",INDEX(Scoring!$B$29:$B$361,MATCH($O17,Scoring!$AB$29:$AB$361,0))) -> Cytarabine | G17: =IF($O17="","",INDEX(Scoring!$AG$29:$AG$361,MATCH($O17,Scoring!$AB$29:$AB$361,0))) -> Cytarabine; Cytarabine Accord; Cytarabine ACC | H17: =IF($O17="","",INDEX(Scoring!$C$29:$C$361,MATCH($O17,Scoring!$AB$29:$AB$361,0))) -> Oncology: acute myeloid and acute lymphoblastic leukaemia | I17: =IF($O17="","",INDEX(Scoring!$I$29:$I$361,MATCH($O17,Scoring!$AB$29:$AB$361,0))) -> Vial | J17: =IF($O17="","",INDEX(Scoring!$Z$29:$Z$361,MATCH($O17,Scoring!$AB$29:$AB$361,0))) -> 100 mg/5 mL vial; 4000 mg/40 mL vial; 2000 mg/20 mL vial; 500 mg/5 mL vial (+3 more) | K17: =IF($O17="","",IF(INDEX(Scoring!$D$29:$D$361,MATCH($O17,Scoring!$AB$29:$AB$361,0))="",INDEX(Scoring!$AF$29:$AF$361,MATCH($O17,Scoring!$AB$29:$AB$361,0)),INDEX(Scoring!$D$29:$D$361,MATCH($O17,Scoring!$AB$29:$AB$361,0)))) -> 6.7 | L17: =IF($O17="","",INDEX(Scoring!$M$29:$M$361,MATCH($O17,Scoring!$AB$29:$AB$361,0))) -> 799 | M17: =IF($O17="","",INDEX(Scoring!$F$29:$F$361,MATCH($O17,Scoring!$AB$29:$AB$361,0))) -> 7739 | N17: =IF($O17="","",INDEX(Scoring!$AI$29:$AI$361,MATCH($O17,Scoring!$AB$29:$AB$361,0))) -> UK, Australia, UK-NI | EU/EEA (25): Germany, France, Netherlands, Belgium + 21 more | O17: =IFERROR(SMALL(Scoring!$AB$29:$AB$361,13),"") -> 1013
A18: =IF($O18="","",INT($O18/1000)) -> 1 | B18: =IF($O18="","",INDEX(Scoring!$A$29:$A$361,MATCH($O18,Scoring!$AB$29:$AB$361,0))) -> Intas | C18: =IF($O18="","",IF(INDEX(Scoring!$P$29:$P$361,MATCH($O18,Scoring!$AB$29:$AB$361,0))="","–",INDEX(Scoring!$P$29:$P$361,MATCH($O18,Scoring!$AB$29:$AB$361,0)))) -> 14 | D18: =IF($O18="","",INDEX(Scoring!$Q$29:$Q$361,MATCH($O18,Scoring!$AB$29:$AB$361,0))) -> Priority 2 | E18: =IF($O18="","",INDEX(Scoring!$AJ$29:$AJ$361,MATCH($O18,Scoring!$AB$29:$AB$361,0))) -> Lower price · high volume | F18: =IF($O18="","",INDEX(Scoring!$B$29:$B$361,MATCH($O18,Scoring!$AB$29:$AB$361,0))) -> Atropine | G18: =IF($O18="","",INDEX(Scoring!$AG$29:$AG$361,MATCH($O18,Scoring!$AB$29:$AB$361,0))) -> Atropine Sulfate; Atropin Accord; Atropina Accord | H18: =IF($O18="","",INDEX(Scoring!$C$29:$C$361,MATCH($O18,Scoring!$AB$29:$AB$361,0))) -> Critical care: slow heart rate, pre-anaesthesia, organophosphate poisoning | I18: =IF($O18="","",INDEX(Scoring!$I$29:$I$361,MATCH($O18,Scoring!$AB$29:$AB$361,0))) -> Vial, Prefilled syringe | J18: =IF($O18="","",INDEX(Scoring!$Z$29:$Z$361,MATCH($O18,Scoring!$AB$29:$AB$361,0))) -> 0.25 mg/5 mL pre-filled syringe; 0.4 mg/1 mL vial; 0.5 mg/5 mL pre-filled syringe; 1 mg/10 mL pre-filled syringe (+3 more) | K18: =IF($O18="","",IF(INDEX(Scoring!$D$29:$D$361,MATCH($O18,Scoring!$AB$29:$AB$361,0))="",INDEX(Scoring!$AF$29:$AF$361,MATCH($O18,Scoring!$AB$29:$AB$361,0)),INDEX(Scoring!$D$29:$D$361,MATCH($O18,Scoring!$AB$29:$AB$361,0)))) -> 16.48 | L18: =IF($O18="","",INDEX(Scoring!$M$29:$M$361,MATCH($O18,Scoring!$AB$29:$AB$361,0))) -> 715 | M18: =IF($O18="","",INDEX(Scoring!$F$29:$F$361,MATCH($O18,Scoring!$AB$29:$AB$361,0))) -> 6805 | N18: =IF($O18="","",INDEX(Scoring!$AI$29:$AI$361,MATCH($O18,Scoring!$AB$29:$AB$361,0))) -> US, UK, UK-NI | EU/EEA (13): Germany, France, Netherlands, Austria + 9 more | O18: =IFERROR(SMALL(Scoring!$AB$29:$AB$361,14),"") -> 1014
A19: =IF($O19="","",INT($O19/1000)) -> 1 | B19: =IF($O19="","",INDEX(Scoring!$A$29:$A$361,MATCH($O19,Scoring!$AB$29:$AB$361,0))) -> Intas | C19: =IF($O19="","",IF(INDEX(Scoring!$P$29:$P$361,MATCH($O19,Scoring!$AB$29:$AB$361,0))="","–",INDEX(Scoring!$P$29:$P$361,MATCH($O19,Scoring!$AB$29:$AB$361,0)))) -> 15 | D19: =IF($O19="","",INDEX(Scoring!$Q$29:$Q$361,MATCH($O19,Scoring!$AB$29:$AB$361,0))) -> Priority 2 | E19: =IF($O19="","",INDEX(Scoring!$AJ$29:$AJ$361,MATCH($O19,Scoring!$AB$29:$AB$361,0))) -> High price · lower volume | F19: =IF($O19="","",INDEX(Scoring!$B$29:$B$361,MATCH($O19,Scoring!$AB$29:$AB$361,0))) -> Teicoplanin | G19: =IF($O19="","",INDEX(Scoring!$AG$29:$AG$361,MATCH($O19,Scoring!$AB$29:$AB$361,0))) -> Teicoplanina Accord | H19: =IF($O19="","",INDEX(Scoring!$C$29:$C$361,MATCH($O19,Scoring!$AB$29:$AB$361,0))) -> Anti-infective: MRSA and serious Gram-positive infections | I19: =IF($O19="","",INDEX(Scoring!$I$29:$I$361,MATCH($O19,Scoring!$AB$29:$AB$361,0))) -> Vial | J19: =IF($O19="","",INDEX(Scoring!$Z$29:$Z$361,MATCH($O19,Scoring!$AB$29:$AB$361,0))) -> 200 mg powder vial | K19: =IF($O19="","",IF(INDEX(Scoring!$D$29:$D$361,MATCH($O19,Scoring!$AB$29:$AB$361,0))="",INDEX(Scoring!$AF$29:$AF$361,MATCH($O19,Scoring!$AB$29:$AB$361,0)),INDEX(Scoring!$D$29:$D$361,MATCH($O19,Scoring!$AB$29:$AB$361,0)))) -> 35.27 | L19: =IF($O19="","",INDEX(Scoring!$M$29:$M$361,MATCH($O19,Scoring!$AB$29:$AB$361,0))) -> 99 | M19: =IF($O19="","",INDEX(Scoring!$F$29:$F$361,MATCH($O19,Scoring!$AB$29:$AB$361,0))) -> 6632.6 | N19: =IF($O19="","",INDEX(Scoring!$AI$29:$AI$361,MATCH($O19,Scoring!$AB$29:$AB$361,0))) -> EU/EEA (3): Austria, Portugal, Spain | O19: =IFERROR(SMALL(Scoring!$AB$29:$AB$361,15),"") -> 1015
A20: =IF($O20="","",INT($O20/1000)) -> 1 | B20: =IF($O20="","",INDEX(Scoring!$A$29:$A$361,MATCH($O20,Scoring!$AB$29:$AB$361,0))) -> Intas | C20: =IF($O20="","",IF(INDEX(Scoring!$P$29:$P$361,MATCH($O20,Scoring!$AB$29:$AB$361,0))="","–",INDEX(Scoring!$P$29:$P$361,MATCH($O20,Scoring!$AB$29:$AB$361,0)))) -> 16 | D20: =IF($O20="","",INDEX(Scoring!$Q$29:$Q$361,MATCH($O20,Scoring!$AB$29:$AB$361,0))) -> Priority 2 | E20: =IF($O20="","",INDEX(Scoring!$AJ$29:$AJ$361,MATCH($O20,Scoring!$AB$29:$AB$361,0))) -> Lower price · high volume | F20: =IF($O20="","",INDEX(Scoring!$B$29:$B$361,MATCH($O20,Scoring!$AB$29:$AB$361,0))) -> Cefepime | G20: =IF($O20="","",INDEX(Scoring!$AG$29:$AG$361,MATCH($O20,Scoring!$AB$29:$AB$361,0))) -> Cefepim Accord; Cefepime Accord | H20: =IF($O20="","",INDEX(Scoring!$C$29:$C$361,MATCH($O20,Scoring!$AB$29:$AB$361,0))) -> Anti-infective: hospital Gram-negative infections, febrile neutropenia | I20: =IF($O20="","",INDEX(Scoring!$I$29:$I$361,MATCH($O20,Scoring!$AB$29:$AB$361,0))) -> Vial | J20: =IF($O20="","",INDEX(Scoring!$Z$29:$Z$361,MATCH($O20,Scoring!$AB$29:$AB$361,0))) -> 1 g powder vial | K20: =IF($O20="","",IF(INDEX(Scoring!$D$29:$D$361,MATCH($O20,Scoring!$AB$29:$AB$361,0))="",INDEX(Scoring!$AF$29:$AF$361,MATCH($O20,Scoring!$AB$29:$AB$361,0)),INDEX(Scoring!$D$29:$D$361,MATCH($O20,Scoring!$AB$29:$AB$361,0)))) -> 9.65 | L20: =IF($O20="","",INDEX(Scoring!$M$29:$M$361,MATCH($O20,Scoring!$AB$29:$AB$361,0))) -> 288 | M20: =IF($O20="","",INDEX(Scoring!$F$29:$F$361,MATCH($O20,Scoring!$AB$29:$AB$361,0))) -> 6294.9 | N20: =IF($O20="","",INDEX(Scoring!$AI$29:$AI$361,MATCH($O20,Scoring!$AB$29:$AB$361,0))) -> EU/EEA (4): Germany, France, Croatia, Portugal | O20: =IFERROR(SMALL(Scoring!$AB$29:$AB$361,16),"") -> 1016
A21: =IF($O21="","",INT($O21/1000)) -> 1 | B21: =IF($O21="","",INDEX(Scoring!$A$29:$A$361,MATCH($O21,Scoring!$AB$29:$AB$361,0))) -> Intas | C21: =IF($O21="","",IF(INDEX(Scoring!$P$29:$P$361,MATCH($O21,Scoring!$AB$29:$AB$361,0))="","–",INDEX(Scoring!$P$29:$P$361,MATCH($O21,Scoring!$AB$29:$AB$361,0)))) -> 17 | D21: =IF($O21="","",INDEX(Scoring!$Q$29:$Q$361,MATCH($O21,Scoring!$AB$29:$AB$361,0))) -> Priority 2 | E21: =IF($O21="","",INDEX(Scoring!$AJ$29:$AJ$361,MATCH($O21,Scoring!$AB$29:$AB$361,0))) -> Lower price · high volume | F21: =IF($O21="","",INDEX(Scoring!$B$29:$B$361,MATCH($O21,Scoring!$AB$29:$AB$361,0))) -> Midazolam | G21: =IF($O21="","",INDEX(Scoring!$AG$29:$AG$361,MATCH($O21,Scoring!$AB$29:$AB$361,0))) -> Midazolam Accord; Intas Midazolam | H21: =IF($O21="","",INDEX(Scoring!$C$29:$C$361,MATCH($O21,Scoring!$AB$29:$AB$361,0))) -> Anaesthesia: sedation for procedures and ICU, anaesthesia induction, seizures | I21: =IF($O21="","",INDEX(Scoring!$I$29:$I$361,MATCH($O21,Scoring!$AB$29:$AB$361,0))) -> Ampoule, Prefilled syringe | J21: =IF($O21="","",INDEX(Scoring!$Z$29:$Z$361,MATCH($O21,Scoring!$AB$29:$AB$361,0))) -> 50 mg/10 mL pre-filled syringe; 5 mg/5 mL pre-filled syringe; 15 mg/3 mL ampoule | K21: =IF($O21="","",IF(INDEX(Scoring!$D$29:$D$361,MATCH($O21,Scoring!$AB$29:$AB$361,0))="",INDEX(Scoring!$AF$29:$AF$361,MATCH($O21,Scoring!$AB$29:$AB$361,0)),INDEX(Scoring!$D$29:$D$361,MATCH($O21,Scoring!$AB$29:$AB$361,0)))) -> 11.33 | L21: =IF($O21="","",INDEX(Scoring!$M$29:$M$361,MATCH($O21,Scoring!$AB$29:$AB$361,0))) -> 177 | M21: =IF($O21="","",INDEX(Scoring!$F$29:$F$361,MATCH($O21,Scoring!$AB$29:$AB$361,0))) -> 4675.1 | N21: =IF($O21="","",INDEX(Scoring!$AI$29:$AI$361,MATCH($O21,Scoring!$AB$29:$AB$361,0))) -> Australia, UK-NI | EU/EEA (22): Germany, France, Netherlands, Belgium + 18 more | O21: =IFERROR(SMALL(Scoring!$AB$29:$AB$361,17),"") -> 1017
A22: =IF($O22="","",INT($O22/1000)) -> 1 | B22: =IF($O22="","",INDEX(Scoring!$A$29:$A$361,MATCH($O22,Scoring!$AB$29:$AB$361,0))) -> Intas | C22: =IF($O22="","",IF(INDEX(Scoring!$P$29:$P$361,MATCH($O22,Scoring!$AB$29:$AB$361,0))="","–",INDEX(Scoring!$P$29:$P$361,MATCH($O22,Scoring!$AB$29:$AB$361,0)))) -> 18 | D22: =IF($O22="","",INDEX(Scoring!$Q$29:$Q$361,MATCH($O22,Scoring!$AB$29:$AB$361,0))) -> Priority 2 | E22: =IF($O22="","",INDEX(Scoring!$AJ$29:$AJ$361,MATCH($O22,Scoring!$AB$29:$AB$361,0))) -> Lower price · high volume | F22: =IF($O22="","",INDEX(Scoring!$B$29:$B$361,MATCH($O22,Scoring!$AB$29:$AB$361,0))) -> Succinylcholine (Suxamethonium) | G22: =IF($O22="","",INDEX(Scoring!$AG$29:$AG$361,MATCH($O22,Scoring!$AB$29:$AB$361,0))) -> Suxamethonium Intas | H22: =IF($O22="","",INDEX(Scoring!$C$29:$C$361,MATCH($O22,Scoring!$AB$29:$AB$361,0))) -> Anaesthesia: muscle relaxant for rapid intubation | I22: =IF($O22="","",INDEX(Scoring!$I$29:$I$361,MATCH($O22,Scoring!$AB$29:$AB$361,0))) -> Prefilled syringe | J22: =IF($O22="","",INDEX(Scoring!$Z$29:$Z$361,MATCH($O22,Scoring!$AB$29:$AB$361,0))) -> 100 mg/2 mL pre-filled syringe | K22: =IF($O22="","",IF(INDEX(Scoring!$D$29:$D$361,MATCH($O22,Scoring!$AB$29:$AB$361,0))="",INDEX(Scoring!$AF$29:$AF$361,MATCH($O22,Scoring!$AB$29:$AB$361,0)),INDEX(Scoring!$D$29:$D$361,MATCH($O22,Scoring!$AB$29:$AB$361,0)))) -> 5.12 | L22: =IF($O22="","",INDEX(Scoring!$M$29:$M$361,MATCH($O22,Scoring!$AB$29:$AB$361,0))) -> 286 | M22: =IF($O22="","",INDEX(Scoring!$F$29:$F$361,MATCH($O22,Scoring!$AB$29:$AB$361,0))) -> 3067.4 | N22: =IF($O22="","",INDEX(Scoring!$AI$29:$AI$361,MATCH($O22,Scoring!$AB$29:$AB$361,0))) -> Australia | O22: =IFERROR(SMALL(Scoring!$AB$29:$AB$361,18),"") -> 1018
A23: =IF($O23="","",INT($O23/1000)) -> 1 | B23: =IF($O23="","",INDEX(Scoring!$A$29:$A$361,MATCH($O23,Scoring!$AB$29:$AB$361,0))) -> Intas | C23: =IF($O23="","",IF(INDEX(Scoring!$P$29:$P$361,MATCH($O23,Scoring!$AB$29:$AB$361,0))="","–",INDEX(Scoring!$P$29:$P$361,MATCH($O23,Scoring!$AB$29:$AB$361,0)))) -> 19 | D23: =IF($O23="","",INDEX(Scoring!$Q$29:$Q$361,MATCH($O23,Scoring!$AB$29:$AB$361,0))) -> Priority 2 | E23: =IF($O23="","",INDEX(Scoring!$AJ$29:$AJ$361,MATCH($O23,Scoring!$AB$29:$AB$361,0))) -> High price · lower volume | F23: =IF($O23="","",INDEX(Scoring!$B$29:$B$361,MATCH($O23,Scoring!$AB$29:$AB$361,0))) -> Leuprorelin | G23: =IF($O23="","",INDEX(Scoring!$AG$29:$AG$361,MATCH($O23,Scoring!$AB$29:$AB$361,0))) -> Camcevi | H23: =IF($O23="","",INDEX(Scoring!$C$29:$C$361,MATCH($O23,Scoring!$AB$29:$AB$361,0))) -> Oncology: hormone therapy for advanced prostate cancer | I23: =IF($O23="","",INDEX(Scoring!$I$29:$I$361,MATCH($O23,Scoring!$AB$29:$AB$361,0))) -> Prefilled syringe | J23: =IF($O23="","",INDEX(Scoring!$Z$29:$Z$361,MATCH($O23,Scoring!$AB$29:$AB$361,0))) -> 21 mg pre-filled syringe; 21 mg/0.25 mL pre-filled syringe | K23: =IF($O23="","",IF(INDEX(Scoring!$D$29:$D$361,MATCH($O23,Scoring!$AB$29:$AB$361,0))="",INDEX(Scoring!$AF$29:$AF$361,MATCH($O23,Scoring!$AB$29:$AB$361,0)),INDEX(Scoring!$D$29:$D$361,MATCH($O23,Scoring!$AB$29:$AB$361,0)))) -> 433.94 | L23: =IF($O23="","",INDEX(Scoring!$M$29:$M$361,MATCH($O23,Scoring!$AB$29:$AB$361,0))) -> 111 | M23: =IF($O23="","",INDEX(Scoring!$F$29:$F$361,MATCH($O23,Scoring!$AB$29:$AB$361,0))) -> 2489.4 | N23: =IF($O23="","",INDEX(Scoring!$AI$29:$AI$361,MATCH($O23,Scoring!$AB$29:$AB$361,0))) -> UK | EU/EEA: all 30 countries | O23: =IFERROR(SMALL(Scoring!$AB$29:$AB$361,19),"") -> 1019
A24: =IF($O24="","",INT($O24/1000)) -> 1 | B24: =IF($O24="","",INDEX(Scoring!$A$29:$A$361,MATCH($O24,Scoring!$AB$29:$AB$361,0))) -> Intas | C24: =IF($O24="","",IF(INDEX(Scoring!$P$29:$P$361,MATCH($O24,Scoring!$AB$29:$AB$361,0))="","–",INDEX(Scoring!$P$29:$P$361,MATCH($O24,Scoring!$AB$29:$AB$361,0)))) -> 20 | D24: =IF($O24="","",INDEX(Scoring!$Q$29:$Q$361,MATCH($O24,Scoring!$AB$29:$AB$361,0))) -> Priority 2 | E24: =IF($O24="","",INDEX(Scoring!$AJ$29:$AJ$361,MATCH($O24,Scoring!$AB$29:$AB$361,0))) -> High price · lower volume | F24: =IF($O24="","",INDEX(Scoring!$B$29:$B$361,MATCH($O24,Scoring!$AB$29:$AB$361,0))) -> Ustekinumab | G24: =IF($O24="","",INDEX(Scoring!$AG$29:$AG$361,MATCH($O24,Scoring!$AB$29:$AB$361,0))) -> Imuldosa | H24: =IF($O24="","",INDEX(Scoring!$C$29:$C$361,MATCH($O24,Scoring!$AB$29:$AB$361,0))) -> Immunology: psoriasis, psoriatic arthritis, Crohn's disease, ulcerative colitis | I24: =IF($O24="","",INDEX(Scoring!$I$29:$I$361,MATCH($O24,Scoring!$AB$29:$AB$361,0))) -> Prefilled syringe | J24: =IF($O24="","",INDEX(Scoring!$Z$29:$Z$361,MATCH($O24,Scoring!$AB$29:$AB$361,0))) -> 45 mg/0.5 mL pre-filled syringe | K24: =IF($O24="","",IF(INDEX(Scoring!$D$29:$D$361,MATCH($O24,Scoring!$AB$29:$AB$361,0))="",INDEX(Scoring!$AF$29:$AF$361,MATCH($O24,Scoring!$AB$29:$AB$361,0)),INDEX(Scoring!$D$29:$D$361,MATCH($O24,Scoring!$AB$29:$AB$361,0)))) -> 2838.33 | L24: =IF($O24="","",INDEX(Scoring!$M$29:$M$361,MATCH($O24,Scoring!$AB$29:$AB$361,0))) -> 125 | M24: =IF($O24="","",INDEX(Scoring!$F$29:$F$361,MATCH($O24,Scoring!$AB$29:$AB$361,0))) -> 2485.9 | N24: =IF($O24="","",INDEX(Scoring!$AI$29:$AI$361,MATCH($O24,Scoring!$AB$29:$AB$361,0))) -> UK, UK-NI | EU/EEA: all 30 countries | O24: =IFERROR(SMALL(Scoring!$AB$29:$AB$361,20),"") -> 1020
A25: =IF($O25="","",INT($O25/1000)) -> 1 | B25: =IF($O25="","",INDEX(Scoring!$A$29:$A$361,MATCH($O25,Scoring!$AB$29:$AB$361,0))) -> Intas | C25: =IF($O25="","",IF(INDEX(Scoring!$P$29:$P$361,MATCH($O25,Scoring!$AB$29:$AB$361,0))="","–",INDEX(Scoring!$P$29:$P$361,MATCH($O25,Scoring!$AB$29:$AB$361,0)))) -> 21 | D25: =IF($O25="","",INDEX(Scoring!$Q$29:$Q$361,MATCH($O25,Scoring!$AB$29:$AB$361,0))) -> Priority 2 | E25: =IF($O25="","",INDEX(Scoring!$AJ$29:$AJ$361,MATCH($O25,Scoring!$AB$29:$AB$361,0))) -> High price · lower volume | F25: =IF($O25="","",INDEX(Scoring!$B$29:$B$361,MATCH($O25,Scoring!$AB$29:$AB$361,0))) -> Degarelix | G25: =IF($O25="","",INDEX(Scoring!$AG$29:$AG$361,MATCH($O25,Scoring!$AB$29:$AB$361,0))) -> Degarelix; Degarelix Accord | H25: =IF($O25="","",INDEX(Scoring!$C$29:$C$361,MATCH($O25,Scoring!$AB$29:$AB$361,0))) -> Oncology: hormone therapy for advanced prostate cancer | I25: =IF($O25="","",INDEX(Scoring!$I$29:$I$361,MATCH($O25,Scoring!$AB$29:$AB$361,0))) -> Vial | J25: =IF($O25="","",INDEX(Scoring!$Z$29:$Z$361,MATCH($O25,Scoring!$AB$29:$AB$361,0))) -> 80 mg powder vial | K25: =IF($O25="","",IF(INDEX(Scoring!$D$29:$D$361,MATCH($O25,Scoring!$AB$29:$AB$361,0))="",INDEX(Scoring!$AF$29:$AF$361,MATCH($O25,Scoring!$AB$29:$AB$361,0)),INDEX(Scoring!$D$29:$D$361,MATCH($O25,Scoring!$AB$29:$AB$361,0)))) -> 92.62 | L25: =IF($O25="","",INDEX(Scoring!$M$29:$M$361,MATCH($O25,Scoring!$AB$29:$AB$361,0))) -> 26 | M25: =IF($O25="","",INDEX(Scoring!$F$29:$F$361,MATCH($O25,Scoring!$AB$29:$AB$361,0))) -> 140.9 | N25: =IF($O25="","",INDEX(Scoring!$AI$29:$AI$361,MATCH($O25,Scoring!$AB$29:$AB$361,0))) -> UK | EU/EEA: all 30 countries | O25: =IFERROR(SMALL(Scoring!$AB$29:$AB$361,21),"") -> 1021
A26: =IF($O26="","",INT($O26/1000)) -> 1 | B26: =IF($O26="","",INDEX(Scoring!$A$29:$A$361,MATCH($O26,Scoring!$AB$29:$AB$361,0))) -> Intas | C26: =IF($O26="","",IF(INDEX(Scoring!$P$29:$P$361,MATCH($O26,Scoring!$AB$29:$AB$361,0))="","–",INDEX(Scoring!$P$29:$P$361,MATCH($O26,Scoring!$AB$29:$AB$361,0)))) -> 22 | D26: =IF($O26="","",INDEX(Scoring!$Q$29:$Q$361,MATCH($O26,Scoring!$AB$29:$AB$361,0))) -> Priority 3 | E26: =IF($O26="","",INDEX(Scoring!$AJ$29:$AJ$361,MATCH($O26,Scoring!$AB$29:$AB$361,0))) -> Lower price · lower volume | F26: =IF($O26="","",INDEX(Scoring!$B$29:$B$361,MATCH($O26,Scoring!$AB$29:$AB$361,0))) -> Flucloxacillin | G26: =IF($O26="","",INDEX(Scoring!$AG$29:$AG$361,MATCH($O26,Scoring!$AB$29:$AB$361,0))) -> Floxapen | H26: =IF($O26="","",INDEX(Scoring!$C$29:$C$361,MATCH($O26,Scoring!$AB$29:$AB$361,0))) -> Anti-infective: staphylococcal skin, bone and heart infections | I26: =IF($O26="","",INDEX(Scoring!$I$29:$I$361,MATCH($O26,Scoring!$AB$29:$AB$361,0))) -> Vial | J26: =IF($O26="","",INDEX(Scoring!$Z$29:$Z$361,MATCH($O26,Scoring!$AB$29:$AB$361,0))) -> 500 mg powder vial | K26: =IF($O26="","",IF(INDEX(Scoring!$D$29:$D$361,MATCH($O26,Scoring!$AB$29:$AB$361,0))="",INDEX(Scoring!$AF$29:$AF$361,MATCH($O26,Scoring!$AB$29:$AB$361,0)),INDEX(Scoring!$D$29:$D$361,MATCH($O26,Scoring!$AB$29:$AB$361,0)))) -> 6.07 | L26: =IF($O26="","",INDEX(Scoring!$M$29:$M$361,MATCH($O26,Scoring!$AB$29:$AB$361,0))) -> 116 | M26: =IF($O26="","",INDEX(Scoring!$F$29:$F$361,MATCH($O26,Scoring!$AB$29:$AB$361,0))) -> 6287.6 | N26: =IF($O26="","",INDEX(Scoring!$AI$29:$AI$361,MATCH($O26,Scoring!$AB$29:$AB$361,0))) -> UK-NI | O26: =IFERROR(SMALL(Scoring!$AB$29:$AB$361,22),"") -> 1022
A27: =IF($O27="","",INT($O27/1000)) -> 1 | B27: =IF($O27="","",INDEX(Scoring!$A$29:$A$361,MATCH($O27,Scoring!$AB$29:$AB$361,0))) -> Intas | C27: =IF($O27="","",IF(INDEX(Scoring!$P$29:$P$361,MATCH($O27,Scoring!$AB$29:$AB$361,0))="","–",INDEX(Scoring!$P$29:$P$361,MATCH($O27,Scoring!$AB$29:$AB$361,0)))) -> 23 | D27: =IF($O27="","",INDEX(Scoring!$Q$29:$Q$361,MATCH($O27,Scoring!$AB$29:$AB$361,0))) -> Priority 3 | E27: =IF($O27="","",INDEX(Scoring!$AJ$29:$AJ$361,MATCH($O27,Scoring!$AB$29:$AB$361,0))) -> Lower price · lower volume | F27: =IF($O27="","",INDEX(Scoring!$B$29:$B$361,MATCH($O27,Scoring!$AB$29:$AB$361,0))) -> Progesterone | G27: =IF($O27="","",INDEX(Scoring!$AG$29:$AG$361,MATCH($O27,Scoring!$AB$29:$AB$361,0))) -> Progesterone | H27: =IF($O27="","",INDEX(Scoring!$C$29:$C$361,MATCH($O27,Scoring!$AB$29:$AB$361,0))) -> Women's health: IVF support, absent periods, abnormal uterine bleeding | I27: =IF($O27="","",INDEX(Scoring!$I$29:$I$361,MATCH($O27,Scoring!$AB$29:$AB$361,0))) -> Not stated | J27: =IF($O27="","",INDEX(Scoring!$Z$29:$Z$361,MATCH($O27,Scoring!$AB$29:$AB$361,0))) -> 50 mg/mL (container not stated) | K27: =IF($O27="","",IF(INDEX(Scoring!$D$29:$D$361,MATCH($O27,Scoring!$AB$29:$AB$361,0))="",INDEX(Scoring!$AF$29:$AF$361,MATCH($O27,Scoring!$AB$29:$AB$361,0)),INDEX(Scoring!$D$29:$D$361,MATCH($O27,Scoring!$AB$29:$AB$361,0)))) -> 6.23 | L27: =IF($O27="","",INDEX(Scoring!$M$29:$M$361,MATCH($O27,Scoring!$AB$29:$AB$361,0))) -> 88 | M27: =IF($O27="","",INDEX(Scoring!$F$29:$F$361,MATCH($O27,Scoring!$AB$29:$AB$361,0))) -> 2646.6 | N27: =IF($O27="","",INDEX(Scoring!$AI$29:$AI$361,MATCH($O27,Scoring!$AB$29:$AB$361,0))) -> US | O27: =IFERROR(SMALL(Scoring!$AB$29:$AB$361,23),"") -> 1023
A28: =IF($O28="","",INT($O28/1000)) -> 1 | B28: =IF($O28="","",INDEX(Scoring!$A$29:$A$361,MATCH($O28,Scoring!$AB$29:$AB$361,0))) -> Intas | C28: =IF($O28="","",IF(INDEX(Scoring!$P$29:$P$361,MATCH($O28,Scoring!$AB$29:$AB$361,0))="","–",INDEX(Scoring!$P$29:$P$361,MATCH($O28,Scoring!$AB$29:$AB$361,0)))) -> 24 | D28: =IF($O28="","",INDEX(Scoring!$Q$29:$Q$361,MATCH($O28,Scoring!$AB$29:$AB$361,0))) -> Priority 3 | E28: =IF($O28="","",INDEX(Scoring!$AJ$29:$AJ$361,MATCH($O28,Scoring!$AB$29:$AB$361,0))) -> Lower price · lower volume | F28: =IF($O28="","",INDEX(Scoring!$B$29:$B$361,MATCH($O28,Scoring!$AB$29:$AB$361,0))) -> Colistimethate Sodium | G28: =IF($O28="","",INDEX(Scoring!$AG$29:$AG$361,MATCH($O28,Scoring!$AB$29:$AB$361,0))) -> Colistimethate Sodium; Colistimetato Accord | H28: =IF($O28="","",INDEX(Scoring!$C$29:$C$361,MATCH($O28,Scoring!$AB$29:$AB$361,0))) -> Anti-infective: last-line treatment for drug-resistant Gram-negative infections | I28: =IF($O28="","",INDEX(Scoring!$I$29:$I$361,MATCH($O28,Scoring!$AB$29:$AB$361,0))) -> Vial | J28: =IF($O28="","",INDEX(Scoring!$Z$29:$Z$361,MATCH($O28,Scoring!$AB$29:$AB$361,0))) -> 2 MIU powder vial; 1 MIU powder vial | K28: =IF($O28="","",IF(INDEX(Scoring!$D$29:$D$361,MATCH($O28,Scoring!$AB$29:$AB$361,0))="",INDEX(Scoring!$AF$29:$AF$361,MATCH($O28,Scoring!$AB$29:$AB$361,0)),INDEX(Scoring!$D$29:$D$361,MATCH($O28,Scoring!$AB$29:$AB$361,0)))) -> 9.75 | L28: =IF($O28="","",INDEX(Scoring!$M$29:$M$361,MATCH($O28,Scoring!$AB$29:$AB$361,0))) -> 83 | M28: =IF($O28="","",INDEX(Scoring!$F$29:$F$361,MATCH($O28,Scoring!$AB$29:$AB$361,0))) -> 2033.7 | N28: =IF($O28="","",INDEX(Scoring!$AI$29:$AI$361,MATCH($O28,Scoring!$AB$29:$AB$361,0))) -> UK, UK-NI | EU/EEA (20): France, Netherlands, Belgium, Austria + 16 more | O28: =IFERROR(SMALL(Scoring!$AB$29:$AB$361,24),"") -> 1024
A29: =IF($O29="","",INT($O29/1000)) -> 1 | B29: =IF($O29="","",INDEX(Scoring!$A$29:$A$361,MATCH($O29,Scoring!$AB$29:$AB$361,0))) -> Intas | C29: =IF($O29="","",IF(INDEX(Scoring!$P$29:$P$361,MATCH($O29,Scoring!$AB$29:$AB$361,0))="","–",INDEX(Scoring!$P$29:$P$361,MATCH($O29,Scoring!$AB$29:$AB$361,0)))) -> 25 | D29: =IF($O29="","",INDEX(Scoring!$Q$29:$Q$361,MATCH($O29,Scoring!$AB$29:$AB$361,0))) -> Priority 3 | E29: =IF($O29="","",INDEX(Scoring!$AJ$29:$AJ$361,MATCH($O29,Scoring!$AB$29:$AB$361,0))) -> Lower price · lower volume | F29: =IF($O29="","",INDEX(Scoring!$B$29:$B$361,MATCH($O29,Scoring!$AB$29:$AB$361,0))) -> Naloxone | G29: =IF($O29="","",INDEX(Scoring!$AG$29:$AG$361,MATCH($O29,Scoring!$AB$29:$AB$361,0))) -> Naloxone Hydrochloride; Naloxone | H29: =IF($O29="","",INDEX(Scoring!$C$29:$C$361,MATCH($O29,Scoring!$AB$29:$AB$361,0))) -> Critical care: reversal of opioid overdose | I29: =IF($O29="","",INDEX(Scoring!$I$29:$I$361,MATCH($O29,Scoring!$AB$29:$AB$361,0))) -> Prefilled syringe | J29: =IF($O29="","",INDEX(Scoring!$Z$29:$Z$361,MATCH($O29,Scoring!$AB$29:$AB$361,0))) -> 0.4 mg/mL (container not stated); 1 mg/mL (container not stated); 400 mcg/mL pre-filled syringe | K29: =IF($O29="","",IF(INDEX(Scoring!$D$29:$D$361,MATCH($O29,Scoring!$AB$29:$AB$361,0))="",INDEX(Scoring!$AF$29:$AF$361,MATCH($O29,Scoring!$AB$29:$AB$361,0)),INDEX(Scoring!$D$29:$D$361,MATCH($O29,Scoring!$AB$29:$AB$361,0)))) -> 5.42 | L29: =IF($O29="","",INDEX(Scoring!$M$29:$M$361,MATCH($O29,Scoring!$AB$29:$AB$361,0))) -> 88 | M29: =IF($O29="","",INDEX(Scoring!$F$29:$F$361,MATCH($O29,Scoring!$AB$29:$AB$361,0))) -> 1437.9 | N29: =IF($O29="","",INDEX(Scoring!$AI$29:$AI$361,MATCH($O29,Scoring!$AB$29:$AB$361,0))) -> US, UK, UK-NI | EU/EEA (12): Germany, France, Netherlands, Austria + 8 more | O29: =IFERROR(SMALL(Scoring!$AB$29:$AB$361,25),"") -> 1025
A30: =IF($O30="","",INT($O30/1000)) -> 1 | B30: =IF($O30="","",INDEX(Scoring!$A$29:$A$361,MATCH($O30,Scoring!$AB$29:$AB$361,0))) -> Intas | C30: =IF($O30="","",IF(INDEX(Scoring!$P$29:$P$361,MATCH($O30,Scoring!$AB$29:$AB$361,0))="","–",INDEX(Scoring!$P$29:$P$361,MATCH($O30,Scoring!$AB$29:$AB$361,0)))) -> 26 | D30: =IF($O30="","",INDEX(Scoring!$Q$29:$Q$361,MATCH($O30,Scoring!$AB$29:$AB$361,0))) -> Priority 3 | E30: =IF($O30="","",INDEX(Scoring!$AJ$29:$AJ$361,MATCH($O30,Scoring!$AB$29:$AB$361,0))) -> Lower price · lower volume | F30: =IF($O30="","",INDEX(Scoring!$B$29:$B$361,MATCH($O30,Scoring!$AB$29:$AB$361,0))) -> Hydroxocobalamin | G30: =IF($O30="","",INDEX(Scoring!$AG$29:$AG$361,MATCH($O30,Scoring!$AB$29:$AB$361,0))) -> Hydroxocobalamin Accord Healthcare | H30: =IF($O30="","",INDEX(Scoring!$C$29:$C$361,MATCH($O30,Scoring!$AB$29:$AB$361,0))) -> Haematology: vitamin B12 deficiency, cyanide poisoning | I30: =IF($O30="","",INDEX(Scoring!$I$29:$I$361,MATCH($O30,Scoring!$AB$29:$AB$361,0))) -> Not stated | J30: =IF($O30="","",INDEX(Scoring!$Z$29:$Z$361,MATCH($O30,Scoring!$AB$29:$AB$361,0))) -> 1 mg/mL (container not stated) | K30: =IF($O30="","",IF(INDEX(Scoring!$D$29:$D$361,MATCH($O30,Scoring!$AB$29:$AB$361,0))="",INDEX(Scoring!$AF$29:$AF$361,MATCH($O30,Scoring!$AB$29:$AB$361,0)),INDEX(Scoring!$D$29:$D$361,MATCH($O30,Scoring!$AB$29:$AB$361,0)))) -> 9.83 | L30: =IF($O30="","",INDEX(Scoring!$M$29:$M$361,MATCH($O30,Scoring!$AB$29:$AB$361,0))) -> 22 | M30: =IF($O30="","",INDEX(Scoring!$F$29:$F$361,MATCH($O30,Scoring!$AB$29:$AB$361,0))) -> 315.7 | N30: =IF($O30="","",INDEX(Scoring!$AI$29:$AI$361,MATCH($O30,Scoring!$AB$29:$AB$361,0))) -> UK-NI | O30: =IFERROR(SMALL(Scoring!$AB$29:$AB$361,26),"") -> 1026
A31: =IF($O31="","",INT($O31/1000)) -> 1 | B31: =IF($O31="","",INDEX(Scoring!$A$29:$A$361,MATCH($O31,Scoring!$AB$29:$AB$361,0))) -> Intas | C31: =IF($O31="","",IF(INDEX(Scoring!$P$29:$P$361,MATCH($O31,Scoring!$AB$29:$AB$361,0))="","–",INDEX(Scoring!$P$29:$P$361,MATCH($O31,Scoring!$AB$29:$AB$361,0)))) -> – | D31: =IF($O31="","",INDEX(Scoring!$Q$29:$Q$361,MATCH($O31,Scoring!$AB$29:$AB$361,0))) -> Excluded – price ≤ $5 | E31: =IF($O31="","",INDEX(Scoring!$AJ$29:$AJ$361,MATCH($O31,Scoring!$AB$29:$AB$361,0))) | F31: =IF($O31="","",INDEX(Scoring!$B$29:$B$361,MATCH($O31,Scoring!$AB$29:$AB$361,0))) -> Amoxicillin | G31: =IF($O31="","",INDEX(Scoring!$AG$29:$AG$361,MATCH($O31,Scoring!$AB$29:$AB$361,0))) -> Amoxicillin Accord Healthcare | H31: =IF($O31="","",INDEX(Scoring!$C$29:$C$361,MATCH($O31,Scoring!$AB$29:$AB$361,0))) -> Anti-infective: serious bacterial infections when oral treatment is not possible | I31: =IF($O31="","",INDEX(Scoring!$I$29:$I$361,MATCH($O31,Scoring!$AB$29:$AB$361,0))) -> Not stated | J31: =IF($O31="","",INDEX(Scoring!$Z$29:$Z$361,MATCH($O31,Scoring!$AB$29:$AB$361,0))) -> 500 mg (container not stated) | K31: =IF($O31="","",IF(INDEX(Scoring!$D$29:$D$361,MATCH($O31,Scoring!$AB$29:$AB$361,0))="",INDEX(Scoring!$AF$29:$AF$361,MATCH($O31,Scoring!$AB$29:$AB$361,0)),INDEX(Scoring!$D$29:$D$361,MATCH($O31,Scoring!$AB$29:$AB$361,0)))) -> 1.59 | L31: =IF($O31="","",INDEX(Scoring!$M$29:$M$361,MATCH($O31,Scoring!$AB$29:$AB$361,0))) -> 715 | M31: =IF($O31="","",INDEX(Scoring!$F$29:$F$361,MATCH($O31,Scoring!$AB$29:$AB$361,0))) -> 33794.9 | N31: =IF($O31="","",INDEX(Scoring!$AI$29:$AI$361,MATCH($O31,Scoring!$AB$29:$AB$361,0))) -> UK-NI | EU/EEA (1): Portugal | O31: =IFERROR(SMALL(Scoring!$AB$29:$AB$361,27),"") -> 1901
A32: =IF($O32="","",INT($O32/1000)) -> 1 | B32: =IF($O32="","",INDEX(Scoring!$A$29:$A$361,MATCH($O32,Scoring!$AB$29:$AB$361,0))) -> Intas | C32: =IF($O32="","",IF(INDEX(Scoring!$P$29:$P$361,MATCH($O32,Scoring!$AB$29:$AB$361,0))="","–",INDEX(Scoring!$P$29:$P$361,MATCH($O32,Scoring!$AB$29:$AB$361,0)))) -> – | D32: =IF($O32="","",INDEX(Scoring!$Q$29:$Q$361,MATCH($O32,Scoring!$AB$29:$AB$361,0))) -> Excluded – price ≤ $5 | E32: =IF($O32="","",INDEX(Scoring!$AJ$29:$AJ$361,MATCH($O32,Scoring!$AB$29:$AB$361,0))) | F32: =IF($O32="","",INDEX(Scoring!$B$29:$B$361,MATCH($O32,Scoring!$AB$29:$AB$361,0))) -> Glycopyrrolate | G32: =IF($O32="","",INDEX(Scoring!$AG$29:$AG$361,MATCH($O32,Scoring!$AB$29:$AB$361,0))) -> Glycopyrrolate Accord | H32: =IF($O32="","",INDEX(Scoring!$C$29:$C$361,MATCH($O32,Scoring!$AB$29:$AB$361,0))) -> Anaesthesia: reduces secretions, reversal of muscle relaxants | I32: =IF($O32="","",INDEX(Scoring!$I$29:$I$361,MATCH($O32,Scoring!$AB$29:$AB$361,0))) -> Ampoule | J32: =IF($O32="","",INDEX(Scoring!$Z$29:$Z$361,MATCH($O32,Scoring!$AB$29:$AB$361,0))) -> 0.6 mg/3 mL ampoule | K32: =IF($O32="","",IF(INDEX(Scoring!$D$29:$D$361,MATCH($O32,Scoring!$AB$29:$AB$361,0))="",INDEX(Scoring!$AF$29:$AF$361,MATCH($O32,Scoring!$AB$29:$AB$361,0)),INDEX(Scoring!$D$29:$D$361,MATCH($O32,Scoring!$AB$29:$AB$361,0)))) -> 3 | L32: =IF($O32="","",INDEX(Scoring!$M$29:$M$361,MATCH($O32,Scoring!$AB$29:$AB$361,0))) -> 119 | M32: =IF($O32="","",INDEX(Scoring!$F$29:$F$361,MATCH($O32,Scoring!$AB$29:$AB$361,0))) -> 1332.4 | N32: =IF($O32="","",INDEX(Scoring!$AI$29:$AI$361,MATCH($O32,Scoring!$AB$29:$AB$361,0))) -> Australia, UK-NI | EU/EEA (6): Germany, Austria, Cyprus, Finland, Italy, Sweden | O32: =IFERROR(SMALL(Scoring!$AB$29:$AB$361,28),"") -> 1902
A33: =IF($O33="","",INT($O33/1000)) -> 1 | B33: =IF($O33="","",INDEX(Scoring!$A$29:$A$361,MATCH($O33,Scoring!$AB$29:$AB$361,0))) -> Intas | C33: =IF($O33="","",IF(INDEX(Scoring!$P$29:$P$361,MATCH($O33,Scoring!$AB$29:$AB$361,0))="","–",INDEX(Scoring!$P$29:$P$361,MATCH($O33,Scoring!$AB$29:$AB$361,0)))) -> – | D33: =IF($O33="","",INDEX(Scoring!$Q$29:$Q$361,MATCH($O33,Scoring!$AB$29:$AB$361,0))) -> Excluded – price ≤ $5 | E33: =IF($O33="","",INDEX(Scoring!$AJ$29:$AJ$361,MATCH($O33,Scoring!$AB$29:$AB$361,0))) | F33: =IF($O33="","",INDEX(Scoring!$B$29:$B$361,MATCH($O33,Scoring!$AB$29:$AB$361,0))) -> Lidocaine | G33: =IF($O33="","",INDEX(Scoring!$AG$29:$AG$361,MATCH($O33,Scoring!$AB$29:$AB$361,0))) -> Lidocaine Accord; Lidocaine Intas | H33: =IF($O33="","",INDEX(Scoring!$C$29:$C$361,MATCH($O33,Scoring!$AB$29:$AB$361,0))) -> Anaesthesia: local anaesthetic, ventricular arrhythmias | I33: =IF($O33="","",INDEX(Scoring!$I$29:$I$361,MATCH($O33,Scoring!$AB$29:$AB$361,0))) -> Vial, Ampoule | J33: =IF($O33="","",INDEX(Scoring!$Z$29:$Z$361,MATCH($O33,Scoring!$AB$29:$AB$361,0))) -> 100 mg/5 mL ampoule; 400 mg/20 mL vial; 40 mg/2 mL ampoule; 200 mg/20 mL vial | K33: =IF($O33="","",IF(INDEX(Scoring!$D$29:$D$361,MATCH($O33,Scoring!$AB$29:$AB$361,0))="",INDEX(Scoring!$AF$29:$AF$361,MATCH($O33,Scoring!$AB$29:$AB$361,0)),INDEX(Scoring!$D$29:$D$361,MATCH($O33,Scoring!$AB$29:$AB$361,0)))) -> 1.42 | L33: =IF($O33="","",INDEX(Scoring!$M$29:$M$361,MATCH($O33,Scoring!$AB$29:$AB$361,0))) -> 670 | M33: =IF($O33="","",INDEX(Scoring!$F$29:$F$361,MATCH($O33,Scoring!$AB$29:$AB$361,0))) -> 18611.6 | N33: =IF($O33="","",INDEX(Scoring!$AI$29:$AI$361,MATCH($O33,Scoring!$AB$29:$AB$361,0))) -> Australia, UK-NI | EU/EEA (7): Austria, Cyprus, Estonia, Lithuania + 3 more | O33: =IFERROR(SMALL(Scoring!$AB$29:$AB$361,29),"") -> 1903
A34: =IF($O34="","",INT($O34/1000)) -> 1 | B34: =IF($O34="","",INDEX(Scoring!$A$29:$A$361,MATCH($O34,Scoring!$AB$29:$AB$361,0))) -> Intas | C34: =IF($O34="","",IF(INDEX(Scoring!$P$29:$P$361,MATCH($O34,Scoring!$AB$29:$AB$361,0))="","–",INDEX(Scoring!$P$29:$P$361,MATCH($O34,Scoring!$AB$29:$AB$361,0)))) -> – | D34: =IF($O34="","",INDEX(Scoring!$Q$29:$Q$361,MATCH($O34,Scoring!$AB$29:$AB$361,0))) -> Excluded – price ≤ $5 | E34: =IF($O34="","",INDEX(Scoring!$AJ$29:$AJ$361,MATCH($O34,Scoring!$AB$29:$AB$361,0))) | F34: =IF($O34="","",INDEX(Scoring!$B$29:$B$361,MATCH($O34,Scoring!$AB$29:$AB$361,0))) -> Phenytoin | G34: =IF($O34="","",INDEX(Scoring!$AG$29:$AG$361,MATCH($O34,Scoring!$AB$29:$AB$361,0))) -> Phenytoin Accord | H34: =IF($O34="","",INDEX(Scoring!$C$29:$C$361,MATCH($O34,Scoring!$AB$29:$AB$361,0))) -> Neurology: status epilepticus, seizure prevention | I34: =IF($O34="","",INDEX(Scoring!$I$29:$I$361,MATCH($O34,Scoring!$AB$29:$AB$361,0))) -> Not stated | J34: =IF($O34="","",INDEX(Scoring!$Z$29:$Z$361,MATCH($O34,Scoring!$AB$29:$AB$361,0))) -> 100 mg/2 mL (container not stated) | K34: =IF($O34="","",IF(INDEX(Scoring!$D$29:$D$361,MATCH($O34,Scoring!$AB$29:$AB$361,0))="",INDEX(Scoring!$AF$29:$AF$361,MATCH($O34,Scoring!$AB$29:$AB$361,0)),INDEX(Scoring!$D$29:$D$361,MATCH($O34,Scoring!$AB$29:$AB$361,0)))) -> 4.49 | L34: =IF($O34="","",INDEX(Scoring!$M$29:$M$361,MATCH($O34,Scoring!$AB$29:$AB$361,0))) -> 208 | M34: =IF($O34="","",INDEX(Scoring!$F$29:$F$361,MATCH($O34,Scoring!$AB$29:$AB$361,0))) -> 2009.5 | N34: =IF($O34="","",INDEX(Scoring!$AI$29:$AI$361,MATCH($O34,Scoring!$AB$29:$AB$361,0))) -> UK-NI | EU/EEA (1): Portugal | O34: =IFERROR(SMALL(Scoring!$AB$29:$AB$361,30),"") -> 1904
A35: =IF($O35="","",INT($O35/1000)) -> 2 | B35: =IF($O35="","",INDEX(Scoring!$A$29:$A$361,MATCH($O35,Scoring!$AB$29:$AB$361,0))) -> Aurobindo | C35: =IF($O35="","",IF(INDEX(Scoring!$P$29:$P$361,MATCH($O35,Scoring!$AB$29:$AB$361,0))="","–",INDEX(Scoring!$P$29:$P$361,MATCH($O35,Scoring!$AB$29:$AB$361,0)))) -> 1 | D35: =IF($O35="","",INDEX(Scoring!$Q$29:$Q$361,MATCH($O35,Scoring!$AB$29:$AB$361,0))) -> Priority 1 | E35: =IF($O35="","",INDEX(Scoring!$AJ$29:$AJ$361,MATCH($O35,Scoring!$AB$29:$AB$361,0))) -> High price · high volume | F35: =IF($O35="","",INDEX(Scoring!$B$29:$B$361,MATCH($O35,Scoring!$AB$29:$AB$361,0))) -> Ertapenem | G35: =IF($O35="","",INDEX(Scoring!$AG$29:$AG$361,MATCH($O35,Scoring!$AB$29:$AB$361,0))) -> Ertapenem Sodium; Ertapenem; Etamep (+1 more) | H35: =IF($O35="","",INDEX(Scoring!$C$29:$C$361,MATCH($O35,Scoring!$AB$29:$AB$361,0))) -> Anti-infective: abdominal, skin and urinary infections, pneumonia | I35: =IF($O35="","",INDEX(Scoring!$I$29:$I$361,MATCH($O35,Scoring!$AB$29:$AB$361,0))) -> Vial | J35: =IF($O35="","",INDEX(Scoring!$Z$29:$Z$361,MATCH($O35,Scoring!$AB$29:$AB$361,0))) -> 1 g powder vial; 1 g in 20 mL powder vial | K35: =IF($O35="","",IF(INDEX(Scoring!$D$29:$D$361,MATCH($O35,Scoring!$AB$29:$AB$361,0))="",INDEX(Scoring!$AF$29:$AF$361,MATCH($O35,Scoring!$AB$29:$AB$361,0)),INDEX(Scoring!$D$29:$D$361,MATCH($O35,Scoring!$AB$29:$AB$361,0)))) -> 28.55 | L35: =IF($O35="","",INDEX(Scoring!$M$29:$M$361,MATCH($O35,Scoring!$AB$29:$AB$361,0))) -> 223 | M35: =IF($O35="","",INDEX(Scoring!$F$29:$F$361,MATCH($O35,Scoring!$AB$29:$AB$361,0))) -> 53539.9 | N35: =IF($O35="","",INDEX(Scoring!$AI$29:$AI$361,MATCH($O35,Scoring!$AB$29:$AB$361,0))) -> US, Canada, South Africa, UK-NI | EU/EEA (6): France, Italy, Poland, Portugal, Romania, Spain | O35: =IFERROR(SMALL(Scoring!$AB$29:$AB$361,31),"") -> 2001
A36: =IF($O36="","",INT($O36/1000)) -> 2 | B36: =IF($O36="","",INDEX(Scoring!$A$29:$A$361,MATCH($O36,Scoring!$AB$29:$AB$361,0))) -> Aurobindo | C36: =IF($O36="","",IF(INDEX(Scoring!$P$29:$P$361,MATCH($O36,Scoring!$AB$29:$AB$361,0))="","–",INDEX(Scoring!$P$29:$P$361,MATCH($O36,Scoring!$AB$29:$AB$361,0)))) -> 2 | D36: =IF($O36="","",INDEX(Scoring!$Q$29:$Q$361,MATCH($O36,Scoring!$AB$29:$AB$361,0))) -> Priority 1 | E36: =IF($O36="","",INDEX(Scoring!$AJ$29:$AJ$361,MATCH($O36,Scoring!$AB$29:$AB$361,0))) -> High price · high volume | F36: =IF($O36="","",INDEX(Scoring!$B$29:$B$361,MATCH($O36,Scoring!$AB$29:$AB$361,0))) -> Azacitidine | G36: =IF($O36="","",INDEX(Scoring!$AG$29:$AG$361,MATCH($O36,Scoring!$AB$29:$AB$361,0))) -> Azacitidine; Azacitidin Puren; Azacitidine Eugia | H36: =IF($O36="","",INDEX(Scoring!$C$29:$C$361,MATCH($O36,Scoring!$AB$29:$AB$361,0))) -> Oncology: myelodysplastic syndromes, acute myeloid leukaemia | I36: =IF($O36="","",INDEX(Scoring!$I$29:$I$361,MATCH($O36,Scoring!$AB$29:$AB$361,0))) -> Vial | J36: =IF($O36="","",INDEX(Scoring!$Z$29:$Z$361,MATCH($O36,Scoring!$AB$29:$AB$361,0))) -> 25 mg/mL powder vial; 100 mg powder vial | K36: =IF($O36="","",IF(INDEX(Scoring!$D$29:$D$361,MATCH($O36,Scoring!$AB$29:$AB$361,0))="",INDEX(Scoring!$AF$29:$AF$361,MATCH($O36,Scoring!$AB$29:$AB$361,0)),INDEX(Scoring!$D$29:$D$361,MATCH($O36,Scoring!$AB$29:$AB$361,0)))) -> 256.12 | L36: =IF($O36="","",INDEX(Scoring!$M$29:$M$361,MATCH($O36,Scoring!$AB$29:$AB$361,0))) -> 632 | M36: =IF($O36="","",INDEX(Scoring!$F$29:$F$361,MATCH($O36,Scoring!$AB$29:$AB$361,0))) -> 42181.7 | N36: =IF($O36="","",INDEX(Scoring!$AI$29:$AI$361,MATCH($O36,Scoring!$AB$29:$AB$361,0))) -> UK, Australia, UK-NI | EU/EEA (8): Germany, France, Netherlands, Belgium + 4 more | O36: =IFERROR(SMALL(Scoring!$AB$29:$AB$361,32),"") -> 2002
A37: =IF($O37="","",INT($O37/1000)) -> 2 | B37: =IF($O37="","",INDEX(Scoring!$A$29:$A$361,MATCH($O37,Scoring!$AB$29:$AB$361,0))) -> Aurobindo | C37: =IF($O37="","",IF(INDEX(Scoring!$P$29:$P$361,MATCH($O37,Scoring!$AB$29:$AB$361,0))="","–",INDEX(Scoring!$P$29:$P$361,MATCH($O37,Scoring!$AB$29:$AB$361,0)))) -> 3 | D37: =IF($O37="","",INDEX(Scoring!$Q$29:$Q$361,MATCH($O37,Scoring!$AB$29:$AB$361,0))) -> Priority 1 | E37: =IF($O37="","",INDEX(Scoring!$AJ$29:$AJ$361,MATCH($O37,Scoring!$AB$29:$AB$361,0))) -> High price · high volume | F37: =IF($O37="","",INDEX(Scoring!$B$29:$B$361,MATCH($O37,Scoring!$AB$29:$AB$361,0))) -> Bortezomib | G37: =IF($O37="","",INDEX(Scoring!$AG$29:$AG$361,MATCH($O37,Scoring!$AB$29:$AB$361,0))) -> Bortezomib; Bortezomib Milpharm; Bortezomib Arrow (+1 more) | H37: =IF($O37="","",INDEX(Scoring!$C$29:$C$361,MATCH($O37,Scoring!$AB$29:$AB$361,0))) -> Oncology: multiple myeloma, mantle cell lymphoma | I37: =IF($O37="","",INDEX(Scoring!$I$29:$I$361,MATCH($O37,Scoring!$AB$29:$AB$361,0))) -> Vial | J37: =IF($O37="","",INDEX(Scoring!$Z$29:$Z$361,MATCH($O37,Scoring!$AB$29:$AB$361,0))) -> 3.5 mg powder vial | K37: =IF($O37="","",IF(INDEX(Scoring!$D$29:$D$361,MATCH($O37,Scoring!$AB$29:$AB$361,0))="",INDEX(Scoring!$AF$29:$AF$361,MATCH($O37,Scoring!$AB$29:$AB$361,0)),INDEX(Scoring!$D$29:$D$361,MATCH($O37,Scoring!$AB$29:$AB$361,0)))) -> 584.34 | L37: =IF($O37="","",INDEX(Scoring!$M$29:$M$361,MATCH($O37,Scoring!$AB$29:$AB$361,0))) -> 905 | M37: =IF($O37="","",INDEX(Scoring!$F$29:$F$361,MATCH($O37,Scoring!$AB$29:$AB$361,0))) -> 28093.4 | N37: =IF($O37="","",INDEX(Scoring!$AI$29:$AI$361,MATCH($O37,Scoring!$AB$29:$AB$361,0))) -> US, UK, Australia, UK-NI | EU/EEA (8): Germany, France, Netherlands, Belgium + 4 more | O37: =IFERROR(SMALL(Scoring!$AB$29:$AB$361,33),"") -> 2003
A38: =IF($O38="","",INT($O38/1000)) -> 2 | B38: =IF($O38="","",INDEX(Scoring!$A$29:$A$361,MATCH($O38,Scoring!$AB$29:$AB$361,0))) -> Aurobindo | C38: =IF($O38="","",IF(INDEX(Scoring!$P$29:$P$361,MATCH($O38,Scoring!$AB$29:$AB$361,0))="","–",INDEX(Scoring!$P$29:$P$361,MATCH($O38,Scoring!$AB$29:$AB$361,0)))) -> 4 | D38: =IF($O38="","",INDEX(Scoring!$Q$29:$Q$361,MATCH($O38,Scoring!$AB$29:$AB$361,0))) -> Priority 1 | E38: =IF($O38="","",INDEX(Scoring!$AJ$29:$AJ$361,MATCH($O38,Scoring!$AB$29:$AB$361,0))) -> High price · high volume | F38: =IF($O38="","",INDEX(Scoring!$B$29:$B$361,MATCH($O38,Scoring!$AB$29:$AB$361,0))) -> Fulvestrant | G38: =IF($O38="","",INDEX(Scoring!$AG$29:$AG$361,MATCH($O38,Scoring!$AB$29:$AB$361,0))) -> Fulvestrant; Fulvestrant Arrow; EUG-Fulvestrant | H38: =IF($O38="","",INDEX(Scoring!$C$29:$C$361,MATCH($O38,Scoring!$AB$29:$AB$361,0))) -> Oncology: hormone receptor-positive advanced breast cancer | I38: =IF($O38="","",INDEX(Scoring!$I$29:$I$361,MATCH($O38,Scoring!$AB$29:$AB$361,0))) -> Prefilled syringe | J38: =IF($O38="","",INDEX(Scoring!$Z$29:$Z$361,MATCH($O38,Scoring!$AB$29:$AB$361,0))) -> 250 mg/5 mL pre-filled syringe | K38: =IF($O38="","",IF(INDEX(Scoring!$D$29:$D$361,MATCH($O38,Scoring!$AB$29:$AB$361,0))="",INDEX(Scoring!$AF$29:$AF$361,MATCH($O38,Scoring!$AB$29:$AB$361,0)),INDEX(Scoring!$D$29:$D$361,MATCH($O38,Scoring!$AB$29:$AB$361,0)))) -> 308.1 | L38: =IF($O38="","",INDEX(Scoring!$M$29:$M$361,MATCH($O38,Scoring!$AB$29:$AB$361,0))) -> 146 | M38: =IF($O38="","",INDEX(Scoring!$F$29:$F$361,MATCH($O38,Scoring!$AB$29:$AB$361,0))) -> 11366.1 | N38: =IF($O38="","",INDEX(Scoring!$AI$29:$AI$361,MATCH($O38,Scoring!$AB$29:$AB$361,0))) -> UK, Australia | EU/EEA (8): Germany, France, Netherlands, Belgium + 4 more | O38: =IFERROR(SMALL(Scoring!$AB$29:$AB$361,34),"") -> 2004
A39: =IF($O39="","",INT($O39/1000)) -> 2 | B39: =IF($O39="","",INDEX(Scoring!$A$29:$A$361,MATCH($O39,Scoring!$AB$29:$AB$361,0))) -> Aurobindo | C39: =IF($O39="","",IF(INDEX(Scoring!$P$29:$P$361,MATCH($O39,Scoring!$AB$29:$AB$361,0))="","–",INDEX(Scoring!$P$29:$P$361,MATCH($O39,Scoring!$AB$29:$AB$361,0)))) -> 5 | D39: =IF($O39="","",INDEX(Scoring!$Q$29:$Q$361,MATCH($O39,Scoring!$AB$29:$AB$361,0))) -> Priority 1 | E39: =IF($O39="","",INDEX(Scoring!$AJ$29:$AJ$361,MATCH($O39,Scoring!$AB$29:$AB$361,0))) -> High price · high volume | F39: =IF($O39="","",INDEX(Scoring!$B$29:$B$361,MATCH($O39,Scoring!$AB$29:$AB$361,0))) -> Folinic Acid (Leucovorin) | G39: =IF($O39="","",INDEX(Scoring!$AG$29:$AG$361,MATCH($O39,Scoring!$AB$29:$AB$361,0))) -> Folinsäure Aurobindo | H39: =IF($O39="","",INDEX(Scoring!$C$29:$C$361,MATCH($O39,Scoring!$AB$29:$AB$361,0))) -> Oncology support: methotrexate rescue, combination therapy in colorectal cancer | I39: =IF($O39="","",INDEX(Scoring!$I$29:$I$361,MATCH($O39,Scoring!$AB$29:$AB$361,0))) -> Vial | J39: =IF($O39="","",INDEX(Scoring!$Z$29:$Z$361,MATCH($O39,Scoring!$AB$29:$AB$361,0))) -> 1000 mg/100 mL vial | K39: =IF($O39="","",IF(INDEX(Scoring!$D$29:$D$361,MATCH($O39,Scoring!$AB$29:$AB$361,0))="",INDEX(Scoring!$AF$29:$AF$361,MATCH($O39,Scoring!$AB$29:$AB$361,0)),INDEX(Scoring!$D$29:$D$361,MATCH($O39,Scoring!$AB$29:$AB$361,0)))) -> 64.93 | L39: =IF($O39="","",INDEX(Scoring!$M$29:$M$361,MATCH($O39,Scoring!$AB$29:$AB$361,0))) -> 243 | M39: =IF($O39="","",INDEX(Scoring!$F$29:$F$361,MATCH($O39,Scoring!$AB$29:$AB$361,0))) -> 3562.5 | N39: =IF($O39="","",INDEX(Scoring!$AI$29:$AI$361,MATCH($O39,Scoring!$AB$29:$AB$361,0))) -> EU/EEA (1): Germany | O39: =IFERROR(SMALL(Scoring!$AB$29:$AB$361,35),"") -> 2005
A40: =IF($O40="","",INT($O40/1000)) -> 2 | B40: =IF($O40="","",INDEX(Scoring!$A$29:$A$361,MATCH($O40,Scoring!$AB$29:$AB$361,0))) -> Aurobindo | C40: =IF($O40="","",IF(INDEX(Scoring!$P$29:$P$361,MATCH($O40,Scoring!$AB$29:$AB$361,0))="","–",INDEX(Scoring!$P$29:$P$361,MATCH($O40,Scoring!$AB$29:$AB$361,0)))) -> 6 | D40: =IF($O40="","",INDEX(Scoring!$Q$29:$Q$361,MATCH($O40,Scoring!$AB$29:$AB$361,0))) -> Priority 1 | E40: =IF($O40="","",INDEX(Scoring!$AJ$29:$AJ$361,MATCH($O40,Scoring!$AB$29:$AB$361,0))) -> High price · high volume | F40: =IF($O40="","",INDEX(Scoring!$B$29:$B$361,MATCH($O40,Scoring!$AB$29:$AB$361,0))) -> Testosterone Enanthate | G40: =IF($O40="","",INDEX(Scoring!$AG$29:$AG$361,MATCH($O40,Scoring!$AB$29:$AB$361,0))) -> Testosterone Enanthate | H40: =IF($O40="","",INDEX(Scoring!$C$29:$C$361,MATCH($O40,Scoring!$AB$29:$AB$361,0))) -> Endocrinology: male hypogonadism, delayed puberty | I40: =IF($O40="","",INDEX(Scoring!$I$29:$I$361,MATCH($O40,Scoring!$AB$29:$AB$361,0))) -> Vial | J40: =IF($O40="","",INDEX(Scoring!$Z$29:$Z$361,MATCH($O40,Scoring!$AB$29:$AB$361,0))) -> 1000 mg/5 mL vial | K40: =IF($O40="","",IF(INDEX(Scoring!$D$29:$D$361,MATCH($O40,Scoring!$AB$29:$AB$361,0))="",INDEX(Scoring!$AF$29:$AF$361,MATCH($O40,Scoring!$AB$29:$AB$361,0)),INDEX(Scoring!$D$29:$D$361,MATCH($O40,Scoring!$AB$29:$AB$361,0)))) -> 36.17 | L40: =IF($O40="","",INDEX(Scoring!$M$29:$M$361,MATCH($O40,Scoring!$AB$29:$AB$361,0))) -> 448 | M40: =IF($O40="","",INDEX(Scoring!$F$29:$F$361,MATCH($O40,Scoring!$AB$29:$AB$361,0))) -> 1202.2 | N40: =IF($O40="","",INDEX(Scoring!$AI$29:$AI$361,MATCH($O40,Scoring!$AB$29:$AB$361,0))) -> US | O40: =IFERROR(SMALL(Scoring!$AB$29:$AB$361,36),"") -> 2006
A41: =IF($O41="","",INT($O41/1000)) -> 2 | B41: =IF($O41="","",INDEX(Scoring!$A$29:$A$361,MATCH($O41,Scoring!$AB$29:$AB$361,0))) -> Aurobindo | C41: =IF($O41="","",IF(INDEX(Scoring!$P$29:$P$361,MATCH($O41,Scoring!$AB$29:$AB$361,0))="","–",INDEX(Scoring!$P$29:$P$361,MATCH($O41,Scoring!$AB$29:$AB$361,0)))) -> 7 | D41: =IF($O41="","",INDEX(Scoring!$Q$29:$Q$361,MATCH($O41,Scoring!$AB$29:$AB$361,0))) -> Priority 2 | E41: =IF($O41="","",INDEX(Scoring!$AJ$29:$AJ$361,MATCH($O41,Scoring!$AB$29:$AB$361,0))) -> Lower price · high volume | F41: =IF($O41="","",INDEX(Scoring!$B$29:$B$361,MATCH($O41,Scoring!$AB$29:$AB$361,0))) -> Ceftriaxone | G41: =IF($O41="","",INDEX(Scoring!$AG$29:$AG$361,MATCH($O41,Scoring!$AB$29:$AB$361,0))) -> Ceftriaxon Puren; Ceftriaxone Almus | H41: =IF($O41="","",INDEX(Scoring!$C$29:$C$361,MATCH($O41,Scoring!$AB$29:$AB$361,0))) -> Anti-infective: pneumonia, meningitis, sepsis, gonorrhoea, typhoid | I41: =IF($O41="","",INDEX(Scoring!$I$29:$I$361,MATCH($O41,Scoring!$AB$29:$AB$361,0))) -> Vial, Ampoule | J41: =IF($O41="","",INDEX(Scoring!$Z$29:$Z$361,MATCH($O41,Scoring!$AB$29:$AB$361,0))) -> 1 g powder vial | K41: =IF($O41="","",IF(INDEX(Scoring!$D$29:$D$361,MATCH($O41,Scoring!$AB$29:$AB$361,0))="",INDEX(Scoring!$AF$29:$AF$361,MATCH($O41,Scoring!$AB$29:$AB$361,0)),INDEX(Scoring!$D$29:$D$361,MATCH($O41,Scoring!$AB$29:$AB$361,0)))) -> 5.6 | L41: =IF($O41="","",INDEX(Scoring!$M$29:$M$361,MATCH($O41,Scoring!$AB$29:$AB$361,0))) -> 3110 | M41: =IF($O41="","",INDEX(Scoring!$F$29:$F$361,MATCH($O41,Scoring!$AB$29:$AB$361,0))) -> 93119.2 | N41: =IF($O41="","",INDEX(Scoring!$AI$29:$AI$361,MATCH($O41,Scoring!$AB$29:$AB$361,0))) -> EU/EEA (4): Germany, France, Italy, Portugal | O41: =IFERROR(SMALL(Scoring!$AB$29:$AB$361,37),"") -> 2007
A42: =IF($O42="","",INT($O42/1000)) -> 2 | B42: =IF($O42="","",INDEX(Scoring!$A$29:$A$361,MATCH($O42,Scoring!$AB$29:$AB$361,0))) -> Aurobindo | C42: =IF($O42="","",IF(INDEX(Scoring!$P$29:$P$361,MATCH($O42,Scoring!$AB$29:$AB$361,0))="","–",INDEX(Scoring!$P$29:$P$361,MATCH($O42,Scoring!$AB$29:$AB$361,0)))) -> 8 | D42: =IF($O42="","",INDEX(Scoring!$Q$29:$Q$361,MATCH($O42,Scoring!$AB$29:$AB$361,0))) -> Priority 2 | E42: =IF($O42="","",INDEX(Scoring!$AJ$29:$AJ$361,MATCH($O42,Scoring!$AB$29:$AB$361,0))) -> Lower price · high volume | F42: =IF($O42="","",INDEX(Scoring!$B$29:$B$361,MATCH($O42,Scoring!$AB$29:$AB$361,0))) -> Ampicillin | G42: =IF($O42="","",INDEX(Scoring!$AG$29:$AG$361,MATCH($O42,Scoring!$AB$29:$AB$361,0))) -> Ampicillin Sodium | H42: =IF($O42="","",INDEX(Scoring!$C$29:$C$361,MATCH($O42,Scoring!$AB$29:$AB$361,0))) -> Anti-infective: meningitis, endocarditis, neonatal sepsis | I42: =IF($O42="","",INDEX(Scoring!$I$29:$I$361,MATCH($O42,Scoring!$AB$29:$AB$361,0))) -> Vial | J42: =IF($O42="","",INDEX(Scoring!$Z$29:$Z$361,MATCH($O42,Scoring!$AB$29:$AB$361,0))) -> 2 g/20 mL vial | K42: =IF($O42="","",IF(INDEX(Scoring!$D$29:$D$361,MATCH($O42,Scoring!$AB$29:$AB$361,0))="",INDEX(Scoring!$AF$29:$AF$361,MATCH($O42,Scoring!$AB$29:$AB$361,0)),INDEX(Scoring!$D$29:$D$361,MATCH($O42,Scoring!$AB$29:$AB$361,0)))) -> 7.79 | L42: =IF($O42="","",INDEX(Scoring!$M$29:$M$361,MATCH($O42,Scoring!$AB$29:$AB$361,0))) -> 934 | M42: =IF($O42="","",INDEX(Scoring!$F$29:$F$361,MATCH($O42,Scoring!$AB$29:$AB$361,0))) -> 35129.8 | N42: =IF($O42="","",INDEX(Scoring!$AI$29:$AI$361,MATCH($O42,Scoring!$AB$29:$AB$361,0))) -> Canada | EU/EEA (1): Germany | O42: =IFERROR(SMALL(Scoring!$AB$29:$AB$361,38),"") -> 2008
A43: =IF($O43="","",INT($O43/1000)) -> 2 | B43: =IF($O43="","",INDEX(Scoring!$A$29:$A$361,MATCH($O43,Scoring!$AB$29:$AB$361,0))) -> Aurobindo | C43: =IF($O43="","",IF(INDEX(Scoring!$P$29:$P$361,MATCH($O43,Scoring!$AB$29:$AB$361,0))="","–",INDEX(Scoring!$P$29:$P$361,MATCH($O43,Scoring!$AB$29:$AB$361,0)))) -> 9 | D43: =IF($O43="","",INDEX(Scoring!$Q$29:$Q$361,MATCH($O43,Scoring!$AB$29:$AB$361,0))) -> Priority 2 | E43: =IF($O43="","",INDEX(Scoring!$AJ$29:$AJ$361,MATCH($O43,Scoring!$AB$29:$AB$361,0))) -> Lower price · high volume | F43: =IF($O43="","",INDEX(Scoring!$B$29:$B$361,MATCH($O43,Scoring!$AB$29:$AB$361,0))) -> Ondansetron | G43: =IF($O43="","",INDEX(Scoring!$AG$29:$AG$361,MATCH($O43,Scoring!$AB$29:$AB$361,0))) -> Ondansetron; Ondansetron Ab; Auro-Ondansetron (+1 more) | H43: =IF($O43="","",INDEX(Scoring!$C$29:$C$361,MATCH($O43,Scoring!$AB$29:$AB$361,0))) -> Oncology support: nausea and vomiting from chemotherapy and surgery | I43: =IF($O43="","",INDEX(Scoring!$I$29:$I$361,MATCH($O43,Scoring!$AB$29:$AB$361,0))) -> Vial, Ampoule | J43: =IF($O43="","",INDEX(Scoring!$Z$29:$Z$361,MATCH($O43,Scoring!$AB$29:$AB$361,0))) -> 2 mg/mL ampoule; 4 mg/2 mL ampoule; 4 mg/2 mL vial; 8 mg/4 mL vial | K43: =IF($O43="","",IF(INDEX(Scoring!$D$29:$D$361,MATCH($O43,Scoring!$AB$29:$AB$361,0))="",INDEX(Scoring!$AF$29:$AF$361,MATCH($O43,Scoring!$AB$29:$AB$361,0)),INDEX(Scoring!$D$29:$D$361,MATCH($O43,Scoring!$AB$29:$AB$361,0)))) -> 9.82 | L43: =IF($O43="","",INDEX(Scoring!$M$29:$M$361,MATCH($O43,Scoring!$AB$29:$AB$361,0))) -> 963 | M43: =IF($O43="","",INDEX(Scoring!$F$29:$F$361,MATCH($O43,Scoring!$AB$29:$AB$361,0))) -> 17590.5 | N43: =IF($O43="","",INDEX(Scoring!$AI$29:$AI$361,MATCH($O43,Scoring!$AB$29:$AB$361,0))) -> UK, Canada, UK-NI | EU/EEA (7): Germany, Belgium, Italy, Luxembourg + 3 more | O43: =IFERROR(SMALL(Scoring!$AB$29:$AB$361,39),"") -> 2009
A44: =IF($O44="","",INT($O44/1000)) -> 2 | B44: =IF($O44="","",INDEX(Scoring!$A$29:$A$361,MATCH($O44,Scoring!$AB$29:$AB$361,0))) -> Aurobindo | C44: =IF($O44="","",IF(INDEX(Scoring!$P$29:$P$361,MATCH($O44,Scoring!$AB$29:$AB$361,0))="","–",INDEX(Scoring!$P$29:$P$361,MATCH($O44,Scoring!$AB$29:$AB$361,0)))) -> 10 | D44: =IF($O44="","",INDEX(Scoring!$Q$29:$Q$361,MATCH($O44,Scoring!$AB$29:$AB$361,0))) -> Priority 2 | E44: =IF($O44="","",INDEX(Scoring!$AJ$29:$AJ$361,MATCH($O44,Scoring!$AB$29:$AB$361,0))) -> Lower price · high volume | F44: =IF($O44="","",INDEX(Scoring!$B$29:$B$361,MATCH($O44,Scoring!$AB$29:$AB$361,0))) -> Bupivacaine | G44: =IF($O44="","",INDEX(Scoring!$AG$29:$AG$361,MATCH($O44,Scoring!$AB$29:$AB$361,0))) -> Bupivan | H44: =IF($O44="","",INDEX(Scoring!$C$29:$C$361,MATCH($O44,Scoring!$AB$29:$AB$361,0))) -> Anaesthesia: long-acting local anaesthetic for spinal, epidural and nerve block | I44: =IF($O44="","",INDEX(Scoring!$I$29:$I$361,MATCH($O44,Scoring!$AB$29:$AB$361,0))) -> Ampoule | J44: =IF($O44="","",INDEX(Scoring!$Z$29:$Z$361,MATCH($O44,Scoring!$AB$29:$AB$361,0))) -> 25 mg/5 mL ampoule | K44: =IF($O44="","",IF(INDEX(Scoring!$D$29:$D$361,MATCH($O44,Scoring!$AB$29:$AB$361,0))="",INDEX(Scoring!$AF$29:$AF$361,MATCH($O44,Scoring!$AB$29:$AB$361,0)),INDEX(Scoring!$D$29:$D$361,MATCH($O44,Scoring!$AB$29:$AB$361,0)))) -> 5.15 | L44: =IF($O44="","",INDEX(Scoring!$M$29:$M$361,MATCH($O44,Scoring!$AB$29:$AB$361,0))) -> 581 | M44: =IF($O44="","",INDEX(Scoring!$F$29:$F$361,MATCH($O44,Scoring!$AB$29:$AB$361,0))) -> 16359.3 | N44: =IF($O44="","",INDEX(Scoring!$AI$29:$AI$361,MATCH($O44,Scoring!$AB$29:$AB$361,0))) -> UK-NI | EU/EEA (5): Germany, Netherlands, Italy, Portugal, Spain | O44: =IFERROR(SMALL(Scoring!$AB$29:$AB$361,40),"") -> 2010
A45: =IF($O45="","",INT($O45/1000)) -> 2 | B45: =IF($O45="","",INDEX(Scoring!$A$29:$A$361,MATCH($O45,Scoring!$AB$29:$AB$361,0))) -> Aurobindo | C45: =IF($O45="","",IF(INDEX(Scoring!$P$29:$P$361,MATCH($O45,Scoring!$AB$29:$AB$361,0))="","–",INDEX(Scoring!$P$29:$P$361,MATCH($O45,Scoring!$AB$29:$AB$361,0)))) -> 11 | D45: =IF($O45="","",INDEX(Scoring!$Q$29:$Q$361,MATCH($O45,Scoring!$AB$29:$AB$361,0))) -> Priority 2 | E45: =IF($O45="","",INDEX(Scoring!$AJ$29:$AJ$361,MATCH($O45,Scoring!$AB$29:$AB$361,0))) -> Lower price · high volume | F45: =IF($O45="","",INDEX(Scoring!$B$29:$B$361,MATCH($O45,Scoring!$AB$29:$AB$361,0))) -> Methotrexate | G45: =IF($O45="","",INDEX(Scoring!$AG$29:$AG$361,MATCH($O45,Scoring!$AB$29:$AB$361,0))) -> Methotrexate Sodium Preservative Free | H45: =IF($O45="","",INDEX(Scoring!$C$29:$C$361,MATCH($O45,Scoring!$AB$29:$AB$361,0))) -> Oncology and immunology: leukaemia, lymphoma, bone cancer, rheumatoid arthritis, psoriasis | I45: =IF($O45="","",INDEX(Scoring!$I$29:$I$361,MATCH($O45,Scoring!$AB$29:$AB$361,0))) -> Vial | J45: =IF($O45="","",INDEX(Scoring!$Z$29:$Z$361,MATCH($O45,Scoring!$AB$29:$AB$361,0))) -> 50 mg/2 mL vial; 200 mg/8 mL vial; 250 mg/10 mL vial | K45: =IF($O45="","",IF(INDEX(Scoring!$D$29:$D$361,MATCH($O45,Scoring!$AB$29:$AB$361,0))="",INDEX(Scoring!$AF$29:$AF$361,MATCH($O45,Scoring!$AB$29:$AB$361,0)),INDEX(Scoring!$D$29:$D$361,MATCH($O45,Scoring!$AB$29:$AB$361,0)))) -> 9.81 | L45: =IF($O45="","",INDEX(Scoring!$M$29:$M$361,MATCH($O45,Scoring!$AB$29:$AB$361,0))) -> 996 | M45: =IF($O45="","",INDEX(Scoring!$F$29:$F$361,MATCH($O45,Scoring!$AB$29:$AB$361,0))) -> 13045.6 | N45: =IF($O45="","",INDEX(Scoring!$AI$29:$AI$361,MATCH($O45,Scoring!$AB$29:$AB$361,0))) -> US | O45: =IFERROR(SMALL(Scoring!$AB$29:$AB$361,41),"") -> 2011
A46: =IF($O46="","",INT($O46/1000)) -> 2 | B46: =IF($O46="","",INDEX(Scoring!$A$29:$A$361,MATCH($O46,Scoring!$AB$29:$AB$361,0))) -> Aurobindo | C46: =IF($O46="","",IF(INDEX(Scoring!$P$29:$P$361,MATCH($O46,Scoring!$AB$29:$AB$361,0))="","–",INDEX(Scoring!$P$29:$P$361,MATCH($O46,Scoring!$AB$29:$AB$361,0)))) -> 12 | D46: =IF($O46="","",INDEX(Scoring!$Q$29:$Q$361,MATCH($O46,Scoring!$AB$29:$AB$361,0))) -> Priority 2 | E46: =IF($O46="","",INDEX(Scoring!$AJ$29:$AJ$361,MATCH($O46,Scoring!$AB$29:$AB$361,0))) -> High price · lower volume | F46: =IF($O46="","",INDEX(Scoring!$B$29:$B$361,MATCH($O46,Scoring!$AB$29:$AB$361,0))) -> Plerixafor | G46: =IF($O46="","",INDEX(Scoring!$AG$29:$AG$361,MATCH($O46,Scoring!$AB$29:$AB$361,0))) -> Plerixafor; Plerixafor Arrow; Plerixafor Eugia | H46: =IF($O46="","",INDEX(Scoring!$C$29:$C$361,MATCH($O46,Scoring!$AB$29:$AB$361,0))) -> Oncology support: stem cell mobilisation in myeloma and lymphoma | I46: =IF($O46="","",INDEX(Scoring!$I$29:$I$361,MATCH($O46,Scoring!$AB$29:$AB$361,0))) -> Vial | J46: =IF($O46="","",INDEX(Scoring!$Z$29:$Z$361,MATCH($O46,Scoring!$AB$29:$AB$361,0))) -> 24 mg/1.2 mL vial | K46: =IF($O46="","",IF(INDEX(Scoring!$D$29:$D$361,MATCH($O46,Scoring!$AB$29:$AB$361,0))="",INDEX(Scoring!$AF$29:$AF$361,MATCH($O46,Scoring!$AB$29:$AB$361,0)),INDEX(Scoring!$D$29:$D$361,MATCH($O46,Scoring!$AB$29:$AB$361,0)))) -> 3710.2 | L46: =IF($O46="","",INDEX(Scoring!$M$29:$M$361,MATCH($O46,Scoring!$AB$29:$AB$361,0))) -> 47 | M46: =IF($O46="","",INDEX(Scoring!$F$29:$F$361,MATCH($O46,Scoring!$AB$29:$AB$361,0))) -> 7904.7 | N46: =IF($O46="","",INDEX(Scoring!$AI$29:$AI$361,MATCH($O46,Scoring!$AB$29:$AB$361,0))) -> US, UK, Canada, Australia, UK-NI | EU/EEA (5): Germany, France, Italy, Portugal, Spain | O46: =IFERROR(SMALL(Scoring!$AB$29:$AB$361,42),"") -> 2012
A47: =IF($O47="","",INT($O47/1000)) -> 2 | B47: =IF($O47="","",INDEX(Scoring!$A$29:$A$361,MATCH($O47,Scoring!$AB$29:$AB$361,0))) -> Aurobindo | C47: =IF($O47="","",IF(INDEX(Scoring!$P$29:$P$361,MATCH($O47,Scoring!$AB$29:$AB$361,0))="","–",INDEX(Scoring!$P$29:$P$361,MATCH($O47,Scoring!$AB$29:$AB$361,0)))) -> 13 | D47: =IF($O47="","",INDEX(Scoring!$Q$29:$Q$361,MATCH($O47,Scoring!$AB$29:$AB$361,0))) -> Priority 2 | E47: =IF($O47="","",INDEX(Scoring!$AJ$29:$AJ$361,MATCH($O47,Scoring!$AB$29:$AB$361,0))) -> Lower price · high volume | F47: =IF($O47="","",INDEX(Scoring!$B$29:$B$361,MATCH($O47,Scoring!$AB$29:$AB$361,0))) -> Testosterone Cypionate | G47: =IF($O47="","",INDEX(Scoring!$AG$29:$AG$361,MATCH($O47,Scoring!$AB$29:$AB$361,0))) -> Testosterone Cypionate | H47: =IF($O47="","",INDEX(Scoring!$C$29:$C$361,MATCH($O47,Scoring!$AB$29:$AB$361,0))) -> Endocrinology: testosterone replacement in male hypogonadism | I47: =IF($O47="","",INDEX(Scoring!$I$29:$I$361,MATCH($O47,Scoring!$AB$29:$AB$361,0))) -> Vial | J47: =IF($O47="","",INDEX(Scoring!$Z$29:$Z$361,MATCH($O47,Scoring!$AB$29:$AB$361,0))) -> 1000 mg/10 mL vial; 200 mg/1 mL vial | K47: =IF($O47="","",IF(INDEX(Scoring!$D$29:$D$361,MATCH($O47,Scoring!$AB$29:$AB$361,0))="",INDEX(Scoring!$AF$29:$AF$361,MATCH($O47,Scoring!$AB$29:$AB$361,0)),INDEX(Scoring!$D$29:$D$361,MATCH($O47,Scoring!$AB$29:$AB$361,0)))) -> 20.63 | L47: =IF($O47="","",INDEX(Scoring!$M$29:$M$361,MATCH($O47,Scoring!$AB$29:$AB$361,0))) -> 291 | M47: =IF($O47="","",INDEX(Scoring!$F$29:$F$361,MATCH($O47,Scoring!$AB$29:$AB$361,0))) -> 6893.7 | N47: =IF($O47="","",INDEX(Scoring!$AI$29:$AI$361,MATCH($O47,Scoring!$AB$29:$AB$361,0))) -> US | O47: =IFERROR(SMALL(Scoring!$AB$29:$AB$361,43),"") -> 2013
A48: =IF($O48="","",INT($O48/1000)) -> 2 | B48: =IF($O48="","",INDEX(Scoring!$A$29:$A$361,MATCH($O48,Scoring!$AB$29:$AB$361,0))) -> Aurobindo | C48: =IF($O48="","",IF(INDEX(Scoring!$P$29:$P$361,MATCH($O48,Scoring!$AB$29:$AB$361,0))="","–",INDEX(Scoring!$P$29:$P$361,MATCH($O48,Scoring!$AB$29:$AB$361,0)))) -> 14 | D48: =IF($O48="","",INDEX(Scoring!$Q$29:$Q$361,MATCH($O48,Scoring!$AB$29:$AB$361,0))) -> Priority 2 | E48: =IF($O48="","",INDEX(Scoring!$AJ$29:$AJ$361,MATCH($O48,Scoring!$AB$29:$AB$361,0))) -> Lower price · high volume | F48: =IF($O48="","",INDEX(Scoring!$B$29:$B$361,MATCH($O48,Scoring!$AB$29:$AB$361,0))) -> Cefepime | G48: =IF($O48="","",INDEX(Scoring!$AG$29:$AG$361,MATCH($O48,Scoring!$AB$29:$AB$361,0))) -> Auro Cefepime | H48: =IF($O48="","",INDEX(Scoring!$C$29:$C$361,MATCH($O48,Scoring!$AB$29:$AB$361,0))) -> Anti-infective: hospital Gram-negative infections, febrile neutropenia | I48: =IF($O48="","",INDEX(Scoring!$I$29:$I$361,MATCH($O48,Scoring!$AB$29:$AB$361,0))) -> Vial | J48: =IF($O48="","",INDEX(Scoring!$Z$29:$Z$361,MATCH($O48,Scoring!$AB$29:$AB$361,0))) -> 1000 mg in 20 mL powder vial; 2000 mg in 50 mL powder vial | K48: =IF($O48="","",IF(INDEX(Scoring!$D$29:$D$361,MATCH($O48,Scoring!$AB$29:$AB$361,0))="",INDEX(Scoring!$AF$29:$AF$361,MATCH($O48,Scoring!$AB$29:$AB$361,0)),INDEX(Scoring!$D$29:$D$361,MATCH($O48,Scoring!$AB$29:$AB$361,0)))) -> 9.08 | L48: =IF($O48="","",INDEX(Scoring!$M$29:$M$361,MATCH($O48,Scoring!$AB$29:$AB$361,0))) -> 288 | M48: =IF($O48="","",INDEX(Scoring!$F$29:$F$361,MATCH($O48,Scoring!$AB$29:$AB$361,0))) -> 6294.9 | N48: =IF($O48="","",INDEX(Scoring!$AI$29:$AI$361,MATCH($O48,Scoring!$AB$29:$AB$361,0))) -> South Africa | O48: =IFERROR(SMALL(Scoring!$AB$29:$AB$361,44),"") -> 2014
A49: =IF($O49="","",INT($O49/1000)) -> 2 | B49: =IF($O49="","",INDEX(Scoring!$A$29:$A$361,MATCH($O49,Scoring!$AB$29:$AB$361,0))) -> Aurobindo | C49: =IF($O49="","",IF(INDEX(Scoring!$P$29:$P$361,MATCH($O49,Scoring!$AB$29:$AB$361,0))="","–",INDEX(Scoring!$P$29:$P$361,MATCH($O49,Scoring!$AB$29:$AB$361,0)))) -> 15 | D49: =IF($O49="","",INDEX(Scoring!$Q$29:$Q$361,MATCH($O49,Scoring!$AB$29:$AB$361,0))) -> Priority 2 | E49: =IF($O49="","",INDEX(Scoring!$AJ$29:$AJ$361,MATCH($O49,Scoring!$AB$29:$AB$361,0))) -> Lower price · high volume | F49: =IF($O49="","",INDEX(Scoring!$B$29:$B$361,MATCH($O49,Scoring!$AB$29:$AB$361,0))) -> Ceftazidime | G49: =IF($O49="","",INDEX(Scoring!$AG$29:$AG$361,MATCH($O49,Scoring!$AB$29:$AB$361,0))) -> Ceftazidime Arrow | H49: =IF($O49="","",INDEX(Scoring!$C$29:$C$361,MATCH($O49,Scoring!$AB$29:$AB$361,0))) -> Anti-infective: Pseudomonas and other hospital Gram-negative infections | I49: =IF($O49="","",INDEX(Scoring!$I$29:$I$361,MATCH($O49,Scoring!$AB$29:$AB$361,0))) -> Vial | J49: =IF($O49="","",INDEX(Scoring!$Z$29:$Z$361,MATCH($O49,Scoring!$AB$29:$AB$361,0))) -> 1 g powder vial | K49: =IF($O49="","",IF(INDEX(Scoring!$D$29:$D$361,MATCH($O49,Scoring!$AB$29:$AB$361,0))="",INDEX(Scoring!$AF$29:$AF$361,MATCH($O49,Scoring!$AB$29:$AB$361,0)),INDEX(Scoring!$D$29:$D$361,MATCH($O49,Scoring!$AB$29:$AB$361,0)))) -> 8.5 | L49: =IF($O49="","",INDEX(Scoring!$M$29:$M$361,MATCH($O49,Scoring!$AB$29:$AB$361,0))) -> 335 | M49: =IF($O49="","",INDEX(Scoring!$F$29:$F$361,MATCH($O49,Scoring!$AB$29:$AB$361,0))) -> 5713.6 | N49: =IF($O49="","",INDEX(Scoring!$AI$29:$AI$361,MATCH($O49,Scoring!$AB$29:$AB$361,0))) -> EU/EEA (1): France | O49: =IFERROR(SMALL(Scoring!$AB$29:$AB$361,45),"") -> 2015
A50: =IF($O50="","",INT($O50/1000)) -> 2 | B50: =IF($O50="","",INDEX(Scoring!$A$29:$A$361,MATCH($O50,Scoring!$AB$29:$AB$361,0))) -> Aurobindo | C50: =IF($O50="","",IF(INDEX(Scoring!$P$29:$P$361,MATCH($O50,Scoring!$AB$29:$AB$361,0))="","–",INDEX(Scoring!$P$29:$P$361,MATCH($O50,Scoring!$AB$29:$AB$361,0)))) -> 16 | D50: =IF($O50="","",INDEX(Scoring!$Q$29:$Q$361,MATCH($O50,Scoring!$AB$29:$AB$361,0))) -> Priority 2 | E50: =IF($O50="","",INDEX(Scoring!$AJ$29:$AJ$361,MATCH($O50,Scoring!$AB$29:$AB$361,0))) -> High price · lower volume | F50: =IF($O50="","",INDEX(Scoring!$B$29:$B$361,MATCH($O50,Scoring!$AB$29:$AB$361,0))) -> Carboprost | G50: =IF($O50="","",INDEX(Scoring!$AG$29:$AG$361,MATCH($O50,Scoring!$AB$29:$AB$361,0))) -> Carboprost Tromethamine | H50: =IF($O50="","",INDEX(Scoring!$C$29:$C$361,MATCH($O50,Scoring!$AB$29:$AB$361,0))) -> Women's health: postpartum haemorrhage, pregnancy termination | I50: =IF($O50="","",INDEX(Scoring!$I$29:$I$361,MATCH($O50,Scoring!$AB$29:$AB$361,0))) -> Vial | J50: =IF($O50="","",INDEX(Scoring!$Z$29:$Z$361,MATCH($O50,Scoring!$AB$29:$AB$361,0))) -> 0.25 mg/1 mL vial | K50: =IF($O50="","",IF(INDEX(Scoring!$D$29:$D$361,MATCH($O50,Scoring!$AB$29:$AB$361,0))="",INDEX(Scoring!$AF$29:$AF$361,MATCH($O50,Scoring!$AB$29:$AB$361,0)),INDEX(Scoring!$D$29:$D$361,MATCH($O50,Scoring!$AB$29:$AB$361,0)))) -> 30.01 | L50: =IF($O50="","",INDEX(Scoring!$M$29:$M$361,MATCH($O50,Scoring!$AB$29:$AB$361,0))) -> 143 | M50: =IF($O50="","",INDEX(Scoring!$F$29:$F$361,MATCH($O50,Scoring!$AB$29:$AB$361,0))) -> 3625.3 | N50: =IF($O50="","",INDEX(Scoring!$AI$29:$AI$361,MATCH($O50,Scoring!$AB$29:$AB$361,0))) -> US | O50: =IFERROR(SMALL(Scoring!$AB$29:$AB$361,46),"") -> 2016
A51: =IF($O51="","",INT($O51/1000)) -> 2 | B51: =IF($O51="","",INDEX(Scoring!$A$29:$A$361,MATCH($O51,Scoring!$AB$29:$AB$361,0))) -> Aurobindo | C51: =IF($O51="","",IF(INDEX(Scoring!$P$29:$P$361,MATCH($O51,Scoring!$AB$29:$AB$361,0))="","–",INDEX(Scoring!$P$29:$P$361,MATCH($O51,Scoring!$AB$29:$AB$361,0)))) -> 17 | D51: =IF($O51="","",INDEX(Scoring!$Q$29:$Q$361,MATCH($O51,Scoring!$AB$29:$AB$361,0))) -> Priority 2 | E51: =IF($O51="","",INDEX(Scoring!$AJ$29:$AJ$361,MATCH($O51,Scoring!$AB$29:$AB$361,0))) -> High price · lower volume | F51: =IF($O51="","",INDEX(Scoring!$B$29:$B$361,MATCH($O51,Scoring!$AB$29:$AB$361,0))) -> Fluphenazine Decanoate | G51: =IF($O51="","",INDEX(Scoring!$AG$29:$AG$361,MATCH($O51,Scoring!$AB$29:$AB$361,0))) -> Fluphenazine Decanoate | H51: =IF($O51="","",INDEX(Scoring!$C$29:$C$361,MATCH($O51,Scoring!$AB$29:$AB$361,0))) -> Psychiatry: long-acting maintenance treatment for schizophrenia | I51: =IF($O51="","",INDEX(Scoring!$I$29:$I$361,MATCH($O51,Scoring!$AB$29:$AB$361,0))) -> Vial | J51: =IF($O51="","",INDEX(Scoring!$Z$29:$Z$361,MATCH($O51,Scoring!$AB$29:$AB$361,0))) -> 125 mg/5 mL vial | K51: =IF($O51="","",IF(INDEX(Scoring!$D$29:$D$361,MATCH($O51,Scoring!$AB$29:$AB$361,0))="",INDEX(Scoring!$AF$29:$AF$361,MATCH($O51,Scoring!$AB$29:$AB$361,0)),INDEX(Scoring!$D$29:$D$361,MATCH($O51,Scoring!$AB$29:$AB$361,0)))) -> 54.55 | L51: =IF($O51="","",INDEX(Scoring!$M$29:$M$361,MATCH($O51,Scoring!$AB$29:$AB$361,0))) -> 126 | M51: =IF($O51="","",INDEX(Scoring!$F$29:$F$361,MATCH($O51,Scoring!$AB$29:$AB$361,0))) -> 3407.5 | N51: =IF($O51="","",INDEX(Scoring!$AI$29:$AI$361,MATCH($O51,Scoring!$AB$29:$AB$361,0))) -> US | O51: =IFERROR(SMALL(Scoring!$AB$29:$AB$361,47),"") -> 2017
A52: =IF($O52="","",INT($O52/1000)) -> 2 | B52: =IF($O52="","",INDEX(Scoring!$A$29:$A$361,MATCH($O52,Scoring!$AB$29:$AB$361,0))) -> Aurobindo | C52: =IF($O52="","",IF(INDEX(Scoring!$P$29:$P$361,MATCH($O52,Scoring!$AB$29:$AB$361,0))="","–",INDEX(Scoring!$P$29:$P$361,MATCH($O52,Scoring!$AB$29:$AB$361,0)))) -> 18 | D52: =IF($O52="","",INDEX(Scoring!$Q$29:$Q$361,MATCH($O52,Scoring!$AB$29:$AB$361,0))) -> Priority 2 | E52: =IF($O52="","",INDEX(Scoring!$AJ$29:$AJ$361,MATCH($O52,Scoring!$AB$29:$AB$361,0))) -> High price · lower volume | F52: =IF($O52="","",INDEX(Scoring!$B$29:$B$361,MATCH($O52,Scoring!$AB$29:$AB$361,0))) -> Medroxyprogesterone Acetate | G52: =IF($O52="","",INDEX(Scoring!$AG$29:$AG$361,MATCH($O52,Scoring!$AB$29:$AB$361,0))) -> Medroxyprogesterone Acetate | H52: =IF($O52="","",INDEX(Scoring!$C$29:$C$361,MATCH($O52,Scoring!$AB$29:$AB$361,0))) -> Women's health: three-monthly contraceptive injection | I52: =IF($O52="","",INDEX(Scoring!$I$29:$I$361,MATCH($O52,Scoring!$AB$29:$AB$361,0))) -> Vial, Prefilled syringe | J52: =IF($O52="","",INDEX(Scoring!$Z$29:$Z$361,MATCH($O52,Scoring!$AB$29:$AB$361,0))) -> 150 mg/1 mL vial; 150 mg/1 mL pre-filled syringe | K52: =IF($O52="","",IF(INDEX(Scoring!$D$29:$D$361,MATCH($O52,Scoring!$AB$29:$AB$361,0))="",INDEX(Scoring!$AF$29:$AF$361,MATCH($O52,Scoring!$AB$29:$AB$361,0)),INDEX(Scoring!$D$29:$D$361,MATCH($O52,Scoring!$AB$29:$AB$361,0)))) -> 35.26 | L52: =IF($O52="","",INDEX(Scoring!$M$29:$M$361,MATCH($O52,Scoring!$AB$29:$AB$361,0))) -> 41 | M52: =IF($O52="","",INDEX(Scoring!$F$29:$F$361,MATCH($O52,Scoring!$AB$29:$AB$361,0))) -> 2690.1 | N52: =IF($O52="","",INDEX(Scoring!$AI$29:$AI$361,MATCH($O52,Scoring!$AB$29:$AB$361,0))) -> US | O52: =IFERROR(SMALL(Scoring!$AB$29:$AB$361,48),"") -> 2018
A53: =IF($O53="","",INT($O53/1000)) -> 2 | B53: =IF($O53="","",INDEX(Scoring!$A$29:$A$361,MATCH($O53,Scoring!$AB$29:$AB$361,0))) -> Aurobindo | C53: =IF($O53="","",IF(INDEX(Scoring!$P$29:$P$361,MATCH($O53,Scoring!$AB$29:$AB$361,0))="","–",INDEX(Scoring!$P$29:$P$361,MATCH($O53,Scoring!$AB$29:$AB$361,0)))) -> 19 | D53: =IF($O53="","",INDEX(Scoring!$Q$29:$Q$361,MATCH($O53,Scoring!$AB$29:$AB$361,0))) -> Priority 2 | E53: =IF($O53="","",INDEX(Scoring!$AJ$29:$AJ$361,MATCH($O53,Scoring!$AB$29:$AB$361,0))) -> High price · lower volume | F53: =IF($O53="","",INDEX(Scoring!$B$29:$B$361,MATCH($O53,Scoring!$AB$29:$AB$361,0))) -> Naloxone | G53: =IF($O53="","",INDEX(Scoring!$AG$29:$AG$361,MATCH($O53,Scoring!$AB$29:$AB$361,0))) -> Naloxone Hydrochloride | H53: =IF($O53="","",INDEX(Scoring!$C$29:$C$361,MATCH($O53,Scoring!$AB$29:$AB$361,0))) -> Critical care: reversal of opioid overdose | I53: =IF($O53="","",INDEX(Scoring!$I$29:$I$361,MATCH($O53,Scoring!$AB$29:$AB$361,0))) -> Vial, Prefilled syringe | J53: =IF($O53="","",INDEX(Scoring!$Z$29:$Z$361,MATCH($O53,Scoring!$AB$29:$AB$361,0))) -> 2 mg/2 mL pre-filled syringe; 0.4 mg/1 mL vial; 4 mg/10 mL vial | K53: =IF($O53="","",IF(INDEX(Scoring!$D$29:$D$361,MATCH($O53,Scoring!$AB$29:$AB$361,0))="",INDEX(Scoring!$AF$29:$AF$361,MATCH($O53,Scoring!$AB$29:$AB$361,0)),INDEX(Scoring!$D$29:$D$361,MATCH($O53,Scoring!$AB$29:$AB$361,0)))) -> 51.32 | L53: =IF($O53="","",INDEX(Scoring!$M$29:$M$361,MATCH($O53,Scoring!$AB$29:$AB$361,0))) -> 88 | M53: =IF($O53="","",INDEX(Scoring!$F$29:$F$361,MATCH($O53,Scoring!$AB$29:$AB$361,0))) -> 1437.9 | N53: =IF($O53="","",INDEX(Scoring!$AI$29:$AI$361,MATCH($O53,Scoring!$AB$29:$AB$361,0))) -> US, Canada | O53: =IFERROR(SMALL(Scoring!$AB$29:$AB$361,49),"") -> 2019
A54: =IF($O54="","",INT($O54/1000)) -> 2 | B54: =IF($O54="","",INDEX(Scoring!$A$29:$A$361,MATCH($O54,Scoring!$AB$29:$AB$361,0))) -> Aurobindo | C54: =IF($O54="","",IF(INDEX(Scoring!$P$29:$P$361,MATCH($O54,Scoring!$AB$29:$AB$361,0))="","–",INDEX(Scoring!$P$29:$P$361,MATCH($O54,Scoring!$AB$29:$AB$361,0)))) -> 20 | D54: =IF($O54="","",INDEX(Scoring!$Q$29:$Q$361,MATCH($O54,Scoring!$AB$29:$AB$361,0))) -> Priority 3 | E54: =IF($O54="","",INDEX(Scoring!$AJ$29:$AJ$361,MATCH($O54,Scoring!$AB$29:$AB$361,0))) -> Lower price · lower volume | F54: =IF($O54="","",INDEX(Scoring!$B$29:$B$361,MATCH($O54,Scoring!$AB$29:$AB$361,0))) -> Methylprednisolone Acetate | G54: =IF($O54="","",INDEX(Scoring!$AG$29:$AG$361,MATCH($O54,Scoring!$AB$29:$AB$361,0))) -> Methylprednisolone Acetate | H54: =IF($O54="","",INDEX(Scoring!$C$29:$C$361,MATCH($O54,Scoring!$AB$29:$AB$361,0))) -> Musculoskeletal and immunology: joint injections for arthritis and bursitis, inflammatory conditions | I54: =IF($O54="","",INDEX(Scoring!$I$29:$I$361,MATCH($O54,Scoring!$AB$29:$AB$361,0))) -> Vial | J54: =IF($O54="","",INDEX(Scoring!$Z$29:$Z$361,MATCH($O54,Scoring!$AB$29:$AB$361,0))) -> 40 mg/mL powder vial; 80 mg/mL powder vial | K54: =IF($O54="","",IF(INDEX(Scoring!$D$29:$D$361,MATCH($O54,Scoring!$AB$29:$AB$361,0))="",INDEX(Scoring!$AF$29:$AF$361,MATCH($O54,Scoring!$AB$29:$AB$361,0)),INDEX(Scoring!$D$29:$D$361,MATCH($O54,Scoring!$AB$29:$AB$361,0)))) -> 9.84 | L54: =IF($O54="","",INDEX(Scoring!$M$29:$M$361,MATCH($O54,Scoring!$AB$29:$AB$361,0))) -> 81 | M54: =IF($O54="","",INDEX(Scoring!$F$29:$F$361,MATCH($O54,Scoring!$AB$29:$AB$361,0))) -> 4745.9 | N54: =IF($O54="","",INDEX(Scoring!$AI$29:$AI$361,MATCH($O54,Scoring!$AB$29:$AB$361,0))) -> US | O54: =IFERROR(SMALL(Scoring!$AB$29:$AB$361,50),"") -> 2020
A55: =IF($O55="","",INT($O55/1000)) -> 2 | B55: =IF($O55="","",INDEX(Scoring!$A$29:$A$361,MATCH($O55,Scoring!$AB$29:$AB$361,0))) -> Aurobindo | C55: =IF($O55="","",IF(INDEX(Scoring!$P$29:$P$361,MATCH($O55,Scoring!$AB$29:$AB$361,0))="","–",INDEX(Scoring!$P$29:$P$361,MATCH($O55,Scoring!$AB$29:$AB$361,0)))) -> 21 | D55: =IF($O55="","",INDEX(Scoring!$Q$29:$Q$361,MATCH($O55,Scoring!$AB$29:$AB$361,0))) -> Priority 3 | E55: =IF($O55="","",INDEX(Scoring!$AJ$29:$AJ$361,MATCH($O55,Scoring!$AB$29:$AB$361,0))) -> Lower price · lower volume | F55: =IF($O55="","",INDEX(Scoring!$B$29:$B$361,MATCH($O55,Scoring!$AB$29:$AB$361,0))) -> Hydralazine | G55: =IF($O55="","",INDEX(Scoring!$AG$29:$AG$361,MATCH($O55,Scoring!$AB$29:$AB$361,0))) -> Hydralazine Hydrochloride | H55: =IF($O55="","",INDEX(Scoring!$C$29:$C$361,MATCH($O55,Scoring!$AB$29:$AB$361,0))) -> Cardiovascular: severe high blood pressure in pregnancy, hypertensive emergency | I55: =IF($O55="","",INDEX(Scoring!$I$29:$I$361,MATCH($O55,Scoring!$AB$29:$AB$361,0))) -> Vial | J55: =IF($O55="","",INDEX(Scoring!$Z$29:$Z$361,MATCH($O55,Scoring!$AB$29:$AB$361,0))) -> 20 mg/1 mL vial | K55: =IF($O55="","",IF(INDEX(Scoring!$D$29:$D$361,MATCH($O55,Scoring!$AB$29:$AB$361,0))="",INDEX(Scoring!$AF$29:$AF$361,MATCH($O55,Scoring!$AB$29:$AB$361,0)),INDEX(Scoring!$D$29:$D$361,MATCH($O55,Scoring!$AB$29:$AB$361,0)))) -> 7.36 | L55: =IF($O55="","",INDEX(Scoring!$M$29:$M$361,MATCH($O55,Scoring!$AB$29:$AB$361,0))) -> 82 | M55: =IF($O55="","",INDEX(Scoring!$F$29:$F$361,MATCH($O55,Scoring!$AB$29:$AB$361,0))) -> 3519.3 | N55: =IF($O55="","",INDEX(Scoring!$AI$29:$AI$361,MATCH($O55,Scoring!$AB$29:$AB$361,0))) -> Canada | O55: =IFERROR(SMALL(Scoring!$AB$29:$AB$361,51),"") -> 2021
A56: =IF($O56="","",INT($O56/1000)) -> 2 | B56: =IF($O56="","",INDEX(Scoring!$A$29:$A$361,MATCH($O56,Scoring!$AB$29:$AB$361,0))) -> Aurobindo | C56: =IF($O56="","",IF(INDEX(Scoring!$P$29:$P$361,MATCH($O56,Scoring!$AB$29:$AB$361,0))="","–",INDEX(Scoring!$P$29:$P$361,MATCH($O56,Scoring!$AB$29:$AB$361,0)))) -> 22 | D56: =IF($O56="","",INDEX(Scoring!$Q$29:$Q$361,MATCH($O56,Scoring!$AB$29:$AB$361,0))) -> Priority 3 | E56: =IF($O56="","",INDEX(Scoring!$AJ$29:$AJ$361,MATCH($O56,Scoring!$AB$29:$AB$361,0))) -> Lower price · lower volume | F56: =IF($O56="","",INDEX(Scoring!$B$29:$B$361,MATCH($O56,Scoring!$AB$29:$AB$361,0))) -> Ephedrine | G56: =IF($O56="","",INDEX(Scoring!$AG$29:$AG$361,MATCH($O56,Scoring!$AB$29:$AB$361,0))) -> Ephedrine Sulfate | H56: =IF($O56="","",INDEX(Scoring!$C$29:$C$361,MATCH($O56,Scoring!$AB$29:$AB$361,0))) -> Anaesthesia: low blood pressure during spinal anaesthesia and caesarean section | I56: =IF($O56="","",INDEX(Scoring!$I$29:$I$361,MATCH($O56,Scoring!$AB$29:$AB$361,0))) -> Vial | J56: =IF($O56="","",INDEX(Scoring!$Z$29:$Z$361,MATCH($O56,Scoring!$AB$29:$AB$361,0))) -> 50 mg/1 mL vial | K56: =IF($O56="","",IF(INDEX(Scoring!$D$29:$D$361,MATCH($O56,Scoring!$AB$29:$AB$361,0))="",INDEX(Scoring!$AF$29:$AF$361,MATCH($O56,Scoring!$AB$29:$AB$361,0)),INDEX(Scoring!$D$29:$D$361,MATCH($O56,Scoring!$AB$29:$AB$361,0)))) -> 5.35 | L56: =IF($O56="","",INDEX(Scoring!$M$29:$M$361,MATCH($O56,Scoring!$AB$29:$AB$361,0))) -> 49 | M56: =IF($O56="","",INDEX(Scoring!$F$29:$F$361,MATCH($O56,Scoring!$AB$29:$AB$361,0))) -> 2937.3 | N56: =IF($O56="","",INDEX(Scoring!$AI$29:$AI$361,MATCH($O56,Scoring!$AB$29:$AB$361,0))) -> US | EU/EEA (1): France | O56: =IFERROR(SMALL(Scoring!$AB$29:$AB$361,52),"") -> 2022
A57: =IF($O57="","",INT($O57/1000)) -> 2 | B57: =IF($O57="","",INDEX(Scoring!$A$29:$A$361,MATCH($O57,Scoring!$AB$29:$AB$361,0))) -> Aurobindo | C57: =IF($O57="","",IF(INDEX(Scoring!$P$29:$P$361,MATCH($O57,Scoring!$AB$29:$AB$361,0))="","–",INDEX(Scoring!$P$29:$P$361,MATCH($O57,Scoring!$AB$29:$AB$361,0)))) -> 23 | D57: =IF($O57="","",INDEX(Scoring!$Q$29:$Q$361,MATCH($O57,Scoring!$AB$29:$AB$361,0))) -> Priority 3 | E57: =IF($O57="","",INDEX(Scoring!$AJ$29:$AJ$361,MATCH($O57,Scoring!$AB$29:$AB$361,0))) -> Lower price · lower volume | F57: =IF($O57="","",INDEX(Scoring!$B$29:$B$361,MATCH($O57,Scoring!$AB$29:$AB$361,0))) -> Progesterone | G57: =IF($O57="","",INDEX(Scoring!$AG$29:$AG$361,MATCH($O57,Scoring!$AB$29:$AB$361,0))) -> Progesterone | H57: =IF($O57="","",INDEX(Scoring!$C$29:$C$361,MATCH($O57,Scoring!$AB$29:$AB$361,0))) -> Women's health: IVF support, absent periods, abnormal uterine bleeding | I57: =IF($O57="","",INDEX(Scoring!$I$29:$I$361,MATCH($O57,Scoring!$AB$29:$AB$361,0))) -> Vial | J57: =IF($O57="","",INDEX(Scoring!$Z$29:$Z$361,MATCH($O57,Scoring!$AB$29:$AB$361,0))) -> 500 mg/10 mL vial | K57: =IF($O57="","",IF(INDEX(Scoring!$D$29:$D$361,MATCH($O57,Scoring!$AB$29:$AB$361,0))="",INDEX(Scoring!$AF$29:$AF$361,MATCH($O57,Scoring!$AB$29:$AB$361,0)),INDEX(Scoring!$D$29:$D$361,MATCH($O57,Scoring!$AB$29:$AB$361,0)))) -> 22.25 | L57: =IF($O57="","",INDEX(Scoring!$M$29:$M$361,MATCH($O57,Scoring!$AB$29:$AB$361,0))) -> 88 | M57: =IF($O57="","",INDEX(Scoring!$F$29:$F$361,MATCH($O57,Scoring!$AB$29:$AB$361,0))) -> 2646.6 | N57: =IF($O57="","",INDEX(Scoring!$AI$29:$AI$361,MATCH($O57,Scoring!$AB$29:$AB$361,0))) -> US | O57: =IFERROR(SMALL(Scoring!$AB$29:$AB$361,53),"") -> 2023
A58: =IF($O58="","",INT($O58/1000)) -> 2 | B58: =IF($O58="","",INDEX(Scoring!$A$29:$A$361,MATCH($O58,Scoring!$AB$29:$AB$361,0))) -> Aurobindo | C58: =IF($O58="","",IF(INDEX(Scoring!$P$29:$P$361,MATCH($O58,Scoring!$AB$29:$AB$361,0))="","–",INDEX(Scoring!$P$29:$P$361,MATCH($O58,Scoring!$AB$29:$AB$361,0)))) -> 24 | D58: =IF($O58="","",INDEX(Scoring!$Q$29:$Q$361,MATCH($O58,Scoring!$AB$29:$AB$361,0))) -> Priority 3 | E58: =IF($O58="","",INDEX(Scoring!$AJ$29:$AJ$361,MATCH($O58,Scoring!$AB$29:$AB$361,0))) -> Lower price · lower volume | F58: =IF($O58="","",INDEX(Scoring!$B$29:$B$361,MATCH($O58,Scoring!$AB$29:$AB$361,0))) -> Chlorpromazine | G58: =IF($O58="","",INDEX(Scoring!$AG$29:$AG$361,MATCH($O58,Scoring!$AB$29:$AB$361,0))) -> Chlorpromazine Hydrochloride | H58: =IF($O58="","",INDEX(Scoring!$C$29:$C$361,MATCH($O58,Scoring!$AB$29:$AB$361,0))) -> Psychiatry: acute psychosis and agitation, severe nausea and vomiting | I58: =IF($O58="","",INDEX(Scoring!$I$29:$I$361,MATCH($O58,Scoring!$AB$29:$AB$361,0))) -> Ampoule | J58: =IF($O58="","",INDEX(Scoring!$Z$29:$Z$361,MATCH($O58,Scoring!$AB$29:$AB$361,0))) -> 25 mg/1 mL ampoule | K58: =IF($O58="","",IF(INDEX(Scoring!$D$29:$D$361,MATCH($O58,Scoring!$AB$29:$AB$361,0))="",INDEX(Scoring!$AF$29:$AF$361,MATCH($O58,Scoring!$AB$29:$AB$361,0)),INDEX(Scoring!$D$29:$D$361,MATCH($O58,Scoring!$AB$29:$AB$361,0)))) -> 14.96 | L58: =IF($O58="","",INDEX(Scoring!$M$29:$M$361,MATCH($O58,Scoring!$AB$29:$AB$361,0))) -> 82 | M58: =IF($O58="","",INDEX(Scoring!$F$29:$F$361,MATCH($O58,Scoring!$AB$29:$AB$361,0))) -> 1358.2 | N58: =IF($O58="","",INDEX(Scoring!$AI$29:$AI$361,MATCH($O58,Scoring!$AB$29:$AB$361,0))) -> US | O58: =IFERROR(SMALL(Scoring!$AB$29:$AB$361,54),"") -> 2024
A59: =IF($O59="","",INT($O59/1000)) -> 2 | B59: =IF($O59="","",INDEX(Scoring!$A$29:$A$361,MATCH($O59,Scoring!$AB$29:$AB$361,0))) -> Aurobindo | C59: =IF($O59="","",IF(INDEX(Scoring!$P$29:$P$361,MATCH($O59,Scoring!$AB$29:$AB$361,0))="","–",INDEX(Scoring!$P$29:$P$361,MATCH($O59,Scoring!$AB$29:$AB$361,0)))) -> 25 | D59: =IF($O59="","",INDEX(Scoring!$Q$29:$Q$361,MATCH($O59,Scoring!$AB$29:$AB$361,0))) -> Priority 3 | E59: =IF($O59="","",INDEX(Scoring!$AJ$29:$AJ$361,MATCH($O59,Scoring!$AB$29:$AB$361,0))) -> Lower price · lower volume | F59: =IF($O59="","",INDEX(Scoring!$B$29:$B$361,MATCH($O59,Scoring!$AB$29:$AB$361,0))) -> Nafcillin | G59: =IF($O59="","",INDEX(Scoring!$AG$29:$AG$361,MATCH($O59,Scoring!$AB$29:$AB$361,0))) -> Nafcillin Sodium | H59: =IF($O59="","",INDEX(Scoring!$C$29:$C$361,MATCH($O59,Scoring!$AB$29:$AB$361,0))) -> Anti-infective: staphylococcal infections | I59: =IF($O59="","",INDEX(Scoring!$I$29:$I$361,MATCH($O59,Scoring!$AB$29:$AB$361,0))) -> Vial | J59: =IF($O59="","",INDEX(Scoring!$Z$29:$Z$361,MATCH($O59,Scoring!$AB$29:$AB$361,0))) -> 1 g powder vial; 2 g powder vial | K59: =IF($O59="","",IF(INDEX(Scoring!$D$29:$D$361,MATCH($O59,Scoring!$AB$29:$AB$361,0))="",INDEX(Scoring!$AF$29:$AF$361,MATCH($O59,Scoring!$AB$29:$AB$361,0)),INDEX(Scoring!$D$29:$D$361,MATCH($O59,Scoring!$AB$29:$AB$361,0)))) -> 7.41 | L59: =IF($O59="","",INDEX(Scoring!$M$29:$M$361,MATCH($O59,Scoring!$AB$29:$AB$361,0))) -> 4 | M59: =IF($O59="","",INDEX(Scoring!$F$29:$F$361,MATCH($O59,Scoring!$AB$29:$AB$361,0))) -> 570.1 | N59: =IF($O59="","",INDEX(Scoring!$AI$29:$AI$361,MATCH($O59,Scoring!$AB$29:$AB$361,0))) -> US | O59: =IFERROR(SMALL(Scoring!$AB$29:$AB$361,55),"") -> 2025
A60: =IF($O60="","",INT($O60/1000)) -> 2 | B60: =IF($O60="","",INDEX(Scoring!$A$29:$A$361,MATCH($O60,Scoring!$AB$29:$AB$361,0))) -> Aurobindo | C60: =IF($O60="","",IF(INDEX(Scoring!$P$29:$P$361,MATCH($O60,Scoring!$AB$29:$AB$361,0))="","–",INDEX(Scoring!$P$29:$P$361,MATCH($O60,Scoring!$AB$29:$AB$361,0)))) -> 26 | D60: =IF($O60="","",INDEX(Scoring!$Q$29:$Q$361,MATCH($O60,Scoring!$AB$29:$AB$361,0))) -> Priority 3 | E60: =IF($O60="","",INDEX(Scoring!$AJ$29:$AJ$361,MATCH($O60,Scoring!$AB$29:$AB$361,0))) -> Lower price · lower volume | F60: =IF($O60="","",INDEX(Scoring!$B$29:$B$361,MATCH($O60,Scoring!$AB$29:$AB$361,0))) -> Oxacillin | G60: =IF($O60="","",INDEX(Scoring!$AG$29:$AG$361,MATCH($O60,Scoring!$AB$29:$AB$361,0))) -> Oxacillin Sodium | H60: =IF($O60="","",INDEX(Scoring!$C$29:$C$361,MATCH($O60,Scoring!$AB$29:$AB$361,0))) -> Anti-infective: staphylococcal infections | I60: =IF($O60="","",INDEX(Scoring!$I$29:$I$361,MATCH($O60,Scoring!$AB$29:$AB$361,0))) -> Vial | J60: =IF($O60="","",INDEX(Scoring!$Z$29:$Z$361,MATCH($O60,Scoring!$AB$29:$AB$361,0))) -> 1 g powder vial | K60: =IF($O60="","",IF(INDEX(Scoring!$D$29:$D$361,MATCH($O60,Scoring!$AB$29:$AB$361,0))="",INDEX(Scoring!$AF$29:$AF$361,MATCH($O60,Scoring!$AB$29:$AB$361,0)),INDEX(Scoring!$D$29:$D$361,MATCH($O60,Scoring!$AB$29:$AB$361,0)))) -> 10.93 | L60: =IF($O60="","",INDEX(Scoring!$M$29:$M$361,MATCH($O60,Scoring!$AB$29:$AB$361,0))) -> 9 | M60: =IF($O60="","",INDEX(Scoring!$F$29:$F$361,MATCH($O60,Scoring!$AB$29:$AB$361,0))) -> 260.9 | N60: =IF($O60="","",INDEX(Scoring!$AI$29:$AI$361,MATCH($O60,Scoring!$AB$29:$AB$361,0))) -> US | O60: =IFERROR(SMALL(Scoring!$AB$29:$AB$361,56),"") -> 2026
A61: =IF($O61="","",INT($O61/1000)) -> 2 | B61: =IF($O61="","",INDEX(Scoring!$A$29:$A$361,MATCH($O61,Scoring!$AB$29:$AB$361,0))) -> Aurobindo | C61: =IF($O61="","",IF(INDEX(Scoring!$P$29:$P$361,MATCH($O61,Scoring!$AB$29:$AB$361,0))="","–",INDEX(Scoring!$P$29:$P$361,MATCH($O61,Scoring!$AB$29:$AB$361,0)))) -> – | D61: =IF($O61="","",INDEX(Scoring!$Q$29:$Q$361,MATCH($O61,Scoring!$AB$29:$AB$361,0))) -> Excluded – price ≤ $5 | E61: =IF($O61="","",INDEX(Scoring!$AJ$29:$AJ$361,MATCH($O61,Scoring!$AB$29:$AB$361,0))) | F61: =IF($O61="","",INDEX(Scoring!$B$29:$B$361,MATCH($O61,Scoring!$AB$29:$AB$361,0))) -> Flucloxacillin | G61: =IF($O61="","",INDEX(Scoring!$AG$29:$AG$361,MATCH($O61,Scoring!$AB$29:$AB$361,0))) -> EUG-Flucloxacillin | H61: =IF($O61="","",INDEX(Scoring!$C$29:$C$361,MATCH($O61,Scoring!$AB$29:$AB$361,0))) -> Anti-infective: staphylococcal skin, bone and heart infections | I61: =IF($O61="","",INDEX(Scoring!$I$29:$I$361,MATCH($O61,Scoring!$AB$29:$AB$361,0))) -> Vial | J61: =IF($O61="","",INDEX(Scoring!$Z$29:$Z$361,MATCH($O61,Scoring!$AB$29:$AB$361,0))) -> 500 mg powder vial; 1000 mg powder vial; 2000 mg powder vial | K61: =IF($O61="","",IF(INDEX(Scoring!$D$29:$D$361,MATCH($O61,Scoring!$AB$29:$AB$361,0))="",INDEX(Scoring!$AF$29:$AF$361,MATCH($O61,Scoring!$AB$29:$AB$361,0)),INDEX(Scoring!$D$29:$D$361,MATCH($O61,Scoring!$AB$29:$AB$361,0)))) -> 3.32 | L61: =IF($O61="","",INDEX(Scoring!$M$29:$M$361,MATCH($O61,Scoring!$AB$29:$AB$361,0))) -> 116 | M61: =IF($O61="","",INDEX(Scoring!$F$29:$F$361,MATCH($O61,Scoring!$AB$29:$AB$361,0))) -> 6287.6 | N61: =IF($O61="","",INDEX(Scoring!$AI$29:$AI$361,MATCH($O61,Scoring!$AB$29:$AB$361,0))) -> Australia, UK-NI | EU/EEA (6): Germany, France, Netherlands, Belgium, Luxembourg, Portugal | O61: =IFERROR(SMALL(Scoring!$AB$29:$AB$361,57),"") -> 2901
A62: =IF($O62="","",INT($O62/1000)) -> 2 | B62: =IF($O62="","",INDEX(Scoring!$A$29:$A$361,MATCH($O62,Scoring!$AB$29:$AB$361,0))) -> Aurobindo | C62: =IF($O62="","",IF(INDEX(Scoring!$P$29:$P$361,MATCH($O62,Scoring!$AB$29:$AB$361,0))="","–",INDEX(Scoring!$P$29:$P$361,MATCH($O62,Scoring!$AB$29:$AB$361,0)))) -> – | D62: =IF($O62="","",INDEX(Scoring!$Q$29:$Q$361,MATCH($O62,Scoring!$AB$29:$AB$361,0))) -> Excluded – price ≤ $5 | E62: =IF($O62="","",INDEX(Scoring!$AJ$29:$AJ$361,MATCH($O62,Scoring!$AB$29:$AB$361,0))) | F62: =IF($O62="","",INDEX(Scoring!$B$29:$B$361,MATCH($O62,Scoring!$AB$29:$AB$361,0))) -> Triamcinolone Acetonide | G62: =IF($O62="","",INDEX(Scoring!$AG$29:$AG$361,MATCH($O62,Scoring!$AB$29:$AB$361,0))) -> Triamcinolone Acetonide | H62: =IF($O62="","",INDEX(Scoring!$C$29:$C$361,MATCH($O62,Scoring!$AB$29:$AB$361,0))) -> Musculoskeletal and immunology: joint and soft-tissue injections, allergic and skin conditions | I62: =IF($O62="","",INDEX(Scoring!$I$29:$I$361,MATCH($O62,Scoring!$AB$29:$AB$361,0))) -> Not stated | J62: =IF($O62="","",INDEX(Scoring!$Z$29:$Z$361,MATCH($O62,Scoring!$AB$29:$AB$361,0))) -> 40 mg/mL (container not stated) | K62: =IF($O62="","",IF(INDEX(Scoring!$D$29:$D$361,MATCH($O62,Scoring!$AB$29:$AB$361,0))="",INDEX(Scoring!$AF$29:$AF$361,MATCH($O62,Scoring!$AB$29:$AB$361,0)),INDEX(Scoring!$D$29:$D$361,MATCH($O62,Scoring!$AB$29:$AB$361,0)))) -> 3.15 | L62: =IF($O62="","",INDEX(Scoring!$M$29:$M$361,MATCH($O62,Scoring!$AB$29:$AB$361,0))) -> 193 | M62: =IF($O62="","",INDEX(Scoring!$F$29:$F$361,MATCH($O62,Scoring!$AB$29:$AB$361,0))) -> 4256.8 | N62: =IF($O62="","",INDEX(Scoring!$AI$29:$AI$361,MATCH($O62,Scoring!$AB$29:$AB$361,0))) -> US | O62: =IFERROR(SMALL(Scoring!$AB$29:$AB$361,58),"") -> 2902
A63: =IF($O63="","",INT($O63/1000)) -> 3 | B63: =IF($O63="","",INDEX(Scoring!$A$29:$A$361,MATCH($O63,Scoring!$AB$29:$AB$361,0))) -> Dr. Reddy's | C63: =IF($O63="","",IF(INDEX(Scoring!$P$29:$P$361,MATCH($O63,Scoring!$AB$29:$AB$361,0))="","–",INDEX(Scoring!$P$29:$P$361,MATCH($O63,Scoring!$AB$29:$AB$361,0)))) -> 1 | D63: =IF($O63="","",INDEX(Scoring!$Q$29:$Q$361,MATCH($O63,Scoring!$AB$29:$AB$361,0))) -> Priority 1 | E63: =IF($O63="","",INDEX(Scoring!$AJ$29:$AJ$361,MATCH($O63,Scoring!$AB$29:$AB$361,0))) -> High price · high volume | F63: =IF($O63="","",INDEX(Scoring!$B$29:$B$361,MATCH($O63,Scoring!$AB$29:$AB$361,0))) -> Ertapenem | G63: =IF($O63="","",INDEX(Scoring!$AG$29:$AG$361,MATCH($O63,Scoring!$AB$29:$AB$361,0))) -> Ertapenem | H63: =IF($O63="","",INDEX(Scoring!$C$29:$C$361,MATCH($O63,Scoring!$AB$29:$AB$361,0))) -> Anti-infective: abdominal, skin and urinary infections, pneumonia | I63: =IF($O63="","",INDEX(Scoring!$I$29:$I$361,MATCH($O63,Scoring!$AB$29:$AB$361,0))) -> Vial | J63: =IF($O63="","",INDEX(Scoring!$Z$29:$Z$361,MATCH($O63,Scoring!$AB$29:$AB$361,0))) -> 1 g vial | K63: =IF($O63="","",IF(INDEX(Scoring!$D$29:$D$361,MATCH($O63,Scoring!$AB$29:$AB$361,0))="",INDEX(Scoring!$AF$29:$AF$361,MATCH($O63,Scoring!$AB$29:$AB$361,0)),INDEX(Scoring!$D$29:$D$361,MATCH($O63,Scoring!$AB$29:$AB$361,0)))) -> 36.59 | L63: =IF($O63="","",INDEX(Scoring!$M$29:$M$361,MATCH($O63,Scoring!$AB$29:$AB$361,0))) -> 223 | M63: =IF($O63="","",INDEX(Scoring!$F$29:$F$361,MATCH($O63,Scoring!$AB$29:$AB$361,0))) -> 53539.9 | N63: =IF($O63="","",INDEX(Scoring!$AI$29:$AI$361,MATCH($O63,Scoring!$AB$29:$AB$361,0))) -> Canada | O63: =IFERROR(SMALL(Scoring!$AB$29:$AB$361,59),"") -> 3001
A64: =IF($O64="","",INT($O64/1000)) -> 3 | B64: =IF($O64="","",INDEX(Scoring!$A$29:$A$361,MATCH($O64,Scoring!$AB$29:$AB$361,0))) -> Dr. Reddy's | C64: =IF($O64="","",IF(INDEX(Scoring!$P$29:$P$361,MATCH($O64,Scoring!$AB$29:$AB$361,0))="","–",INDEX(Scoring!$P$29:$P$361,MATCH($O64,Scoring!$AB$29:$AB$361,0)))) -> 2 | D64: =IF($O64="","",INDEX(Scoring!$Q$29:$Q$361,MATCH($O64,Scoring!$AB$29:$AB$361,0))) -> Priority 1 | E64: =IF($O64="","",INDEX(Scoring!$AJ$29:$AJ$361,MATCH($O64,Scoring!$AB$29:$AB$361,0))) -> High price · high volume | F64: =IF($O64="","",INDEX(Scoring!$B$29:$B$361,MATCH($O64,Scoring!$AB$29:$AB$361,0))) -> Azacitidine | G64: =IF($O64="","",INDEX(Scoring!$AG$29:$AG$361,MATCH($O64,Scoring!$AB$29:$AB$361,0))) -> Azacitidine Betapharm; Azacitidine; Reddaza (+1 more) | H64: =IF($O64="","",INDEX(Scoring!$C$29:$C$361,MATCH($O64,Scoring!$AB$29:$AB$361,0))) -> Oncology: myelodysplastic syndromes, acute myeloid leukaemia | I64: =IF($O64="","",INDEX(Scoring!$I$29:$I$361,MATCH($O64,Scoring!$AB$29:$AB$361,0))) -> Vial | J64: =IF($O64="","",INDEX(Scoring!$Z$29:$Z$361,MATCH($O64,Scoring!$AB$29:$AB$361,0))) -> 25 mg/mL vial; 100 mg powder vial; 100 mg in 30 mL powder vial | K64: =IF($O64="","",IF(INDEX(Scoring!$D$29:$D$361,MATCH($O64,Scoring!$AB$29:$AB$361,0))="",INDEX(Scoring!$AF$29:$AF$361,MATCH($O64,Scoring!$AB$29:$AB$361,0)),INDEX(Scoring!$D$29:$D$361,MATCH($O64,Scoring!$AB$29:$AB$361,0)))) -> 259.25 | L64: =IF($O64="","",INDEX(Scoring!$M$29:$M$361,MATCH($O64,Scoring!$AB$29:$AB$361,0))) -> 632 | M64: =IF($O64="","",INDEX(Scoring!$F$29:$F$361,MATCH($O64,Scoring!$AB$29:$AB$361,0))) -> 42181.7 | N64: =IF($O64="","",INDEX(Scoring!$AI$29:$AI$361,MATCH($O64,Scoring!$AB$29:$AB$361,0))) -> UK, Canada, Australia, South Africa | EU/EEA: all 30 countries | O64: =IFERROR(SMALL(Scoring!$AB$29:$AB$361,60),"") -> 3002
A65: =IF($O65="","",INT($O65/1000)) -> 3 | B65: =IF($O65="","",INDEX(Scoring!$A$29:$A$361,MATCH($O65,Scoring!$AB$29:$AB$361,0))) -> Dr. Reddy's | C65: =IF($O65="","",IF(INDEX(Scoring!$P$29:$P$361,MATCH($O65,Scoring!$AB$29:$AB$361,0))="","–",INDEX(Scoring!$P$29:$P$361,MATCH($O65,Scoring!$AB$29:$AB$361,0)))) -> 3 | D65: =IF($O65="","",INDEX(Scoring!$Q$29:$Q$361,MATCH($O65,Scoring!$AB$29:$AB$361,0))) -> Priority 1 | E65: =IF($O65="","",INDEX(Scoring!$AJ$29:$AJ$361,MATCH($O65,Scoring!$AB$29:$AB$361,0))) -> High price · high volume | F65: =IF($O65="","",INDEX(Scoring!$B$29:$B$361,MATCH($O65,Scoring!$AB$29:$AB$361,0))) -> Bortezomib | G65: =IF($O65="","",INDEX(Scoring!$AG$29:$AG$361,MATCH($O65,Scoring!$AB$29:$AB$361,0))) -> Bortezomib; Bortezomib Dr. Reddy's; Bertred | H65: =IF($O65="","",INDEX(Scoring!$C$29:$C$361,MATCH($O65,Scoring!$AB$29:$AB$361,0))) -> Oncology: multiple myeloma, mantle cell lymphoma | I65: =IF($O65="","",INDEX(Scoring!$I$29:$I$361,MATCH($O65,Scoring!$AB$29:$AB$361,0))) -> Vial | J65: =IF($O65="","",INDEX(Scoring!$Z$29:$Z$361,MATCH($O65,Scoring!$AB$29:$AB$361,0))) -> 3.5 mg powder vial; 3.5 mg in 10 mL powder vial | K65: =IF($O65="","",IF(INDEX(Scoring!$D$29:$D$361,MATCH($O65,Scoring!$AB$29:$AB$361,0))="",INDEX(Scoring!$AF$29:$AF$361,MATCH($O65,Scoring!$AB$29:$AB$361,0)),INDEX(Scoring!$D$29:$D$361,MATCH($O65,Scoring!$AB$29:$AB$361,0)))) -> 711.76 | L65: =IF($O65="","",INDEX(Scoring!$M$29:$M$361,MATCH($O65,Scoring!$AB$29:$AB$361,0))) -> 905 | M65: =IF($O65="","",INDEX(Scoring!$F$29:$F$361,MATCH($O65,Scoring!$AB$29:$AB$361,0))) -> 28093.4 | N65: =IF($O65="","",INDEX(Scoring!$AI$29:$AI$361,MATCH($O65,Scoring!$AB$29:$AB$361,0))) -> US, UK, Canada, South Africa, UK-NI | EU/EEA (13): Germany, France, Netherlands, Finland + 9 more | O65: =IFERROR(SMALL(Scoring!$AB$29:$AB$361,61),"") -> 3003
A66: =IF($O66="","",INT($O66/1000)) -> 3 | B66: =IF($O66="","",INDEX(Scoring!$A$29:$A$361,MATCH($O66,Scoring!$AB$29:$AB$361,0))) -> Dr. Reddy's | C66: =IF($O66="","",IF(INDEX(Scoring!$P$29:$P$361,MATCH($O66,Scoring!$AB$29:$AB$361,0))="","–",INDEX(Scoring!$P$29:$P$361,MATCH($O66,Scoring!$AB$29:$AB$361,0)))) -> 4 | D66: =IF($O66="","",INDEX(Scoring!$Q$29:$Q$361,MATCH($O66,Scoring!$AB$29:$AB$361,0))) -> Priority 1 | E66: =IF($O66="","",INDEX(Scoring!$AJ$29:$AJ$361,MATCH($O66,Scoring!$AB$29:$AB$361,0))) -> High price · high volume | F66: =IF($O66="","",INDEX(Scoring!$B$29:$B$361,MATCH($O66,Scoring!$AB$29:$AB$361,0))) -> Fulvestrant | G66: =IF($O66="","",INDEX(Scoring!$AG$29:$AG$361,MATCH($O66,Scoring!$AB$29:$AB$361,0))) -> Fulvestrant; Fulvestrant Dr. Reddy's; Fulvestrant Beta (+1 more) | H66: =IF($O66="","",INDEX(Scoring!$C$29:$C$361,MATCH($O66,Scoring!$AB$29:$AB$361,0))) -> Oncology: hormone receptor-positive advanced breast cancer | I66: =IF($O66="","",INDEX(Scoring!$I$29:$I$361,MATCH($O66,Scoring!$AB$29:$AB$361,0))) -> Prefilled syringe | J66: =IF($O66="","",INDEX(Scoring!$Z$29:$Z$361,MATCH($O66,Scoring!$AB$29:$AB$361,0))) -> 250 mg/5 mL pre-filled syringe | K66: =IF($O66="","",IF(INDEX(Scoring!$D$29:$D$361,MATCH($O66,Scoring!$AB$29:$AB$361,0))="",INDEX(Scoring!$AF$29:$AF$361,MATCH($O66,Scoring!$AB$29:$AB$361,0)),INDEX(Scoring!$D$29:$D$361,MATCH($O66,Scoring!$AB$29:$AB$361,0)))) -> 248.6 | L66: =IF($O66="","",INDEX(Scoring!$M$29:$M$361,MATCH($O66,Scoring!$AB$29:$AB$361,0))) -> 146 | M66: =IF($O66="","",INDEX(Scoring!$F$29:$F$361,MATCH($O66,Scoring!$AB$29:$AB$361,0))) -> 11366.1 | N66: =IF($O66="","",INDEX(Scoring!$AI$29:$AI$361,MATCH($O66,Scoring!$AB$29:$AB$361,0))) -> US, UK, South Africa, UK-NI | EU/EEA (10): Germany, Denmark, Ireland, Italy + 6 more | O66: =IFERROR(SMALL(Scoring!$AB$29:$AB$361,62),"") -> 3004
A67: =IF($O67="","",INT($O67/1000)) -> 3 | B67: =IF($O67="","",INDEX(Scoring!$A$29:$A$361,MATCH($O67,Scoring!$AB$29:$AB$361,0))) -> Dr. Reddy's | C67: =IF($O67="","",IF(INDEX(Scoring!$P$29:$P$361,MATCH($O67,Scoring!$AB$29:$AB$361,0))="","–",INDEX(Scoring!$P$29:$P$361,MATCH($O67,Scoring!$AB$29:$AB$361,0)))) -> 5 | D67: =IF($O67="","",INDEX(Scoring!$Q$29:$Q$361,MATCH($O67,Scoring!$AB$29:$AB$361,0))) -> Priority 2 | E67: =IF($O67="","",INDEX(Scoring!$AJ$29:$AJ$361,MATCH($O67,Scoring!$AB$29:$AB$361,0))) -> High price · lower volume | F67: =IF($O67="","",INDEX(Scoring!$B$29:$B$361,MATCH($O67,Scoring!$AB$29:$AB$361,0))) -> Plerixafor | G67: =IF($O67="","",INDEX(Scoring!$AG$29:$AG$361,MATCH($O67,Scoring!$AB$29:$AB$361,0))) -> Plerixafor | H67: =IF($O67="","",INDEX(Scoring!$C$29:$C$361,MATCH($O67,Scoring!$AB$29:$AB$361,0))) -> Oncology support: stem cell mobilisation in myeloma and lymphoma | I67: =IF($O67="","",INDEX(Scoring!$I$29:$I$361,MATCH($O67,Scoring!$AB$29:$AB$361,0))) -> Vial | J67: =IF($O67="","",INDEX(Scoring!$Z$29:$Z$361,MATCH($O67,Scoring!$AB$29:$AB$361,0))) -> 24 mg/1.2 mL vial | K67: =IF($O67="","",IF(INDEX(Scoring!$D$29:$D$361,MATCH($O67,Scoring!$AB$29:$AB$361,0))="",INDEX(Scoring!$AF$29:$AF$361,MATCH($O67,Scoring!$AB$29:$AB$361,0)),INDEX(Scoring!$D$29:$D$361,MATCH($O67,Scoring!$AB$29:$AB$361,0)))) -> 343.8 | L67: =IF($O67="","",INDEX(Scoring!$M$29:$M$361,MATCH($O67,Scoring!$AB$29:$AB$361,0))) -> 47 | M67: =IF($O67="","",INDEX(Scoring!$F$29:$F$361,MATCH($O67,Scoring!$AB$29:$AB$361,0))) -> 7904.7 | N67: =IF($O67="","",INDEX(Scoring!$AI$29:$AI$361,MATCH($O67,Scoring!$AB$29:$AB$361,0))) -> US | O67: =IFERROR(SMALL(Scoring!$AB$29:$AB$361,63),"") -> 3005
A68: =IF($O68="","",INT($O68/1000)) -> 3 | B68: =IF($O68="","",INDEX(Scoring!$A$29:$A$361,MATCH($O68,Scoring!$AB$29:$AB$361,0))) -> Dr. Reddy's | C68: =IF($O68="","",IF(INDEX(Scoring!$P$29:$P$361,MATCH($O68,Scoring!$AB$29:$AB$361,0))="","–",INDEX(Scoring!$P$29:$P$361,MATCH($O68,Scoring!$AB$29:$AB$361,0)))) -> 6 | D68: =IF($O68="","",INDEX(Scoring!$Q$29:$Q$361,MATCH($O68,Scoring!$AB$29:$AB$361,0))) -> Priority 2 | E68: =IF($O68="","",INDEX(Scoring!$AJ$29:$AJ$361,MATCH($O68,Scoring!$AB$29:$AB$361,0))) -> High price · lower volume | F68: =IF($O68="","",INDEX(Scoring!$B$29:$B$361,MATCH($O68,Scoring!$AB$29:$AB$361,0))) -> Carboprost | G68: =IF($O68="","",INDEX(Scoring!$AG$29:$AG$361,MATCH($O68,Scoring!$AB$29:$AB$361,0))) -> Carboprost Tromethamine; Carboprost Dr. Reddy's | H68: =IF($O68="","",INDEX(Scoring!$C$29:$C$361,MATCH($O68,Scoring!$AB$29:$AB$361,0))) -> Women's health: postpartum haemorrhage, pregnancy termination | I68: =IF($O68="","",INDEX(Scoring!$I$29:$I$361,MATCH($O68,Scoring!$AB$29:$AB$361,0))) -> Vial, Prefilled syringe | J68: =IF($O68="","",INDEX(Scoring!$Z$29:$Z$361,MATCH($O68,Scoring!$AB$29:$AB$361,0))) -> 0.25 mg/1 mL pre-filled syringe; 250 mcg/1 mL vial | K68: =IF($O68="","",IF(INDEX(Scoring!$D$29:$D$361,MATCH($O68,Scoring!$AB$29:$AB$361,0))="",INDEX(Scoring!$AF$29:$AF$361,MATCH($O68,Scoring!$AB$29:$AB$361,0)),INDEX(Scoring!$D$29:$D$361,MATCH($O68,Scoring!$AB$29:$AB$361,0)))) -> 127.38 | L68: =IF($O68="","",INDEX(Scoring!$M$29:$M$361,MATCH($O68,Scoring!$AB$29:$AB$361,0))) -> 143 | M68: =IF($O68="","",INDEX(Scoring!$F$29:$F$361,MATCH($O68,Scoring!$AB$29:$AB$361,0))) -> 3625.3 | N68: =IF($O68="","",INDEX(Scoring!$AI$29:$AI$361,MATCH($O68,Scoring!$AB$29:$AB$361,0))) -> US, Australia | O68: =IFERROR(SMALL(Scoring!$AB$29:$AB$361,64),"") -> 3006
A69: =IF($O69="","",INT($O69/1000)) -> 3 | B69: =IF($O69="","",INDEX(Scoring!$A$29:$A$361,MATCH($O69,Scoring!$AB$29:$AB$361,0))) -> Dr. Reddy's | C69: =IF($O69="","",IF(INDEX(Scoring!$P$29:$P$361,MATCH($O69,Scoring!$AB$29:$AB$361,0))="","–",INDEX(Scoring!$P$29:$P$361,MATCH($O69,Scoring!$AB$29:$AB$361,0)))) -> 7 | D69: =IF($O69="","",INDEX(Scoring!$Q$29:$Q$361,MATCH($O69,Scoring!$AB$29:$AB$361,0))) -> Priority 2 | E69: =IF($O69="","",INDEX(Scoring!$AJ$29:$AJ$361,MATCH($O69,Scoring!$AB$29:$AB$361,0))) -> Lower price · high volume | F69: =IF($O69="","",INDEX(Scoring!$B$29:$B$361,MATCH($O69,Scoring!$AB$29:$AB$361,0))) -> Succinylcholine (Suxamethonium) | G69: =IF($O69="","",INDEX(Scoring!$AG$29:$AG$361,MATCH($O69,Scoring!$AB$29:$AB$361,0))) -> Succinylcholine Chloride | H69: =IF($O69="","",INDEX(Scoring!$C$29:$C$361,MATCH($O69,Scoring!$AB$29:$AB$361,0))) -> Anaesthesia: muscle relaxant for rapid intubation | I69: =IF($O69="","",INDEX(Scoring!$I$29:$I$361,MATCH($O69,Scoring!$AB$29:$AB$361,0))) -> Vial | J69: =IF($O69="","",INDEX(Scoring!$Z$29:$Z$361,MATCH($O69,Scoring!$AB$29:$AB$361,0))) -> 200 mg/10 mL vial | K69: =IF($O69="","",IF(INDEX(Scoring!$D$29:$D$361,MATCH($O69,Scoring!$AB$29:$AB$361,0))="",INDEX(Scoring!$AF$29:$AF$361,MATCH($O69,Scoring!$AB$29:$AB$361,0)),INDEX(Scoring!$D$29:$D$361,MATCH($O69,Scoring!$AB$29:$AB$361,0)))) -> 22.76 | L69: =IF($O69="","",INDEX(Scoring!$M$29:$M$361,MATCH($O69,Scoring!$AB$29:$AB$361,0))) -> 286 | M69: =IF($O69="","",INDEX(Scoring!$F$29:$F$361,MATCH($O69,Scoring!$AB$29:$AB$361,0))) -> 3067.4 | N69: =IF($O69="","",INDEX(Scoring!$AI$29:$AI$361,MATCH($O69,Scoring!$AB$29:$AB$361,0))) -> US, Canada | O69: =IFERROR(SMALL(Scoring!$AB$29:$AB$361,65),"") -> 3007
A70: =IF($O70="","",INT($O70/1000)) -> 3 | B70: =IF($O70="","",INDEX(Scoring!$A$29:$A$361,MATCH($O70,Scoring!$AB$29:$AB$361,0))) -> Dr. Reddy's | C70: =IF($O70="","",IF(INDEX(Scoring!$P$29:$P$361,MATCH($O70,Scoring!$AB$29:$AB$361,0))="","–",INDEX(Scoring!$P$29:$P$361,MATCH($O70,Scoring!$AB$29:$AB$361,0)))) -> 8 | D70: =IF($O70="","",INDEX(Scoring!$Q$29:$Q$361,MATCH($O70,Scoring!$AB$29:$AB$361,0))) -> Priority 2 | E70: =IF($O70="","",INDEX(Scoring!$AJ$29:$AJ$361,MATCH($O70,Scoring!$AB$29:$AB$361,0))) -> Lower price · high volume | F70: =IF($O70="","",INDEX(Scoring!$B$29:$B$361,MATCH($O70,Scoring!$AB$29:$AB$361,0))) -> Neostigmine | G70: =IF($O70="","",INDEX(Scoring!$AG$29:$AG$361,MATCH($O70,Scoring!$AB$29:$AB$361,0))) -> Neostigmine Methylsulfate | H70: =IF($O70="","",INDEX(Scoring!$C$29:$C$361,MATCH($O70,Scoring!$AB$29:$AB$361,0))) -> Anaesthesia and neurology: reversal of muscle relaxants after surgery, myasthenia gravis | I70: =IF($O70="","",INDEX(Scoring!$I$29:$I$361,MATCH($O70,Scoring!$AB$29:$AB$361,0))) -> Vial, Prefilled syringe | J70: =IF($O70="","",INDEX(Scoring!$Z$29:$Z$361,MATCH($O70,Scoring!$AB$29:$AB$361,0))) -> 3 mg/3 mL pre-filled syringe; 5 mg/10 mL vial; 10 mg/10 mL vial | K70: =IF($O70="","",IF(INDEX(Scoring!$D$29:$D$361,MATCH($O70,Scoring!$AB$29:$AB$361,0))="",INDEX(Scoring!$AF$29:$AF$361,MATCH($O70,Scoring!$AB$29:$AB$361,0)),INDEX(Scoring!$D$29:$D$361,MATCH($O70,Scoring!$AB$29:$AB$361,0)))) -> 17.79 | L70: =IF($O70="","",INDEX(Scoring!$M$29:$M$361,MATCH($O70,Scoring!$AB$29:$AB$361,0))) -> 234 | M70: =IF($O70="","",INDEX(Scoring!$F$29:$F$361,MATCH($O70,Scoring!$AB$29:$AB$361,0))) -> 1830.5 | N70: =IF($O70="","",INDEX(Scoring!$AI$29:$AI$361,MATCH($O70,Scoring!$AB$29:$AB$361,0))) -> US | O70: =IFERROR(SMALL(Scoring!$AB$29:$AB$361,66),"") -> 3008
A71: =IF($O71="","",INT($O71/1000)) -> 3 | B71: =IF($O71="","",INDEX(Scoring!$A$29:$A$361,MATCH($O71,Scoring!$AB$29:$AB$361,0))) -> Dr. Reddy's | C71: =IF($O71="","",IF(INDEX(Scoring!$P$29:$P$361,MATCH($O71,Scoring!$AB$29:$AB$361,0))="","–",INDEX(Scoring!$P$29:$P$361,MATCH($O71,Scoring!$AB$29:$AB$361,0)))) -> 9 | D71: =IF($O71="","",INDEX(Scoring!$Q$29:$Q$361,MATCH($O71,Scoring!$AB$29:$AB$361,0))) -> Priority 2 | E71: =IF($O71="","",INDEX(Scoring!$AJ$29:$AJ$361,MATCH($O71,Scoring!$AB$29:$AB$361,0))) -> High price · lower volume | F71: =IF($O71="","",INDEX(Scoring!$B$29:$B$361,MATCH($O71,Scoring!$AB$29:$AB$361,0))) -> Desmopressin | G71: =IF($O71="","",INDEX(Scoring!$AG$29:$AG$361,MATCH($O71,Scoring!$AB$29:$AB$361,0))) -> Desmopressin Acetate | H71: =IF($O71="","",INDEX(Scoring!$C$29:$C$361,MATCH($O71,Scoring!$AB$29:$AB$361,0))) -> Endocrinology and haematology: diabetes insipidus, haemophilia A, von Willebrand disease | I71: =IF($O71="","",INDEX(Scoring!$I$29:$I$361,MATCH($O71,Scoring!$AB$29:$AB$361,0))) -> Vial | J71: =IF($O71="","",INDEX(Scoring!$Z$29:$Z$361,MATCH($O71,Scoring!$AB$29:$AB$361,0))) -> 0.04 mg/10 mL vial | K71: =IF($O71="","",IF(INDEX(Scoring!$D$29:$D$361,MATCH($O71,Scoring!$AB$29:$AB$361,0))="",INDEX(Scoring!$AF$29:$AF$361,MATCH($O71,Scoring!$AB$29:$AB$361,0)),INDEX(Scoring!$D$29:$D$361,MATCH($O71,Scoring!$AB$29:$AB$361,0)))) -> 133.8 | L71: =IF($O71="","",INDEX(Scoring!$M$29:$M$361,MATCH($O71,Scoring!$AB$29:$AB$361,0))) -> 40 | M71: =IF($O71="","",INDEX(Scoring!$F$29:$F$361,MATCH($O71,Scoring!$AB$29:$AB$361,0))) -> 543 | N71: =IF($O71="","",INDEX(Scoring!$AI$29:$AI$361,MATCH($O71,Scoring!$AB$29:$AB$361,0))) -> US | O71: =IFERROR(SMALL(Scoring!$AB$29:$AB$361,67),"") -> 3009
A72: =IF($O72="","",INT($O72/1000)) -> 3 | B72: =IF($O72="","",INDEX(Scoring!$A$29:$A$361,MATCH($O72,Scoring!$AB$29:$AB$361,0))) -> Dr. Reddy's | C72: =IF($O72="","",IF(INDEX(Scoring!$P$29:$P$361,MATCH($O72,Scoring!$AB$29:$AB$361,0))="","–",INDEX(Scoring!$P$29:$P$361,MATCH($O72,Scoring!$AB$29:$AB$361,0)))) -> 10 | D72: =IF($O72="","",INDEX(Scoring!$Q$29:$Q$361,MATCH($O72,Scoring!$AB$29:$AB$361,0))) -> Priority 3 | E72: =IF($O72="","",INDEX(Scoring!$AJ$29:$AJ$361,MATCH($O72,Scoring!$AB$29:$AB$361,0))) -> Lower price · lower volume | F72: =IF($O72="","",INDEX(Scoring!$B$29:$B$361,MATCH($O72,Scoring!$AB$29:$AB$361,0))) -> Ephedrine | G72: =IF($O72="","",INDEX(Scoring!$AG$29:$AG$361,MATCH($O72,Scoring!$AB$29:$AB$361,0))) -> Ephedrine Sulfate | H72: =IF($O72="","",INDEX(Scoring!$C$29:$C$361,MATCH($O72,Scoring!$AB$29:$AB$361,0))) -> Anaesthesia: low blood pressure during spinal anaesthesia and caesarean section | I72: =IF($O72="","",INDEX(Scoring!$I$29:$I$361,MATCH($O72,Scoring!$AB$29:$AB$361,0))) -> Vial | J72: =IF($O72="","",INDEX(Scoring!$Z$29:$Z$361,MATCH($O72,Scoring!$AB$29:$AB$361,0))) -> 50 mg/1 mL vial | K72: =IF($O72="","",IF(INDEX(Scoring!$D$29:$D$361,MATCH($O72,Scoring!$AB$29:$AB$361,0))="",INDEX(Scoring!$AF$29:$AF$361,MATCH($O72,Scoring!$AB$29:$AB$361,0)),INDEX(Scoring!$D$29:$D$361,MATCH($O72,Scoring!$AB$29:$AB$361,0)))) -> 5.35 | L72: =IF($O72="","",INDEX(Scoring!$M$29:$M$361,MATCH($O72,Scoring!$AB$29:$AB$361,0))) -> 49 | M72: =IF($O72="","",INDEX(Scoring!$F$29:$F$361,MATCH($O72,Scoring!$AB$29:$AB$361,0))) -> 2937.3 | N72: =IF($O72="","",INDEX(Scoring!$AI$29:$AI$361,MATCH($O72,Scoring!$AB$29:$AB$361,0))) -> US | O72: =IFERROR(SMALL(Scoring!$AB$29:$AB$361,68),"") -> 3010
A73: =IF($O73="","",INT($O73/1000)) -> 3 | B73: =IF($O73="","",INDEX(Scoring!$A$29:$A$361,MATCH($O73,Scoring!$AB$29:$AB$361,0))) -> Dr. Reddy's | C73: =IF($O73="","",IF(INDEX(Scoring!$P$29:$P$361,MATCH($O73,Scoring!$AB$29:$AB$361,0))="","–",INDEX(Scoring!$P$29:$P$361,MATCH($O73,Scoring!$AB$29:$AB$361,0)))) -> 11 | D73: =IF($O73="","",INDEX(Scoring!$Q$29:$Q$361,MATCH($O73,Scoring!$AB$29:$AB$361,0))) -> Priority 3 | E73: =IF($O73="","",INDEX(Scoring!$AJ$29:$AJ$361,MATCH($O73,Scoring!$AB$29:$AB$361,0))) -> Lower price · lower volume | F73: =IF($O73="","",INDEX(Scoring!$B$29:$B$361,MATCH($O73,Scoring!$AB$29:$AB$361,0))) -> Phytonadione | G73: =IF($O73="","",INDEX(Scoring!$AG$29:$AG$361,MATCH($O73,Scoring!$AB$29:$AB$361,0))) -> Phytonadione | H73: =IF($O73="","",INDEX(Scoring!$C$29:$C$361,MATCH($O73,Scoring!$AB$29:$AB$361,0))) -> Haematology: vitamin K for newborn bleeding prevention, warfarin reversal | I73: =IF($O73="","",INDEX(Scoring!$I$29:$I$361,MATCH($O73,Scoring!$AB$29:$AB$361,0))) -> Ampoule | J73: =IF($O73="","",INDEX(Scoring!$Z$29:$Z$361,MATCH($O73,Scoring!$AB$29:$AB$361,0))) -> 1 mg/0.5 mL in 1 mL ampoule; 10 mg/1 mL ampoule | K73: =IF($O73="","",IF(INDEX(Scoring!$D$29:$D$361,MATCH($O73,Scoring!$AB$29:$AB$361,0))="",INDEX(Scoring!$AF$29:$AF$361,MATCH($O73,Scoring!$AB$29:$AB$361,0)),INDEX(Scoring!$D$29:$D$361,MATCH($O73,Scoring!$AB$29:$AB$361,0)))) -> 16.96 | L73: =IF($O73="","",INDEX(Scoring!$M$29:$M$361,MATCH($O73,Scoring!$AB$29:$AB$361,0))) -> 24 | M73: =IF($O73="","",INDEX(Scoring!$F$29:$F$361,MATCH($O73,Scoring!$AB$29:$AB$361,0))) -> 2702.3 | N73: =IF($O73="","",INDEX(Scoring!$AI$29:$AI$361,MATCH($O73,Scoring!$AB$29:$AB$361,0))) -> US | O73: =IFERROR(SMALL(Scoring!$AB$29:$AB$361,69),"") -> 3011
A74: =IF($O74="","",INT($O74/1000)) -> 3 | B74: =IF($O74="","",INDEX(Scoring!$A$29:$A$361,MATCH($O74,Scoring!$AB$29:$AB$361,0))) -> Dr. Reddy's | C74: =IF($O74="","",IF(INDEX(Scoring!$P$29:$P$361,MATCH($O74,Scoring!$AB$29:$AB$361,0))="","–",INDEX(Scoring!$P$29:$P$361,MATCH($O74,Scoring!$AB$29:$AB$361,0)))) -> 12 | D74: =IF($O74="","",INDEX(Scoring!$Q$29:$Q$361,MATCH($O74,Scoring!$AB$29:$AB$361,0))) -> Priority 3 | E74: =IF($O74="","",INDEX(Scoring!$AJ$29:$AJ$361,MATCH($O74,Scoring!$AB$29:$AB$361,0))) -> Lower price · lower volume | F74: =IF($O74="","",INDEX(Scoring!$B$29:$B$361,MATCH($O74,Scoring!$AB$29:$AB$361,0))) -> Naloxone | G74: =IF($O74="","",INDEX(Scoring!$AG$29:$AG$361,MATCH($O74,Scoring!$AB$29:$AB$361,0))) -> Naloxone Hydrochloride | H74: =IF($O74="","",INDEX(Scoring!$C$29:$C$361,MATCH($O74,Scoring!$AB$29:$AB$361,0))) -> Critical care: reversal of opioid overdose | I74: =IF($O74="","",INDEX(Scoring!$I$29:$I$361,MATCH($O74,Scoring!$AB$29:$AB$361,0))) -> Prefilled syringe | J74: =IF($O74="","",INDEX(Scoring!$Z$29:$Z$361,MATCH($O74,Scoring!$AB$29:$AB$361,0))) -> 2 mg/2 mL pre-filled syringe | K74: =IF($O74="","",IF(INDEX(Scoring!$D$29:$D$361,MATCH($O74,Scoring!$AB$29:$AB$361,0))="",INDEX(Scoring!$AF$29:$AF$361,MATCH($O74,Scoring!$AB$29:$AB$361,0)),INDEX(Scoring!$D$29:$D$361,MATCH($O74,Scoring!$AB$29:$AB$361,0)))) -> 13.87 | L74: =IF($O74="","",INDEX(Scoring!$M$29:$M$361,MATCH($O74,Scoring!$AB$29:$AB$361,0))) -> 88 | M74: =IF($O74="","",INDEX(Scoring!$F$29:$F$361,MATCH($O74,Scoring!$AB$29:$AB$361,0))) -> 1437.9 | N74: =IF($O74="","",INDEX(Scoring!$AI$29:$AI$361,MATCH($O74,Scoring!$AB$29:$AB$361,0))) -> US | O74: =IFERROR(SMALL(Scoring!$AB$29:$AB$361,70),"") -> 3012
A75: =IF($O75="","",INT($O75/1000)) -> 3 | B75: =IF($O75="","",INDEX(Scoring!$A$29:$A$361,MATCH($O75,Scoring!$AB$29:$AB$361,0))) -> Dr. Reddy's | C75: =IF($O75="","",IF(INDEX(Scoring!$P$29:$P$361,MATCH($O75,Scoring!$AB$29:$AB$361,0))="","–",INDEX(Scoring!$P$29:$P$361,MATCH($O75,Scoring!$AB$29:$AB$361,0)))) -> 13 | D75: =IF($O75="","",INDEX(Scoring!$Q$29:$Q$361,MATCH($O75,Scoring!$AB$29:$AB$361,0))) -> Priority 3 | E75: =IF($O75="","",INDEX(Scoring!$AJ$29:$AJ$361,MATCH($O75,Scoring!$AB$29:$AB$361,0))) -> Lower price · lower volume | F75: =IF($O75="","",INDEX(Scoring!$B$29:$B$361,MATCH($O75,Scoring!$AB$29:$AB$361,0))) -> Diazepam | G75: =IF($O75="","",INDEX(Scoring!$AG$29:$AG$361,MATCH($O75,Scoring!$AB$29:$AB$361,0))) -> Diazepam | H75: =IF($O75="","",INDEX(Scoring!$C$29:$C$361,MATCH($O75,Scoring!$AB$29:$AB$361,0))) -> Neurology: status epilepticus, seizures, acute anxiety and sedation | I75: =IF($O75="","",INDEX(Scoring!$I$29:$I$361,MATCH($O75,Scoring!$AB$29:$AB$361,0))) -> Prefilled syringe | J75: =IF($O75="","",INDEX(Scoring!$Z$29:$Z$361,MATCH($O75,Scoring!$AB$29:$AB$361,0))) -> 10 mg/2 mL pre-filled syringe | K75: =IF($O75="","",IF(INDEX(Scoring!$D$29:$D$361,MATCH($O75,Scoring!$AB$29:$AB$361,0))="",INDEX(Scoring!$AF$29:$AF$361,MATCH($O75,Scoring!$AB$29:$AB$361,0)),INDEX(Scoring!$D$29:$D$361,MATCH($O75,Scoring!$AB$29:$AB$361,0)))) -> 10.14 | L75: =IF($O75="","",INDEX(Scoring!$M$29:$M$361,MATCH($O75,Scoring!$AB$29:$AB$361,0))) -> 35 | M75: =IF($O75="","",INDEX(Scoring!$F$29:$F$361,MATCH($O75,Scoring!$AB$29:$AB$361,0))) -> 1053.6 | N75: =IF($O75="","",INDEX(Scoring!$AI$29:$AI$361,MATCH($O75,Scoring!$AB$29:$AB$361,0))) -> US | O75: =IFERROR(SMALL(Scoring!$AB$29:$AB$361,71),"") -> 3013
A76: =IF($O76="","",INT($O76/1000)) -> 3 | B76: =IF($O76="","",INDEX(Scoring!$A$29:$A$361,MATCH($O76,Scoring!$AB$29:$AB$361,0))) -> Dr. Reddy's | C76: =IF($O76="","",IF(INDEX(Scoring!$P$29:$P$361,MATCH($O76,Scoring!$AB$29:$AB$361,0))="","–",INDEX(Scoring!$P$29:$P$361,MATCH($O76,Scoring!$AB$29:$AB$361,0)))) -> – | D76: =IF($O76="","",INDEX(Scoring!$Q$29:$Q$361,MATCH($O76,Scoring!$AB$29:$AB$361,0))) -> Excluded – price ≤ $5 | E76: =IF($O76="","",INDEX(Scoring!$AJ$29:$AJ$361,MATCH($O76,Scoring!$AB$29:$AB$361,0))) | F76: =IF($O76="","",INDEX(Scoring!$B$29:$B$361,MATCH($O76,Scoring!$AB$29:$AB$361,0))) -> Triamcinolone Acetonide | G76: =IF($O76="","",INDEX(Scoring!$AG$29:$AG$361,MATCH($O76,Scoring!$AB$29:$AB$361,0))) -> Triamcinolone Acetonide | H76: =IF($O76="","",INDEX(Scoring!$C$29:$C$361,MATCH($O76,Scoring!$AB$29:$AB$361,0))) -> Musculoskeletal and immunology: joint and soft-tissue injections, allergic and skin conditions | I76: =IF($O76="","",INDEX(Scoring!$I$29:$I$361,MATCH($O76,Scoring!$AB$29:$AB$361,0))) -> Not stated | J76: =IF($O76="","",INDEX(Scoring!$Z$29:$Z$361,MATCH($O76,Scoring!$AB$29:$AB$361,0))) -> 10 mg/mL (container not stated); 40 mg/mL (container not stated) | K76: =IF($O76="","",IF(INDEX(Scoring!$D$29:$D$361,MATCH($O76,Scoring!$AB$29:$AB$361,0))="",INDEX(Scoring!$AF$29:$AF$361,MATCH($O76,Scoring!$AB$29:$AB$361,0)),INDEX(Scoring!$D$29:$D$361,MATCH($O76,Scoring!$AB$29:$AB$361,0)))) -> 3.55 | L76: =IF($O76="","",INDEX(Scoring!$M$29:$M$361,MATCH($O76,Scoring!$AB$29:$AB$361,0))) -> 193 | M76: =IF($O76="","",INDEX(Scoring!$F$29:$F$361,MATCH($O76,Scoring!$AB$29:$AB$361,0))) -> 4256.8 | N76: =IF($O76="","",INDEX(Scoring!$AI$29:$AI$361,MATCH($O76,Scoring!$AB$29:$AB$361,0))) -> US | O76: =IFERROR(SMALL(Scoring!$AB$29:$AB$361,72),"") -> 3901
A77: =IF($O77="","",INT($O77/1000)) -> 4 | B77: =IF($O77="","",INDEX(Scoring!$A$29:$A$361,MATCH($O77,Scoring!$AB$29:$AB$361,0))) -> Cipla | C77: =IF($O77="","",IF(INDEX(Scoring!$P$29:$P$361,MATCH($O77,Scoring!$AB$29:$AB$361,0))="","–",INDEX(Scoring!$P$29:$P$361,MATCH($O77,Scoring!$AB$29:$AB$361,0)))) -> 1 | D77: =IF($O77="","",INDEX(Scoring!$Q$29:$Q$361,MATCH($O77,Scoring!$AB$29:$AB$361,0))) -> Priority 1 | E77: =IF($O77="","",INDEX(Scoring!$AJ$29:$AJ$361,MATCH($O77,Scoring!$AB$29:$AB$361,0))) -> High price · high volume | F77: =IF($O77="","",INDEX(Scoring!$B$29:$B$361,MATCH($O77,Scoring!$AB$29:$AB$361,0))) -> Bortezomib | G77: =IF($O77="","",INDEX(Scoring!$AG$29:$AG$361,MATCH($O77,Scoring!$AB$29:$AB$361,0))) -> Onbort | H77: =IF($O77="","",INDEX(Scoring!$C$29:$C$361,MATCH($O77,Scoring!$AB$29:$AB$361,0))) -> Oncology: multiple myeloma, mantle cell lymphoma | I77: =IF($O77="","",INDEX(Scoring!$I$29:$I$361,MATCH($O77,Scoring!$AB$29:$AB$361,0))) -> Vial | J77: =IF($O77="","",INDEX(Scoring!$Z$29:$Z$361,MATCH($O77,Scoring!$AB$29:$AB$361,0))) -> 3.5 mg/1.4 mL vial | K77: =IF($O77="","",IF(INDEX(Scoring!$D$29:$D$361,MATCH($O77,Scoring!$AB$29:$AB$361,0))="",INDEX(Scoring!$AF$29:$AF$361,MATCH($O77,Scoring!$AB$29:$AB$361,0)),INDEX(Scoring!$D$29:$D$361,MATCH($O77,Scoring!$AB$29:$AB$361,0)))) -> 163.29 | L77: =IF($O77="","",INDEX(Scoring!$M$29:$M$361,MATCH($O77,Scoring!$AB$29:$AB$361,0))) -> 905 | M77: =IF($O77="","",INDEX(Scoring!$F$29:$F$361,MATCH($O77,Scoring!$AB$29:$AB$361,0))) -> 28093.4 | N77: =IF($O77="","",INDEX(Scoring!$AI$29:$AI$361,MATCH($O77,Scoring!$AB$29:$AB$361,0))) -> South Africa | O77: =IFERROR(SMALL(Scoring!$AB$29:$AB$361,73),"") -> 4001
A78: =IF($O78="","",INT($O78/1000)) -> 4 | B78: =IF($O78="","",INDEX(Scoring!$A$29:$A$361,MATCH($O78,Scoring!$AB$29:$AB$361,0))) -> Cipla | C78: =IF($O78="","",IF(INDEX(Scoring!$P$29:$P$361,MATCH($O78,Scoring!$AB$29:$AB$361,0))="","–",INDEX(Scoring!$P$29:$P$361,MATCH($O78,Scoring!$AB$29:$AB$361,0)))) -> 2 | D78: =IF($O78="","",INDEX(Scoring!$Q$29:$Q$361,MATCH($O78,Scoring!$AB$29:$AB$361,0))) -> Priority 1 | E78: =IF($O78="","",INDEX(Scoring!$AJ$29:$AJ$361,MATCH($O78,Scoring!$AB$29:$AB$361,0))) -> High price · high volume | F78: =IF($O78="","",INDEX(Scoring!$B$29:$B$361,MATCH($O78,Scoring!$AB$29:$AB$361,0))) -> Fulvestrant | G78: =IF($O78="","",INDEX(Scoring!$AG$29:$AG$361,MATCH($O78,Scoring!$AB$29:$AB$361,0))) -> Fulvestrant Cipla | H78: =IF($O78="","",INDEX(Scoring!$C$29:$C$361,MATCH($O78,Scoring!$AB$29:$AB$361,0))) -> Oncology: hormone receptor-positive advanced breast cancer | I78: =IF($O78="","",INDEX(Scoring!$I$29:$I$361,MATCH($O78,Scoring!$AB$29:$AB$361,0))) -> Prefilled syringe | J78: =IF($O78="","",INDEX(Scoring!$Z$29:$Z$361,MATCH($O78,Scoring!$AB$29:$AB$361,0))) -> 250 mg/5 mL pre-filled syringe | K78: =IF($O78="","",IF(INDEX(Scoring!$D$29:$D$361,MATCH($O78,Scoring!$AB$29:$AB$361,0))="",INDEX(Scoring!$AF$29:$AF$361,MATCH($O78,Scoring!$AB$29:$AB$361,0)),INDEX(Scoring!$D$29:$D$361,MATCH($O78,Scoring!$AB$29:$AB$361,0)))) -> 531.87 | L78: =IF($O78="","",INDEX(Scoring!$M$29:$M$361,MATCH($O78,Scoring!$AB$29:$AB$361,0))) -> 146 | M78: =IF($O78="","",INDEX(Scoring!$F$29:$F$361,MATCH($O78,Scoring!$AB$29:$AB$361,0))) -> 11366.1 | N78: =IF($O78="","",INDEX(Scoring!$AI$29:$AI$361,MATCH($O78,Scoring!$AB$29:$AB$361,0))) -> EU/EEA (1): Germany | O78: =IFERROR(SMALL(Scoring!$AB$29:$AB$361,74),"") -> 4002
A79: =IF($O79="","",INT($O79/1000)) -> 4 | B79: =IF($O79="","",INDEX(Scoring!$A$29:$A$361,MATCH($O79,Scoring!$AB$29:$AB$361,0))) -> Cipla | C79: =IF($O79="","",IF(INDEX(Scoring!$P$29:$P$361,MATCH($O79,Scoring!$AB$29:$AB$361,0))="","–",INDEX(Scoring!$P$29:$P$361,MATCH($O79,Scoring!$AB$29:$AB$361,0)))) -> 3 | D79: =IF($O79="","",INDEX(Scoring!$Q$29:$Q$361,MATCH($O79,Scoring!$AB$29:$AB$361,0))) -> Priority 1 | E79: =IF($O79="","",INDEX(Scoring!$AJ$29:$AJ$361,MATCH($O79,Scoring!$AB$29:$AB$361,0))) -> High price · high volume | F79: =IF($O79="","",INDEX(Scoring!$B$29:$B$361,MATCH($O79,Scoring!$AB$29:$AB$361,0))) -> Bleomycin | G79: =IF($O79="","",INDEX(Scoring!$AG$29:$AG$361,MATCH($O79,Scoring!$AB$29:$AB$361,0))) -> Cipla Bleomycin 15K; Cipla Bleomycin | H79: =IF($O79="","",INDEX(Scoring!$C$29:$C$361,MATCH($O79,Scoring!$AB$29:$AB$361,0))) -> Oncology: Hodgkin lymphoma, testicular and squamous cell cancers | I79: =IF($O79="","",INDEX(Scoring!$I$29:$I$361,MATCH($O79,Scoring!$AB$29:$AB$361,0))) -> Vial | J79: =IF($O79="","",INDEX(Scoring!$Z$29:$Z$361,MATCH($O79,Scoring!$AB$29:$AB$361,0))) -> 15000 IU powder vial; 15 units (15000 IU) in 5 mL powder vial | K79: =IF($O79="","",IF(INDEX(Scoring!$D$29:$D$361,MATCH($O79,Scoring!$AB$29:$AB$361,0))="",INDEX(Scoring!$AF$29:$AF$361,MATCH($O79,Scoring!$AB$29:$AB$361,0)),INDEX(Scoring!$D$29:$D$361,MATCH($O79,Scoring!$AB$29:$AB$361,0)))) -> 41.27 | L79: =IF($O79="","",INDEX(Scoring!$M$29:$M$361,MATCH($O79,Scoring!$AB$29:$AB$361,0))) -> 441 | M79: =IF($O79="","",INDEX(Scoring!$F$29:$F$361,MATCH($O79,Scoring!$AB$29:$AB$361,0))) -> 3973.7 | N79: =IF($O79="","",INDEX(Scoring!$AI$29:$AI$361,MATCH($O79,Scoring!$AB$29:$AB$361,0))) -> Australia, South Africa | O79: =IFERROR(SMALL(Scoring!$AB$29:$AB$361,75),"") -> 4003
A80: =IF($O80="","",INT($O80/1000)) -> 4 | B80: =IF($O80="","",INDEX(Scoring!$A$29:$A$361,MATCH($O80,Scoring!$AB$29:$AB$361,0))) -> Cipla | C80: =IF($O80="","",IF(INDEX(Scoring!$P$29:$P$361,MATCH($O80,Scoring!$AB$29:$AB$361,0))="","–",INDEX(Scoring!$P$29:$P$361,MATCH($O80,Scoring!$AB$29:$AB$361,0)))) -> 4 | D80: =IF($O80="","",INDEX(Scoring!$Q$29:$Q$361,MATCH($O80,Scoring!$AB$29:$AB$361,0))) -> Priority 2 | E80: =IF($O80="","",INDEX(Scoring!$AJ$29:$AJ$361,MATCH($O80,Scoring!$AB$29:$AB$361,0))) -> Lower price · high volume | F80: =IF($O80="","",INDEX(Scoring!$B$29:$B$361,MATCH($O80,Scoring!$AB$29:$AB$361,0))) -> Measles Vaccine | G80: =IF($O80="","",INDEX(Scoring!$AG$29:$AG$361,MATCH($O80,Scoring!$AB$29:$AB$361,0))) -> Measles Vaccine Cipla | H80: =IF($O80="","",INDEX(Scoring!$C$29:$C$361,MATCH($O80,Scoring!$AB$29:$AB$361,0))) -> Vaccines: childhood measles immunisation | I80: =IF($O80="","",INDEX(Scoring!$I$29:$I$361,MATCH($O80,Scoring!$AB$29:$AB$361,0))) -> Vial | J80: =IF($O80="","",INDEX(Scoring!$Z$29:$Z$361,MATCH($O80,Scoring!$AB$29:$AB$361,0))) -> 1000 CCID50/0.5 mL vial | K80: =IF($O80="","",IF(INDEX(Scoring!$D$29:$D$361,MATCH($O80,Scoring!$AB$29:$AB$361,0))="",INDEX(Scoring!$AF$29:$AF$361,MATCH($O80,Scoring!$AB$29:$AB$361,0)),INDEX(Scoring!$D$29:$D$361,MATCH($O80,Scoring!$AB$29:$AB$361,0)))) -> 9.55 | L80: =IF($O80="","",INDEX(Scoring!$M$29:$M$361,MATCH($O80,Scoring!$AB$29:$AB$361,0))) -> 590 | M80: =IF($O80="","",INDEX(Scoring!$F$29:$F$361,MATCH($O80,Scoring!$AB$29:$AB$361,0))) -> 417765.2 | N80: =IF($O80="","",INDEX(Scoring!$AI$29:$AI$361,MATCH($O80,Scoring!$AB$29:$AB$361,0))) -> South Africa | O80: =IFERROR(SMALL(Scoring!$AB$29:$AB$361,76),"") -> 4004
A81: =IF($O81="","",INT($O81/1000)) -> 4 | B81: =IF($O81="","",INDEX(Scoring!$A$29:$A$361,MATCH($O81,Scoring!$AB$29:$AB$361,0))) -> Cipla | C81: =IF($O81="","",IF(INDEX(Scoring!$P$29:$P$361,MATCH($O81,Scoring!$AB$29:$AB$361,0))="","–",INDEX(Scoring!$P$29:$P$361,MATCH($O81,Scoring!$AB$29:$AB$361,0)))) -> 5 | D81: =IF($O81="","",INDEX(Scoring!$Q$29:$Q$361,MATCH($O81,Scoring!$AB$29:$AB$361,0))) -> Priority 2 | E81: =IF($O81="","",INDEX(Scoring!$AJ$29:$AJ$361,MATCH($O81,Scoring!$AB$29:$AB$361,0))) -> Lower price · high volume | F81: =IF($O81="","",INDEX(Scoring!$B$29:$B$361,MATCH($O81,Scoring!$AB$29:$AB$361,0))) -> Azacitidine | G81: =IF($O81="","",INDEX(Scoring!$AG$29:$AG$361,MATCH($O81,Scoring!$AB$29:$AB$361,0))) -> Azacitidine Cipla | H81: =IF($O81="","",INDEX(Scoring!$C$29:$C$361,MATCH($O81,Scoring!$AB$29:$AB$361,0))) -> Oncology: myelodysplastic syndromes, acute myeloid leukaemia | I81: =IF($O81="","",INDEX(Scoring!$I$29:$I$361,MATCH($O81,Scoring!$AB$29:$AB$361,0))) -> Vial | J81: =IF($O81="","",INDEX(Scoring!$Z$29:$Z$361,MATCH($O81,Scoring!$AB$29:$AB$361,0))) -> 100 mg powder vial | K81: =IF($O81="","",IF(INDEX(Scoring!$D$29:$D$361,MATCH($O81,Scoring!$AB$29:$AB$361,0))="",INDEX(Scoring!$AF$29:$AF$361,MATCH($O81,Scoring!$AB$29:$AB$361,0)),INDEX(Scoring!$D$29:$D$361,MATCH($O81,Scoring!$AB$29:$AB$361,0)))) -> 10.24 | L81: =IF($O81="","",INDEX(Scoring!$M$29:$M$361,MATCH($O81,Scoring!$AB$29:$AB$361,0))) -> 632 | M81: =IF($O81="","",INDEX(Scoring!$F$29:$F$361,MATCH($O81,Scoring!$AB$29:$AB$361,0))) -> 42181.7 | N81: =IF($O81="","",INDEX(Scoring!$AI$29:$AI$361,MATCH($O81,Scoring!$AB$29:$AB$361,0))) -> Australia | O81: =IFERROR(SMALL(Scoring!$AB$29:$AB$361,77),"") -> 4005
A82: =IF($O82="","",INT($O82/1000)) -> 4 | B82: =IF($O82="","",INDEX(Scoring!$A$29:$A$361,MATCH($O82,Scoring!$AB$29:$AB$361,0))) -> Cipla | C82: =IF($O82="","",IF(INDEX(Scoring!$P$29:$P$361,MATCH($O82,Scoring!$AB$29:$AB$361,0))="","–",INDEX(Scoring!$P$29:$P$361,MATCH($O82,Scoring!$AB$29:$AB$361,0)))) -> 6 | D82: =IF($O82="","",INDEX(Scoring!$Q$29:$Q$361,MATCH($O82,Scoring!$AB$29:$AB$361,0))) -> Priority 2 | E82: =IF($O82="","",INDEX(Scoring!$AJ$29:$AJ$361,MATCH($O82,Scoring!$AB$29:$AB$361,0))) -> Lower price · high volume | F82: =IF($O82="","",INDEX(Scoring!$B$29:$B$361,MATCH($O82,Scoring!$AB$29:$AB$361,0))) -> Testosterone Cypionate | G82: =IF($O82="","",INDEX(Scoring!$AG$29:$AG$361,MATCH($O82,Scoring!$AB$29:$AB$361,0))) -> Testosterone Cypionate | H82: =IF($O82="","",INDEX(Scoring!$C$29:$C$361,MATCH($O82,Scoring!$AB$29:$AB$361,0))) -> Endocrinology: testosterone replacement in male hypogonadism | I82: =IF($O82="","",INDEX(Scoring!$I$29:$I$361,MATCH($O82,Scoring!$AB$29:$AB$361,0))) -> Vial | J82: =IF($O82="","",INDEX(Scoring!$Z$29:$Z$361,MATCH($O82,Scoring!$AB$29:$AB$361,0))) -> 1000 mg/10 mL vial; 200 mg/1 mL vial | K82: =IF($O82="","",IF(INDEX(Scoring!$D$29:$D$361,MATCH($O82,Scoring!$AB$29:$AB$361,0))="",INDEX(Scoring!$AF$29:$AF$361,MATCH($O82,Scoring!$AB$29:$AB$361,0)),INDEX(Scoring!$D$29:$D$361,MATCH($O82,Scoring!$AB$29:$AB$361,0)))) -> 20.63 | L82: =IF($O82="","",INDEX(Scoring!$M$29:$M$361,MATCH($O82,Scoring!$AB$29:$AB$361,0))) -> 291 | M82: =IF($O82="","",INDEX(Scoring!$F$29:$F$361,MATCH($O82,Scoring!$AB$29:$AB$361,0))) -> 6893.7 | N82: =IF($O82="","",INDEX(Scoring!$AI$29:$AI$361,MATCH($O82,Scoring!$AB$29:$AB$361,0))) -> US | O82: =IFERROR(SMALL(Scoring!$AB$29:$AB$361,78),"") -> 4006
A83: =IF($O83="","",INT($O83/1000)) -> 4 | B83: =IF($O83="","",INDEX(Scoring!$A$29:$A$361,MATCH($O83,Scoring!$AB$29:$AB$361,0))) -> Cipla | C83: =IF($O83="","",IF(INDEX(Scoring!$P$29:$P$361,MATCH($O83,Scoring!$AB$29:$AB$361,0))="","–",INDEX(Scoring!$P$29:$P$361,MATCH($O83,Scoring!$AB$29:$AB$361,0)))) -> 7 | D83: =IF($O83="","",INDEX(Scoring!$Q$29:$Q$361,MATCH($O83,Scoring!$AB$29:$AB$361,0))) -> Priority 2 | E83: =IF($O83="","",INDEX(Scoring!$AJ$29:$AJ$361,MATCH($O83,Scoring!$AB$29:$AB$361,0))) -> Lower price · high volume | F83: =IF($O83="","",INDEX(Scoring!$B$29:$B$361,MATCH($O83,Scoring!$AB$29:$AB$361,0))) -> Cefepime | G83: =IF($O83="","",INDEX(Scoring!$AG$29:$AG$361,MATCH($O83,Scoring!$AB$29:$AB$361,0))) -> Cefect | H83: =IF($O83="","",INDEX(Scoring!$C$29:$C$361,MATCH($O83,Scoring!$AB$29:$AB$361,0))) -> Anti-infective: hospital Gram-negative infections, febrile neutropenia | I83: =IF($O83="","",INDEX(Scoring!$I$29:$I$361,MATCH($O83,Scoring!$AB$29:$AB$361,0))) -> Not stated | J83: =IF($O83="","",INDEX(Scoring!$Z$29:$Z$361,MATCH($O83,Scoring!$AB$29:$AB$361,0))) -> 1 g (container not stated); 2 g (container not stated) | K83: =IF($O83="","",IF(INDEX(Scoring!$D$29:$D$361,MATCH($O83,Scoring!$AB$29:$AB$361,0))="",INDEX(Scoring!$AF$29:$AF$361,MATCH($O83,Scoring!$AB$29:$AB$361,0)),INDEX(Scoring!$D$29:$D$361,MATCH($O83,Scoring!$AB$29:$AB$361,0)))) -> 24.42 | L83: =IF($O83="","",INDEX(Scoring!$M$29:$M$361,MATCH($O83,Scoring!$AB$29:$AB$361,0))) -> 288 | M83: =IF($O83="","",INDEX(Scoring!$F$29:$F$361,MATCH($O83,Scoring!$AB$29:$AB$361,0))) -> 6294.9 | N83: =IF($O83="","",INDEX(Scoring!$AI$29:$AI$361,MATCH($O83,Scoring!$AB$29:$AB$361,0))) -> South Africa | O83: =IFERROR(SMALL(Scoring!$AB$29:$AB$361,79),"") -> 4007
A84: =IF($O84="","",INT($O84/1000)) -> 4 | B84: =IF($O84="","",INDEX(Scoring!$A$29:$A$361,MATCH($O84,Scoring!$AB$29:$AB$361,0))) -> Cipla | C84: =IF($O84="","",IF(INDEX(Scoring!$P$29:$P$361,MATCH($O84,Scoring!$AB$29:$AB$361,0))="","–",INDEX(Scoring!$P$29:$P$361,MATCH($O84,Scoring!$AB$29:$AB$361,0)))) -> 8 | D84: =IF($O84="","",INDEX(Scoring!$Q$29:$Q$361,MATCH($O84,Scoring!$AB$29:$AB$361,0))) -> Priority 2 | E84: =IF($O84="","",INDEX(Scoring!$AJ$29:$AJ$361,MATCH($O84,Scoring!$AB$29:$AB$361,0))) -> Lower price · high volume | F84: =IF($O84="","",INDEX(Scoring!$B$29:$B$361,MATCH($O84,Scoring!$AB$29:$AB$361,0))) -> Hydrocortisone | G84: =IF($O84="","",INDEX(Scoring!$AG$29:$AG$361,MATCH($O84,Scoring!$AB$29:$AB$361,0))) -> Hydrocortisone Sodium Succinate; Cipla Hydrocortisone | H84: =IF($O84="","",INDEX(Scoring!$C$29:$C$361,MATCH($O84,Scoring!$AB$29:$AB$361,0))) -> Endocrinology and critical care: adrenal crisis, anaphylaxis, severe asthma, shock | I84: =IF($O84="","",INDEX(Scoring!$I$29:$I$361,MATCH($O84,Scoring!$AB$29:$AB$361,0))) -> Vial | J84: =IF($O84="","",INDEX(Scoring!$Z$29:$Z$361,MATCH($O84,Scoring!$AB$29:$AB$361,0))) -> 100 mg powder vial | K84: =IF($O84="","",IF(INDEX(Scoring!$D$29:$D$361,MATCH($O84,Scoring!$AB$29:$AB$361,0))="",INDEX(Scoring!$AF$29:$AF$361,MATCH($O84,Scoring!$AB$29:$AB$361,0)),INDEX(Scoring!$D$29:$D$361,MATCH($O84,Scoring!$AB$29:$AB$361,0)))) -> 23.15 | L84: =IF($O84="","",INDEX(Scoring!$M$29:$M$361,MATCH($O84,Scoring!$AB$29:$AB$361,0))) -> 325 | M84: =IF($O84="","",INDEX(Scoring!$F$29:$F$361,MATCH($O84,Scoring!$AB$29:$AB$361,0))) -> 4796.6 | N84: =IF($O84="","",INDEX(Scoring!$AI$29:$AI$361,MATCH($O84,Scoring!$AB$29:$AB$361,0))) -> US, Australia | O84: =IFERROR(SMALL(Scoring!$AB$29:$AB$361,80),"") -> 4008
A85: =IF($O85="","",INT($O85/1000)) -> 4 | B85: =IF($O85="","",INDEX(Scoring!$A$29:$A$361,MATCH($O85,Scoring!$AB$29:$AB$361,0))) -> Cipla | C85: =IF($O85="","",IF(INDEX(Scoring!$P$29:$P$361,MATCH($O85,Scoring!$AB$29:$AB$361,0))="","–",INDEX(Scoring!$P$29:$P$361,MATCH($O85,Scoring!$AB$29:$AB$361,0)))) -> 9 | D85: =IF($O85="","",INDEX(Scoring!$Q$29:$Q$361,MATCH($O85,Scoring!$AB$29:$AB$361,0))) -> Priority 2 | E85: =IF($O85="","",INDEX(Scoring!$AJ$29:$AJ$361,MATCH($O85,Scoring!$AB$29:$AB$361,0))) -> High price · lower volume | F85: =IF($O85="","",INDEX(Scoring!$B$29:$B$361,MATCH($O85,Scoring!$AB$29:$AB$361,0))) -> Isoprenaline (Isoproterenol) | G85: =IF($O85="","",INDEX(Scoring!$AG$29:$AG$361,MATCH($O85,Scoring!$AB$29:$AB$361,0))) -> Cipla Isoprenaline; Isocipraline | H85: =IF($O85="","",INDEX(Scoring!$C$29:$C$361,MATCH($O85,Scoring!$AB$29:$AB$361,0))) -> Cardiovascular: heart block, severe slow heart rate | I85: =IF($O85="","",INDEX(Scoring!$I$29:$I$361,MATCH($O85,Scoring!$AB$29:$AB$361,0))) -> Ampoule | J85: =IF($O85="","",INDEX(Scoring!$Z$29:$Z$361,MATCH($O85,Scoring!$AB$29:$AB$361,0))) -> 0.2 mg/1 mL ampoule; 1 mg/5 mL ampoule | K85: =IF($O85="","",IF(INDEX(Scoring!$D$29:$D$361,MATCH($O85,Scoring!$AB$29:$AB$361,0))="",INDEX(Scoring!$AF$29:$AF$361,MATCH($O85,Scoring!$AB$29:$AB$361,0)),INDEX(Scoring!$D$29:$D$361,MATCH($O85,Scoring!$AB$29:$AB$361,0)))) -> 82.51 | L85: =IF($O85="","",INDEX(Scoring!$M$29:$M$361,MATCH($O85,Scoring!$AB$29:$AB$361,0))) -> 87 | M85: =IF($O85="","",INDEX(Scoring!$F$29:$F$361,MATCH($O85,Scoring!$AB$29:$AB$361,0))) -> 2931.4 | N85: =IF($O85="","",INDEX(Scoring!$AI$29:$AI$361,MATCH($O85,Scoring!$AB$29:$AB$361,0))) -> Australia | O85: =IFERROR(SMALL(Scoring!$AB$29:$AB$361,81),"") -> 4009
A86: =IF($O86="","",INT($O86/1000)) -> 4 | B86: =IF($O86="","",INDEX(Scoring!$A$29:$A$361,MATCH($O86,Scoring!$AB$29:$AB$361,0))) -> Cipla | C86: =IF($O86="","",IF(INDEX(Scoring!$P$29:$P$361,MATCH($O86,Scoring!$AB$29:$AB$361,0))="","–",INDEX(Scoring!$P$29:$P$361,MATCH($O86,Scoring!$AB$29:$AB$361,0)))) -> 10 | D86: =IF($O86="","",INDEX(Scoring!$Q$29:$Q$361,MATCH($O86,Scoring!$AB$29:$AB$361,0))) -> Priority 2 | E86: =IF($O86="","",INDEX(Scoring!$AJ$29:$AJ$361,MATCH($O86,Scoring!$AB$29:$AB$361,0))) -> High price · lower volume | F86: =IF($O86="","",INDEX(Scoring!$B$29:$B$361,MATCH($O86,Scoring!$AB$29:$AB$361,0))) -> Phytonadione | G86: =IF($O86="","",INDEX(Scoring!$AG$29:$AG$361,MATCH($O86,Scoring!$AB$29:$AB$361,0))) -> Phytonadione | H86: =IF($O86="","",INDEX(Scoring!$C$29:$C$361,MATCH($O86,Scoring!$AB$29:$AB$361,0))) -> Haematology: vitamin K for newborn bleeding prevention, warfarin reversal | I86: =IF($O86="","",INDEX(Scoring!$I$29:$I$361,MATCH($O86,Scoring!$AB$29:$AB$361,0))) -> Vial, Prefilled syringe | J86: =IF($O86="","",INDEX(Scoring!$Z$29:$Z$361,MATCH($O86,Scoring!$AB$29:$AB$361,0))) -> 1 mg/0.5 mL pre-filled syringe; 10 mg/1 mL vial | K86: =IF($O86="","",IF(INDEX(Scoring!$D$29:$D$361,MATCH($O86,Scoring!$AB$29:$AB$361,0))="",INDEX(Scoring!$AF$29:$AF$361,MATCH($O86,Scoring!$AB$29:$AB$361,0)),INDEX(Scoring!$D$29:$D$361,MATCH($O86,Scoring!$AB$29:$AB$361,0)))) -> 39.89 | L86: =IF($O86="","",INDEX(Scoring!$M$29:$M$361,MATCH($O86,Scoring!$AB$29:$AB$361,0))) -> 24 | M86: =IF($O86="","",INDEX(Scoring!$F$29:$F$361,MATCH($O86,Scoring!$AB$29:$AB$361,0))) -> 2702.3 | N86: =IF($O86="","",INDEX(Scoring!$AI$29:$AI$361,MATCH($O86,Scoring!$AB$29:$AB$361,0))) -> US | O86: =IFERROR(SMALL(Scoring!$AB$29:$AB$361,82),"") -> 4010
A87: =IF($O87="","",INT($O87/1000)) -> 4 | B87: =IF($O87="","",INDEX(Scoring!$A$29:$A$361,MATCH($O87,Scoring!$AB$29:$AB$361,0))) -> Cipla | C87: =IF($O87="","",IF(INDEX(Scoring!$P$29:$P$361,MATCH($O87,Scoring!$AB$29:$AB$361,0))="","–",INDEX(Scoring!$P$29:$P$361,MATCH($O87,Scoring!$AB$29:$AB$361,0)))) -> 11 | D87: =IF($O87="","",INDEX(Scoring!$Q$29:$Q$361,MATCH($O87,Scoring!$AB$29:$AB$361,0))) -> Priority 2 | E87: =IF($O87="","",INDEX(Scoring!$AJ$29:$AJ$361,MATCH($O87,Scoring!$AB$29:$AB$361,0))) -> High price · lower volume | F87: =IF($O87="","",INDEX(Scoring!$B$29:$B$361,MATCH($O87,Scoring!$AB$29:$AB$361,0))) -> Testosterone Undecanoate | G87: =IF($O87="","",INDEX(Scoring!$AG$29:$AG$361,MATCH($O87,Scoring!$AB$29:$AB$361,0))) -> Testosterone Cipla | H87: =IF($O87="","",INDEX(Scoring!$C$29:$C$361,MATCH($O87,Scoring!$AB$29:$AB$361,0))) -> Endocrinology: long-acting testosterone replacement in male hypogonadism | I87: =IF($O87="","",INDEX(Scoring!$I$29:$I$361,MATCH($O87,Scoring!$AB$29:$AB$361,0))) -> Vial | J87: =IF($O87="","",INDEX(Scoring!$Z$29:$Z$361,MATCH($O87,Scoring!$AB$29:$AB$361,0))) -> 1000 mg/4 mL vial | K87: =IF($O87="","",IF(INDEX(Scoring!$D$29:$D$361,MATCH($O87,Scoring!$AB$29:$AB$361,0))="",INDEX(Scoring!$AF$29:$AF$361,MATCH($O87,Scoring!$AB$29:$AB$361,0)),INDEX(Scoring!$D$29:$D$361,MATCH($O87,Scoring!$AB$29:$AB$361,0)))) -> 118.45 | L87: =IF($O87="","",INDEX(Scoring!$M$29:$M$361,MATCH($O87,Scoring!$AB$29:$AB$361,0))) -> 132 | M87: =IF($O87="","",INDEX(Scoring!$F$29:$F$361,MATCH($O87,Scoring!$AB$29:$AB$361,0))) -> 184.9 | N87: =IF($O87="","",INDEX(Scoring!$AI$29:$AI$361,MATCH($O87,Scoring!$AB$29:$AB$361,0))) -> South Africa | O87: =IFERROR(SMALL(Scoring!$AB$29:$AB$361,83),"") -> 4011
A88: =IF($O88="","",INT($O88/1000)) -> 4 | B88: =IF($O88="","",INDEX(Scoring!$A$29:$A$361,MATCH($O88,Scoring!$AB$29:$AB$361,0))) -> Cipla | C88: =IF($O88="","",IF(INDEX(Scoring!$P$29:$P$361,MATCH($O88,Scoring!$AB$29:$AB$361,0))="","–",INDEX(Scoring!$P$29:$P$361,MATCH($O88,Scoring!$AB$29:$AB$361,0)))) -> 12 | D88: =IF($O88="","",INDEX(Scoring!$Q$29:$Q$361,MATCH($O88,Scoring!$AB$29:$AB$361,0))) -> Priority 2 | E88: =IF($O88="","",INDEX(Scoring!$AJ$29:$AJ$361,MATCH($O88,Scoring!$AB$29:$AB$361,0))) -> High price · lower volume | F88: =IF($O88="","",INDEX(Scoring!$B$29:$B$361,MATCH($O88,Scoring!$AB$29:$AB$361,0))) -> Lanreotide | G88: =IF($O88="","",INDEX(Scoring!$AG$29:$AG$361,MATCH($O88,Scoring!$AB$29:$AB$361,0))) -> Lanreotide Acetate | H88: =IF($O88="","",INDEX(Scoring!$C$29:$C$361,MATCH($O88,Scoring!$AB$29:$AB$361,0))) -> Endocrinology and oncology: acromegaly, neuroendocrine tumours | I88: =IF($O88="","",INDEX(Scoring!$I$29:$I$361,MATCH($O88,Scoring!$AB$29:$AB$361,0))) -> Prefilled syringe | J88: =IF($O88="","",INDEX(Scoring!$Z$29:$Z$361,MATCH($O88,Scoring!$AB$29:$AB$361,0))) -> 60 mg/0.2 mL pre-filled syringe; 90 mg/0.3 mL pre-filled syringe; 120 mg/0.5 mL pre-filled syringe | K88: =IF($O88="","",IF(INDEX(Scoring!$D$29:$D$361,MATCH($O88,Scoring!$AB$29:$AB$361,0))="",INDEX(Scoring!$AF$29:$AF$361,MATCH($O88,Scoring!$AB$29:$AB$361,0)),INDEX(Scoring!$D$29:$D$361,MATCH($O88,Scoring!$AB$29:$AB$361,0)))) -> 5970.59 | L88: =IF($O88="","",INDEX(Scoring!$M$29:$M$361,MATCH($O88,Scoring!$AB$29:$AB$361,0))) -> 25 | M88: =IF($O88="","",INDEX(Scoring!$F$29:$F$361,MATCH($O88,Scoring!$AB$29:$AB$361,0))) -> 0.2 | N88: =IF($O88="","",INDEX(Scoring!$AI$29:$AI$361,MATCH($O88,Scoring!$AB$29:$AB$361,0))) -> US | O88: =IFERROR(SMALL(Scoring!$AB$29:$AB$361,84),"") -> 4012
A89: =IF($O89="","",INT($O89/1000)) -> 4 | B89: =IF($O89="","",INDEX(Scoring!$A$29:$A$361,MATCH($O89,Scoring!$AB$29:$AB$361,0))) -> Cipla | C89: =IF($O89="","",IF(INDEX(Scoring!$P$29:$P$361,MATCH($O89,Scoring!$AB$29:$AB$361,0))="","–",INDEX(Scoring!$P$29:$P$361,MATCH($O89,Scoring!$AB$29:$AB$361,0)))) -> 13 | D89: =IF($O89="","",INDEX(Scoring!$Q$29:$Q$361,MATCH($O89,Scoring!$AB$29:$AB$361,0))) -> Priority 3 | E89: =IF($O89="","",INDEX(Scoring!$AJ$29:$AJ$361,MATCH($O89,Scoring!$AB$29:$AB$361,0))) -> Lower price · lower volume | F89: =IF($O89="","",INDEX(Scoring!$B$29:$B$361,MATCH($O89,Scoring!$AB$29:$AB$361,0))) -> Teicoplanin | G89: =IF($O89="","",INDEX(Scoring!$AG$29:$AG$361,MATCH($O89,Scoring!$AB$29:$AB$361,0))) -> Cipla Teicoplanin | H89: =IF($O89="","",INDEX(Scoring!$C$29:$C$361,MATCH($O89,Scoring!$AB$29:$AB$361,0))) -> Anti-infective: MRSA and serious Gram-positive infections | I89: =IF($O89="","",INDEX(Scoring!$I$29:$I$361,MATCH($O89,Scoring!$AB$29:$AB$361,0))) -> Vial | J89: =IF($O89="","",INDEX(Scoring!$Z$29:$Z$361,MATCH($O89,Scoring!$AB$29:$AB$361,0))) -> 400 mg in 3 mL powder vial | K89: =IF($O89="","",IF(INDEX(Scoring!$D$29:$D$361,MATCH($O89,Scoring!$AB$29:$AB$361,0))="",INDEX(Scoring!$AF$29:$AF$361,MATCH($O89,Scoring!$AB$29:$AB$361,0)),INDEX(Scoring!$D$29:$D$361,MATCH($O89,Scoring!$AB$29:$AB$361,0)))) -> 13.97 | L89: =IF($O89="","",INDEX(Scoring!$M$29:$M$361,MATCH($O89,Scoring!$AB$29:$AB$361,0))) -> 99 | M89: =IF($O89="","",INDEX(Scoring!$F$29:$F$361,MATCH($O89,Scoring!$AB$29:$AB$361,0))) -> 6632.6 | N89: =IF($O89="","",INDEX(Scoring!$AI$29:$AI$361,MATCH($O89,Scoring!$AB$29:$AB$361,0))) -> South Africa | O89: =IFERROR(SMALL(Scoring!$AB$29:$AB$361,85),"") -> 4013
A90: =IF($O90="","",INT($O90/1000)) -> 4 | B90: =IF($O90="","",INDEX(Scoring!$A$29:$A$361,MATCH($O90,Scoring!$AB$29:$AB$361,0))) -> Cipla | C90: =IF($O90="","",IF(INDEX(Scoring!$P$29:$P$361,MATCH($O90,Scoring!$AB$29:$AB$361,0))="","–",INDEX(Scoring!$P$29:$P$361,MATCH($O90,Scoring!$AB$29:$AB$361,0)))) -> 14 | D90: =IF($O90="","",INDEX(Scoring!$Q$29:$Q$361,MATCH($O90,Scoring!$AB$29:$AB$361,0))) -> Priority 3 | E90: =IF($O90="","",INDEX(Scoring!$AJ$29:$AJ$361,MATCH($O90,Scoring!$AB$29:$AB$361,0))) -> Lower price · lower volume | F90: =IF($O90="","",INDEX(Scoring!$B$29:$B$361,MATCH($O90,Scoring!$AB$29:$AB$361,0))) -> Medroxyprogesterone Acetate | G90: =IF($O90="","",INDEX(Scoring!$AG$29:$AG$361,MATCH($O90,Scoring!$AB$29:$AB$361,0))) -> Cipla Medroxyprogesterone | H90: =IF($O90="","",INDEX(Scoring!$C$29:$C$361,MATCH($O90,Scoring!$AB$29:$AB$361,0))) -> Women's health: three-monthly contraceptive injection | I90: =IF($O90="","",INDEX(Scoring!$I$29:$I$361,MATCH($O90,Scoring!$AB$29:$AB$361,0))) -> Vial | J90: =IF($O90="","",INDEX(Scoring!$Z$29:$Z$361,MATCH($O90,Scoring!$AB$29:$AB$361,0))) -> 150 mg/1 mL vial | K90: =IF($O90="","",IF(INDEX(Scoring!$D$29:$D$361,MATCH($O90,Scoring!$AB$29:$AB$361,0))="",INDEX(Scoring!$AF$29:$AF$361,MATCH($O90,Scoring!$AB$29:$AB$361,0)),INDEX(Scoring!$D$29:$D$361,MATCH($O90,Scoring!$AB$29:$AB$361,0)))) -> 19.65 | L90: =IF($O90="","",INDEX(Scoring!$M$29:$M$361,MATCH($O90,Scoring!$AB$29:$AB$361,0))) -> 41 | M90: =IF($O90="","",INDEX(Scoring!$F$29:$F$361,MATCH($O90,Scoring!$AB$29:$AB$361,0))) -> 2690.1 | N90: =IF($O90="","",INDEX(Scoring!$AI$29:$AI$361,MATCH($O90,Scoring!$AB$29:$AB$361,0))) -> Australia | O90: =IFERROR(SMALL(Scoring!$AB$29:$AB$361,86),"") -> 4014
A91: =IF($O91="","",INT($O91/1000)) -> 4 | B91: =IF($O91="","",INDEX(Scoring!$A$29:$A$361,MATCH($O91,Scoring!$AB$29:$AB$361,0))) -> Cipla | C91: =IF($O91="","",IF(INDEX(Scoring!$P$29:$P$361,MATCH($O91,Scoring!$AB$29:$AB$361,0))="","–",INDEX(Scoring!$P$29:$P$361,MATCH($O91,Scoring!$AB$29:$AB$361,0)))) -> – | D91: =IF($O91="","",INDEX(Scoring!$Q$29:$Q$361,MATCH($O91,Scoring!$AB$29:$AB$361,0))) -> Excluded – price ≤ $5 | E91: =IF($O91="","",INDEX(Scoring!$AJ$29:$AJ$361,MATCH($O91,Scoring!$AB$29:$AB$361,0))) | F91: =IF($O91="","",INDEX(Scoring!$B$29:$B$361,MATCH($O91,Scoring!$AB$29:$AB$361,0))) -> Phenylephrine | G91: =IF($O91="","",INDEX(Scoring!$AG$29:$AG$361,MATCH($O91,Scoring!$AB$29:$AB$361,0))) -> Phenylephrine Cipla | H91: =IF($O91="","",INDEX(Scoring!$C$29:$C$361,MATCH($O91,Scoring!$AB$29:$AB$361,0))) -> Anaesthesia: low blood pressure during anaesthesia | I91: =IF($O91="","",INDEX(Scoring!$I$29:$I$361,MATCH($O91,Scoring!$AB$29:$AB$361,0))) -> Vial | J91: =IF($O91="","",INDEX(Scoring!$Z$29:$Z$361,MATCH($O91,Scoring!$AB$29:$AB$361,0))) -> 10 mg/1 mL vial | K91: =IF($O91="","",IF(INDEX(Scoring!$D$29:$D$361,MATCH($O91,Scoring!$AB$29:$AB$361,0))="",INDEX(Scoring!$AF$29:$AF$361,MATCH($O91,Scoring!$AB$29:$AB$361,0)),INDEX(Scoring!$D$29:$D$361,MATCH($O91,Scoring!$AB$29:$AB$361,0)))) -> 1 | L91: =IF($O91="","",INDEX(Scoring!$M$29:$M$361,MATCH($O91,Scoring!$AB$29:$AB$361,0))) -> 226 | M91: =IF($O91="","",INDEX(Scoring!$F$29:$F$361,MATCH($O91,Scoring!$AB$29:$AB$361,0))) -> 5695.2 | N91: =IF($O91="","",INDEX(Scoring!$AI$29:$AI$361,MATCH($O91,Scoring!$AB$29:$AB$361,0))) -> Australia | O91: =IFERROR(SMALL(Scoring!$AB$29:$AB$361,87),"") -> 4901
A92: =IF($O92="","",INT($O92/1000)) -> 5 | B92: =IF($O92="","",INDEX(Scoring!$A$29:$A$361,MATCH($O92,Scoring!$AB$29:$AB$361,0))) -> Emcure | C92: =IF($O92="","",IF(INDEX(Scoring!$P$29:$P$361,MATCH($O92,Scoring!$AB$29:$AB$361,0))="","–",INDEX(Scoring!$P$29:$P$361,MATCH($O92,Scoring!$AB$29:$AB$361,0)))) -> 1 | D92: =IF($O92="","",INDEX(Scoring!$Q$29:$Q$361,MATCH($O92,Scoring!$AB$29:$AB$361,0))) -> Priority 1 | E92: =IF($O92="","",INDEX(Scoring!$AJ$29:$AJ$361,MATCH($O92,Scoring!$AB$29:$AB$361,0))) -> High price · high volume | F92: =IF($O92="","",INDEX(Scoring!$B$29:$B$361,MATCH($O92,Scoring!$AB$29:$AB$361,0))) -> Azacitidine | G92: =IF($O92="","",INDEX(Scoring!$AG$29:$AG$361,MATCH($O92,Scoring!$AB$29:$AB$361,0))) -> Azacitidine Tillomed; Azacitidin Tillomed | H92: =IF($O92="","",INDEX(Scoring!$C$29:$C$361,MATCH($O92,Scoring!$AB$29:$AB$361,0))) -> Oncology: myelodysplastic syndromes, acute myeloid leukaemia | I92: =IF($O92="","",INDEX(Scoring!$I$29:$I$361,MATCH($O92,Scoring!$AB$29:$AB$361,0))) -> Vial | J92: =IF($O92="","",INDEX(Scoring!$Z$29:$Z$361,MATCH($O92,Scoring!$AB$29:$AB$361,0))) -> 25 mg/mL powder vial; 100 mg powder vial | K92: =IF($O92="","",IF(INDEX(Scoring!$D$29:$D$361,MATCH($O92,Scoring!$AB$29:$AB$361,0))="",INDEX(Scoring!$AF$29:$AF$361,MATCH($O92,Scoring!$AB$29:$AB$361,0)),INDEX(Scoring!$D$29:$D$361,MATCH($O92,Scoring!$AB$29:$AB$361,0)))) -> 410.89 | L92: =IF($O92="","",INDEX(Scoring!$M$29:$M$361,MATCH($O92,Scoring!$AB$29:$AB$361,0))) -> 632 | M92: =IF($O92="","",INDEX(Scoring!$F$29:$F$361,MATCH($O92,Scoring!$AB$29:$AB$361,0))) -> 42181.7 | N92: =IF($O92="","",INDEX(Scoring!$AI$29:$AI$361,MATCH($O92,Scoring!$AB$29:$AB$361,0))) -> UK, UK-NI | EU/EEA (9): Germany, France, Netherlands, Austria + 5 more | O92: =IFERROR(SMALL(Scoring!$AB$29:$AB$361,88),"") -> 5001
A93: =IF($O93="","",INT($O93/1000)) -> 5 | B93: =IF($O93="","",INDEX(Scoring!$A$29:$A$361,MATCH($O93,Scoring!$AB$29:$AB$361,0))) -> Emcure | C93: =IF($O93="","",IF(INDEX(Scoring!$P$29:$P$361,MATCH($O93,Scoring!$AB$29:$AB$361,0))="","–",INDEX(Scoring!$P$29:$P$361,MATCH($O93,Scoring!$AB$29:$AB$361,0)))) -> 2 | D93: =IF($O93="","",INDEX(Scoring!$Q$29:$Q$361,MATCH($O93,Scoring!$AB$29:$AB$361,0))) -> Priority 1 | E93: =IF($O93="","",INDEX(Scoring!$AJ$29:$AJ$361,MATCH($O93,Scoring!$AB$29:$AB$361,0))) -> High price · high volume | F93: =IF($O93="","",INDEX(Scoring!$B$29:$B$361,MATCH($O93,Scoring!$AB$29:$AB$361,0))) -> Bortezomib | G93: =IF($O93="","",INDEX(Scoring!$AG$29:$AG$361,MATCH($O93,Scoring!$AB$29:$AB$361,0))) -> Bortezomib Tillomed; Bortezomib | H93: =IF($O93="","",INDEX(Scoring!$C$29:$C$361,MATCH($O93,Scoring!$AB$29:$AB$361,0))) -> Oncology: multiple myeloma, mantle cell lymphoma | I93: =IF($O93="","",INDEX(Scoring!$I$29:$I$361,MATCH($O93,Scoring!$AB$29:$AB$361,0))) -> Vial | J93: =IF($O93="","",INDEX(Scoring!$Z$29:$Z$361,MATCH($O93,Scoring!$AB$29:$AB$361,0))) -> 3.5 mg powder vial; 3.5 mg in 10 mL powder vial | K93: =IF($O93="","",IF(INDEX(Scoring!$D$29:$D$361,MATCH($O93,Scoring!$AB$29:$AB$361,0))="",INDEX(Scoring!$AF$29:$AF$361,MATCH($O93,Scoring!$AB$29:$AB$361,0)),INDEX(Scoring!$D$29:$D$361,MATCH($O93,Scoring!$AB$29:$AB$361,0)))) -> 1212.91 | L93: =IF($O93="","",INDEX(Scoring!$M$29:$M$361,MATCH($O93,Scoring!$AB$29:$AB$361,0))) -> 905 | M93: =IF($O93="","",INDEX(Scoring!$F$29:$F$361,MATCH($O93,Scoring!$AB$29:$AB$361,0))) -> 28093.4 | N93: =IF($O93="","",INDEX(Scoring!$AI$29:$AI$361,MATCH($O93,Scoring!$AB$29:$AB$361,0))) -> Canada, UK-NI | EU/EEA (2): Germany, France | O93: =IFERROR(SMALL(Scoring!$AB$29:$AB$361,89),"") -> 5002
A94: =IF($O94="","",INT($O94/1000)) -> 5 | B94: =IF($O94="","",INDEX(Scoring!$A$29:$A$361,MATCH($O94,Scoring!$AB$29:$AB$361,0))) -> Emcure | C94: =IF($O94="","",IF(INDEX(Scoring!$P$29:$P$361,MATCH($O94,Scoring!$AB$29:$AB$361,0))="","–",INDEX(Scoring!$P$29:$P$361,MATCH($O94,Scoring!$AB$29:$AB$361,0)))) -> 3 | D94: =IF($O94="","",INDEX(Scoring!$Q$29:$Q$361,MATCH($O94,Scoring!$AB$29:$AB$361,0))) -> Priority 1 | E94: =IF($O94="","",INDEX(Scoring!$AJ$29:$AJ$361,MATCH($O94,Scoring!$AB$29:$AB$361,0))) -> High price · high volume | F94: =IF($O94="","",INDEX(Scoring!$B$29:$B$361,MATCH($O94,Scoring!$AB$29:$AB$361,0))) -> Amikacin | G94: =IF($O94="","",INDEX(Scoring!$AG$29:$AG$361,MATCH($O94,Scoring!$AB$29:$AB$361,0))) -> Amikacin; Amikacin Tillomed Laboratories; Amikacin Sulfate (+1 more) | H94: =IF($O94="","",INDEX(Scoring!$C$29:$C$361,MATCH($O94,Scoring!$AB$29:$AB$361,0))) -> Anti-infective: serious and drug-resistant Gram-negative infections, resistant TB | I94: =IF($O94="","",INDEX(Scoring!$I$29:$I$361,MATCH($O94,Scoring!$AB$29:$AB$361,0))) -> Vial | J94: =IF($O94="","",INDEX(Scoring!$Z$29:$Z$361,MATCH($O94,Scoring!$AB$29:$AB$361,0))) -> 500 mg/2 mL vial | K94: =IF($O94="","",IF(INDEX(Scoring!$D$29:$D$361,MATCH($O94,Scoring!$AB$29:$AB$361,0))="",INDEX(Scoring!$AF$29:$AF$361,MATCH($O94,Scoring!$AB$29:$AB$361,0)),INDEX(Scoring!$D$29:$D$361,MATCH($O94,Scoring!$AB$29:$AB$361,0)))) -> 27.98 | L94: =IF($O94="","",INDEX(Scoring!$M$29:$M$361,MATCH($O94,Scoring!$AB$29:$AB$361,0))) -> 657 | M94: =IF($O94="","",INDEX(Scoring!$F$29:$F$361,MATCH($O94,Scoring!$AB$29:$AB$361,0))) -> 8433.6 | N94: =IF($O94="","",INDEX(Scoring!$AI$29:$AI$361,MATCH($O94,Scoring!$AB$29:$AB$361,0))) -> UK, Canada, Australia, UK-NI | EU/EEA (1): Malta | O94: =IFERROR(SMALL(Scoring!$AB$29:$AB$361,90),"") -> 5003
A95: =IF($O95="","",INT($O95/1000)) -> 5 | B95: =IF($O95="","",INDEX(Scoring!$A$29:$A$361,MATCH($O95,Scoring!$AB$29:$AB$361,0))) -> Emcure | C95: =IF($O95="","",IF(INDEX(Scoring!$P$29:$P$361,MATCH($O95,Scoring!$AB$29:$AB$361,0))="","–",INDEX(Scoring!$P$29:$P$361,MATCH($O95,Scoring!$AB$29:$AB$361,0)))) -> 4 | D95: =IF($O95="","",INDEX(Scoring!$Q$29:$Q$361,MATCH($O95,Scoring!$AB$29:$AB$361,0))) -> Priority 2 | E95: =IF($O95="","",INDEX(Scoring!$AJ$29:$AJ$361,MATCH($O95,Scoring!$AB$29:$AB$361,0))) -> Lower price · high volume | F95: =IF($O95="","",INDEX(Scoring!$B$29:$B$361,MATCH($O95,Scoring!$AB$29:$AB$361,0))) -> Ampicillin | G95: =IF($O95="","",INDEX(Scoring!$AG$29:$AG$361,MATCH($O95,Scoring!$AB$29:$AB$361,0))) -> Ampicillina Tillomed | H95: =IF($O95="","",INDEX(Scoring!$C$29:$C$361,MATCH($O95,Scoring!$AB$29:$AB$361,0))) -> Anti-infective: meningitis, endocarditis, neonatal sepsis | I95: =IF($O95="","",INDEX(Scoring!$I$29:$I$361,MATCH($O95,Scoring!$AB$29:$AB$361,0))) -> Vial | J95: =IF($O95="","",INDEX(Scoring!$Z$29:$Z$361,MATCH($O95,Scoring!$AB$29:$AB$361,0))) -> 1 g vial | K95: =IF($O95="","",IF(INDEX(Scoring!$D$29:$D$361,MATCH($O95,Scoring!$AB$29:$AB$361,0))="",INDEX(Scoring!$AF$29:$AF$361,MATCH($O95,Scoring!$AB$29:$AB$361,0)),INDEX(Scoring!$D$29:$D$361,MATCH($O95,Scoring!$AB$29:$AB$361,0)))) -> 9.04 | L95: =IF($O95="","",INDEX(Scoring!$M$29:$M$361,MATCH($O95,Scoring!$AB$29:$AB$361,0))) -> 934 | M95: =IF($O95="","",INDEX(Scoring!$F$29:$F$361,MATCH($O95,Scoring!$AB$29:$AB$361,0))) -> 35129.8 | N95: =IF($O95="","",INDEX(Scoring!$AI$29:$AI$361,MATCH($O95,Scoring!$AB$29:$AB$361,0))) -> EU/EEA (1): Italy | O95: =IFERROR(SMALL(Scoring!$AB$29:$AB$361,91),"") -> 5004
A96: =IF($O96="","",INT($O96/1000)) -> 5 | B96: =IF($O96="","",INDEX(Scoring!$A$29:$A$361,MATCH($O96,Scoring!$AB$29:$AB$361,0))) -> Emcure | C96: =IF($O96="","",IF(INDEX(Scoring!$P$29:$P$361,MATCH($O96,Scoring!$AB$29:$AB$361,0))="","–",INDEX(Scoring!$P$29:$P$361,MATCH($O96,Scoring!$AB$29:$AB$361,0)))) -> 5 | D96: =IF($O96="","",INDEX(Scoring!$Q$29:$Q$361,MATCH($O96,Scoring!$AB$29:$AB$361,0))) -> Priority 2 | E96: =IF($O96="","",INDEX(Scoring!$AJ$29:$AJ$361,MATCH($O96,Scoring!$AB$29:$AB$361,0))) -> Lower price · high volume | F96: =IF($O96="","",INDEX(Scoring!$B$29:$B$361,MATCH($O96,Scoring!$AB$29:$AB$361,0))) -> Ondansetron | G96: =IF($O96="","",INDEX(Scoring!$AG$29:$AG$361,MATCH($O96,Scoring!$AB$29:$AB$361,0))) -> Ondansetron Tillomed | H96: =IF($O96="","",INDEX(Scoring!$C$29:$C$361,MATCH($O96,Scoring!$AB$29:$AB$361,0))) -> Oncology support: nausea and vomiting from chemotherapy and surgery | I96: =IF($O96="","",INDEX(Scoring!$I$29:$I$361,MATCH($O96,Scoring!$AB$29:$AB$361,0))) -> Ampoule | J96: =IF($O96="","",INDEX(Scoring!$Z$29:$Z$361,MATCH($O96,Scoring!$AB$29:$AB$361,0))) -> 4 mg/2 mL ampoule | K96: =IF($O96="","",IF(INDEX(Scoring!$D$29:$D$361,MATCH($O96,Scoring!$AB$29:$AB$361,0))="",INDEX(Scoring!$AF$29:$AF$361,MATCH($O96,Scoring!$AB$29:$AB$361,0)),INDEX(Scoring!$D$29:$D$361,MATCH($O96,Scoring!$AB$29:$AB$361,0)))) -> 5.32 | L96: =IF($O96="","",INDEX(Scoring!$M$29:$M$361,MATCH($O96,Scoring!$AB$29:$AB$361,0))) -> 963 | M96: =IF($O96="","",INDEX(Scoring!$F$29:$F$361,MATCH($O96,Scoring!$AB$29:$AB$361,0))) -> 17590.5 | N96: =IF($O96="","",INDEX(Scoring!$AI$29:$AI$361,MATCH($O96,Scoring!$AB$29:$AB$361,0))) -> EU/EEA (1): Germany | O96: =IFERROR(SMALL(Scoring!$AB$29:$AB$361,92),"") -> 5005
A97: =IF($O97="","",INT($O97/1000)) -> 5 | B97: =IF($O97="","",INDEX(Scoring!$A$29:$A$361,MATCH($O97,Scoring!$AB$29:$AB$361,0))) -> Emcure | C97: =IF($O97="","",IF(INDEX(Scoring!$P$29:$P$361,MATCH($O97,Scoring!$AB$29:$AB$361,0))="","–",INDEX(Scoring!$P$29:$P$361,MATCH($O97,Scoring!$AB$29:$AB$361,0)))) -> 6 | D97: =IF($O97="","",INDEX(Scoring!$Q$29:$Q$361,MATCH($O97,Scoring!$AB$29:$AB$361,0))) -> Priority 2 | E97: =IF($O97="","",INDEX(Scoring!$AJ$29:$AJ$361,MATCH($O97,Scoring!$AB$29:$AB$361,0))) -> High price · lower volume | F97: =IF($O97="","",INDEX(Scoring!$B$29:$B$361,MATCH($O97,Scoring!$AB$29:$AB$361,0))) -> Plerixafor | G97: =IF($O97="","",INDEX(Scoring!$AG$29:$AG$361,MATCH($O97,Scoring!$AB$29:$AB$361,0))) -> Plerixafor; Plerixafor Tillomed | H97: =IF($O97="","",INDEX(Scoring!$C$29:$C$361,MATCH($O97,Scoring!$AB$29:$AB$361,0))) -> Oncology support: stem cell mobilisation in myeloma and lymphoma | I97: =IF($O97="","",INDEX(Scoring!$I$29:$I$361,MATCH($O97,Scoring!$AB$29:$AB$361,0))) -> Vial | J97: =IF($O97="","",INDEX(Scoring!$Z$29:$Z$361,MATCH($O97,Scoring!$AB$29:$AB$361,0))) -> 24 mg/1.2 mL vial | K97: =IF($O97="","",IF(INDEX(Scoring!$D$29:$D$361,MATCH($O97,Scoring!$AB$29:$AB$361,0))="",INDEX(Scoring!$AF$29:$AF$361,MATCH($O97,Scoring!$AB$29:$AB$361,0)),INDEX(Scoring!$D$29:$D$361,MATCH($O97,Scoring!$AB$29:$AB$361,0)))) -> 6173.01 | L97: =IF($O97="","",INDEX(Scoring!$M$29:$M$361,MATCH($O97,Scoring!$AB$29:$AB$361,0))) -> 47 | M97: =IF($O97="","",INDEX(Scoring!$F$29:$F$361,MATCH($O97,Scoring!$AB$29:$AB$361,0))) -> 7904.7 | N97: =IF($O97="","",INDEX(Scoring!$AI$29:$AI$361,MATCH($O97,Scoring!$AB$29:$AB$361,0))) -> UK | EU/EEA (3): Germany, France, Italy | O97: =IFERROR(SMALL(Scoring!$AB$29:$AB$361,93),"") -> 5006
A98: =IF($O98="","",INT($O98/1000)) -> 5 | B98: =IF($O98="","",INDEX(Scoring!$A$29:$A$361,MATCH($O98,Scoring!$AB$29:$AB$361,0))) -> Emcure | C98: =IF($O98="","",IF(INDEX(Scoring!$P$29:$P$361,MATCH($O98,Scoring!$AB$29:$AB$361,0))="","–",INDEX(Scoring!$P$29:$P$361,MATCH($O98,Scoring!$AB$29:$AB$361,0)))) -> 7 | D98: =IF($O98="","",INDEX(Scoring!$Q$29:$Q$361,MATCH($O98,Scoring!$AB$29:$AB$361,0))) -> Priority 2 | E98: =IF($O98="","",INDEX(Scoring!$AJ$29:$AJ$361,MATCH($O98,Scoring!$AB$29:$AB$361,0))) -> High price · lower volume | F98: =IF($O98="","",INDEX(Scoring!$B$29:$B$361,MATCH($O98,Scoring!$AB$29:$AB$361,0))) -> Isoprenaline (Isoproterenol) | G98: =IF($O98="","",INDEX(Scoring!$AG$29:$AG$361,MATCH($O98,Scoring!$AB$29:$AB$361,0))) -> Isoproterenol Hydrochloride | H98: =IF($O98="","",INDEX(Scoring!$C$29:$C$361,MATCH($O98,Scoring!$AB$29:$AB$361,0))) -> Cardiovascular: heart block, severe slow heart rate | I98: =IF($O98="","",INDEX(Scoring!$I$29:$I$361,MATCH($O98,Scoring!$AB$29:$AB$361,0))) -> Vial | J98: =IF($O98="","",INDEX(Scoring!$Z$29:$Z$361,MATCH($O98,Scoring!$AB$29:$AB$361,0))) -> 0.2 mg/1 mL vial; 1 mg/5 mL vial | K98: =IF($O98="","",IF(INDEX(Scoring!$D$29:$D$361,MATCH($O98,Scoring!$AB$29:$AB$361,0))="",INDEX(Scoring!$AF$29:$AF$361,MATCH($O98,Scoring!$AB$29:$AB$361,0)),INDEX(Scoring!$D$29:$D$361,MATCH($O98,Scoring!$AB$29:$AB$361,0)))) -> 25.24 | L98: =IF($O98="","",INDEX(Scoring!$M$29:$M$361,MATCH($O98,Scoring!$AB$29:$AB$361,0))) -> 87 | M98: =IF($O98="","",INDEX(Scoring!$F$29:$F$361,MATCH($O98,Scoring!$AB$29:$AB$361,0))) -> 2931.4 | N98: =IF($O98="","",INDEX(Scoring!$AI$29:$AI$361,MATCH($O98,Scoring!$AB$29:$AB$361,0))) -> Canada | EU/EEA (2): France, Portugal | O98: =IFERROR(SMALL(Scoring!$AB$29:$AB$361,94),"") -> 5007
A99: =IF($O99="","",INT($O99/1000)) -> 5 | B99: =IF($O99="","",INDEX(Scoring!$A$29:$A$361,MATCH($O99,Scoring!$AB$29:$AB$361,0))) -> Emcure | C99: =IF($O99="","",IF(INDEX(Scoring!$P$29:$P$361,MATCH($O99,Scoring!$AB$29:$AB$361,0))="","–",INDEX(Scoring!$P$29:$P$361,MATCH($O99,Scoring!$AB$29:$AB$361,0)))) -> 8 | D99: =IF($O99="","",INDEX(Scoring!$Q$29:$Q$361,MATCH($O99,Scoring!$AB$29:$AB$361,0))) -> Priority 2 | E99: =IF($O99="","",INDEX(Scoring!$AJ$29:$AJ$361,MATCH($O99,Scoring!$AB$29:$AB$361,0))) -> Lower price · high volume | F99: =IF($O99="","",INDEX(Scoring!$B$29:$B$361,MATCH($O99,Scoring!$AB$29:$AB$361,0))) -> Neostigmine | G99: =IF($O99="","",INDEX(Scoring!$AG$29:$AG$361,MATCH($O99,Scoring!$AB$29:$AB$361,0))) -> Neostigmine Methylsulfate | H99: =IF($O99="","",INDEX(Scoring!$C$29:$C$361,MATCH($O99,Scoring!$AB$29:$AB$361,0))) -> Anaesthesia and neurology: reversal of muscle relaxants after surgery, myasthenia gravis | I99: =IF($O99="","",INDEX(Scoring!$I$29:$I$361,MATCH($O99,Scoring!$AB$29:$AB$361,0))) -> Vial | J99: =IF($O99="","",INDEX(Scoring!$Z$29:$Z$361,MATCH($O99,Scoring!$AB$29:$AB$361,0))) -> 5 mg/10 mL vial; 10 mg/10 mL vial | K99: =IF($O99="","",IF(INDEX(Scoring!$D$29:$D$361,MATCH($O99,Scoring!$AB$29:$AB$361,0))="",INDEX(Scoring!$AF$29:$AF$361,MATCH($O99,Scoring!$AB$29:$AB$361,0)),INDEX(Scoring!$D$29:$D$361,MATCH($O99,Scoring!$AB$29:$AB$361,0)))) -> 7.98 | L99: =IF($O99="","",INDEX(Scoring!$M$29:$M$361,MATCH($O99,Scoring!$AB$29:$AB$361,0))) -> 234 | M99: =IF($O99="","",INDEX(Scoring!$F$29:$F$361,MATCH($O99,Scoring!$AB$29:$AB$361,0))) -> 1830.5 | N99: =IF($O99="","",INDEX(Scoring!$AI$29:$AI$361,MATCH($O99,Scoring!$AB$29:$AB$361,0))) -> Canada | O99: =IFERROR(SMALL(Scoring!$AB$29:$AB$361,95),"") -> 5008
A100: =IF($O100="","",INT($O100/1000)) -> 5 | B100: =IF($O100="","",INDEX(Scoring!$A$29:$A$361,MATCH($O100,Scoring!$AB$29:$AB$361,0))) -> Emcure | C100: =IF($O100="","",IF(INDEX(Scoring!$P$29:$P$361,MATCH($O100,Scoring!$AB$29:$AB$361,0))="","–",INDEX(Scoring!$P$29:$P$361,MATCH($O100,Scoring!$AB$29:$AB$361,0)))) -> 9 | D100: =IF($O100="","",INDEX(Scoring!$Q$29:$Q$361,MATCH($O100,Scoring!$AB$29:$AB$361,0))) -> Priority 2 | E100: =IF($O100="","",INDEX(Scoring!$AJ$29:$AJ$361,MATCH($O100,Scoring!$AB$29:$AB$361,0))) -> High price · lower volume | F100: =IF($O100="","",INDEX(Scoring!$B$29:$B$361,MATCH($O100,Scoring!$AB$29:$AB$361,0))) -> Pentamidine | G100: =IF($O100="","",INDEX(Scoring!$AG$29:$AG$361,MATCH($O100,Scoring!$AB$29:$AB$361,0))) -> Pentamidine Isetionate Tillomed; Pentamidindiisetionat Tillomed; Pentamidine Isetionate (+1 more) | H100: =IF($O100="","",INDEX(Scoring!$C$29:$C$361,MATCH($O100,Scoring!$AB$29:$AB$361,0))) -> Anti-infective: Pneumocystis pneumonia, leishmaniasis | I100: =IF($O100="","",INDEX(Scoring!$I$29:$I$361,MATCH($O100,Scoring!$AB$29:$AB$361,0))) -> Vial | J100: =IF($O100="","",INDEX(Scoring!$Z$29:$Z$361,MATCH($O100,Scoring!$AB$29:$AB$361,0))) -> 300 mg powder vial; 300 mg in 20 mL powder vial | K100: =IF($O100="","",IF(INDEX(Scoring!$D$29:$D$361,MATCH($O100,Scoring!$AB$29:$AB$361,0))="",INDEX(Scoring!$AF$29:$AF$361,MATCH($O100,Scoring!$AB$29:$AB$361,0)),INDEX(Scoring!$D$29:$D$361,MATCH($O100,Scoring!$AB$29:$AB$361,0)))) -> 186.04 | L100: =IF($O100="","",INDEX(Scoring!$M$29:$M$361,MATCH($O100,Scoring!$AB$29:$AB$361,0))) -> 9 | M100: =IF($O100="","",INDEX(Scoring!$F$29:$F$361,MATCH($O100,Scoring!$AB$29:$AB$361,0))) -> 1652 | N100: =IF($O100="","",INDEX(Scoring!$AI$29:$AI$361,MATCH($O100,Scoring!$AB$29:$AB$361,0))) -> UK, Canada, Australia, UK-NI | EU/EEA (8): Germany, France, Netherlands, Denmark + 4 more | O100: =IFERROR(SMALL(Scoring!$AB$29:$AB$361,96),"") -> 5009
...

Sheet 2x2 – Option 1
A1: 2x2 – unit price × injectable shipments (#) (Option 1)
A2: Pick a company in cell B3. Bubble = injectable export value ($'000). Axes are logarithmic; the axis lines sit at the median cut-offs (price USD 25.09; volume 146), so the top-right quadrant is Priority 1. Unpriced drugs and price ≤ $5 exclusions are listed but not plotted. Linked to Summary – Option 1.
A3: Company: | B3: Intas | D3: Helper: first row in Summary | E3: =MATCH($B$3,'Summary – Option 1'!$B$5:$B$337,0) -> 1
A5: # | B5: Drug (API) | C5: Priority tier | D5: 2x2 quadrant | E5: Avg price (USD / unit) | F5: Injectable shipments (#) | G5: Injectable export value ($'000) | H5: Chart label | I5: Helper: P1 x | J5: Helper: P1 y | K5: Helper: P1 bubble | L5: Helper: P2 x | M5: Helper: P2 y | N5: Helper: P2 bubble | O5: Helper: P3 x | P5: Helper: P3 y | Q5: Helper: P3 bubble
A6: 1 | B6: =IFERROR(IF(INDEX('Summary – Option 1'!$B$5:$B$337,$E$3+$A6-1)=$B$3,INDEX('Summary – Option 1'!$F$5:$F$337,$E$3+$A6-1),""),"") -> Azacitidine | C6: =IF($B6="","",INDEX('Summary – Option 1'!$D$5:$D$337,$E$3+$A6-1)) -> Priority 1 | D6: =IF($B6="","",INDEX('Summary – Option 1'!$E$5:$E$337,$E$3+$A6-1)) -> High price · high volume | E6: =IF($B6="","",INDEX('Summary – Option 1'!$K$5:$K$337,$E$3+$A6-1)) -> 256.12 | F6: =IF($B6="","",INDEX('Summary – Option 1'!$L$5:$L$337,$E$3+$A6-1)) -> 632 | G6: =IF($B6="","",INDEX('Summary – Option 1'!$M$5:$M$337,$E$3+$A6-1)) -> 42181.7 | H6: =IF(OR($B6="",LEFT($C6,8)="Excluded",NOT(ISNUMBER($E6))),"",$B6&" (P"&RIGHT($C6,1)&")") -> Azacitidine (P1) | I6: =IF(OR($H6="",N($F6)<=0,$C6<>"Priority 1"),NA(),$E6) -> 256.12 | J6: =IF(OR($H6="",N($F6)<=0,$C6<>"Priority 1"),NA(),$F6) -> 632 | K6: =IF(OR($H6="",N($F6)<=0,$C6<>"Priority 1"),NA(),MAX($G6,1)) -> 42181.7 | L6: =IF(OR($H6="",N($F6)<=0,$C6<>"Priority 2"),NA(),$E6) -> #N/A | M6: =IF(OR($H6="",N($F6)<=0,$C6<>"Priority 2"),NA(),$F6) -> #N/A | N6: =IF(OR($H6="",N($F6)<=0,$C6<>"Priority 2"),NA(),MAX($G6,1)) -> #N/A | O6: =IF(OR($H6="",N($F6)<=0,$C6<>"Priority 3"),NA(),$E6) -> #N/A | P6: =IF(OR($H6="",N($F6)<=0,$C6<>"Priority 3"),NA(),$F6) -> #N/A | Q6: =IF(OR($H6="",N($F6)<=0,$C6<>"Priority 3"),NA(),MAX($G6,1)) -> #N/A
A7: 2 | B7: =IFERROR(IF(INDEX('Summary – Option 1'!$B$5:$B$337,$E$3+$A7-1)=$B$3,INDEX('Summary – Option 1'!$F$5:$F$337,$E$3+$A7-1),""),"") -> Bortezomib | C7: =IF($B7="","",INDEX('Summary – Option 1'!$D$5:$D$337,$E$3+$A7-1)) -> Priority 1 | D7: =IF($B7="","",INDEX('Summary – Option 1'!$E$5:$E$337,$E$3+$A7-1)) -> High price · high volume | E7: =IF($B7="","",INDEX('Summary – Option 1'!$K$5:$K$337,$E$3+$A7-1)) -> 569.27 | F7: =IF($B7="","",INDEX('Summary – Option 1'!$L$5:$L$337,$E$3+$A7-1)) -> 905 | G7: =IF($B7="","",INDEX('Summary – Option 1'!$M$5:$M$337,$E$3+$A7-1)) -> 28093.4 | H7: =IF(OR($B7="",LEFT($C7,8)="Excluded",NOT(ISNUMBER($E7))),"",$B7&" (P"&RIGHT($C7,1)&")") -> Bortezomib (P1) | I7: =IF(OR($H7="",N($F7)<=0,$C7<>"Priority 1"),NA(),$E7) -> 569.27 | J7: =IF(OR($H7="",N($F7)<=0,$C7<>"Priority 1"),NA(),$F7) -> 905 | K7: =IF(OR($H7="",N($F7)<=0,$C7<>"Priority 1"),NA(),MAX($G7,1)) -> 28093.4 | L7: =IF(OR($H7="",N($F7)<=0,$C7<>"Priority 2"),NA(),$E7) -> #N/A | M7: =IF(OR($H7="",N($F7)<=0,$C7<>"Priority 2"),NA(),$F7) -> #N/A | N7: =IF(OR($H7="",N($F7)<=0,$C7<>"Priority 2"),NA(),MAX($G7,1)) -> #N/A | O7: =IF(OR($H7="",N($F7)<=0,$C7<>"Priority 3"),NA(),$E7) -> #N/A | P7: =IF(OR($H7="",N($F7)<=0,$C7<>"Priority 3"),NA(),$F7) -> #N/A | Q7: =IF(OR($H7="",N($F7)<=0,$C7<>"Priority 3"),NA(),MAX($G7,1)) -> #N/A
A8: 3 | B8: =IFERROR(IF(INDEX('Summary – Option 1'!$B$5:$B$337,$E$3+$A8-1)=$B$3,INDEX('Summary – Option 1'!$F$5:$F$337,$E$3+$A8-1),""),"") -> Pegfilgrastim | C8: =IF($B8="","",INDEX('Summary – Option 1'!$D$5:$D$337,$E$3+$A8-1)) -> Priority 1 | D8: =IF($B8="","",INDEX('Summary – Option 1'!$E$5:$E$337,$E$3+$A8-1)) -> High price · high volume | E8: =IF($B8="","",INDEX('Summary – Option 1'!$K$5:$K$337,$E$3+$A8-1)) -> 907.38 | F8: =IF($B8="","",INDEX('Summary – Option 1'!$L$5:$L$337,$E$3+$A8-1)) -> 155 | G8: =IF($B8="","",INDEX('Summary – Option 1'!$M$5:$M$337,$E$3+$A8-1)) -> 22036.1 | H8: =IF(OR($B8="",LEFT($C8,8)="Excluded",NOT(ISNUMBER($E8))),"",$B8&" (P"&RIGHT($C8,1)&")") -> Pegfilgrastim (P1) | I8: =IF(OR($H8="",N($F8)<=0,$C8<>"Priority 1"),NA(),$E8) -> 907.38 | J8: =IF(OR($H8="",N($F8)<=0,$C8<>"Priority 1"),NA(),$F8) -> 155 | K8: =IF(OR($H8="",N($F8)<=0,$C8<>"Priority 1"),NA(),MAX($G8,1)) -> 22036.1 | L8: =IF(OR($H8="",N($F8)<=0,$C8<>"Priority 2"),NA(),$E8) -> #N/A | M8: =IF(OR($H8="",N($F8)<=0,$C8<>"Priority 2"),NA(),$F8) -> #N/A | N8: =IF(OR($H8="",N($F8)<=0,$C8<>"Priority 2"),NA(),MAX($G8,1)) -> #N/A | O8: =IF(OR($H8="",N($F8)<=0,$C8<>"Priority 3"),NA(),$E8) -> #N/A | P8: =IF(OR($H8="",N($F8)<=0,$C8<>"Priority 3"),NA(),$F8) -> #N/A | Q8: =IF(OR($H8="",N($F8)<=0,$C8<>"Priority 3"),NA(),MAX($G8,1)) -> #N/A
A9: 4 | B9: =IFERROR(IF(INDEX('Summary – Option 1'!$B$5:$B$337,$E$3+$A9-1)=$B$3,INDEX('Summary – Option 1'!$F$5:$F$337,$E$3+$A9-1),""),"") -> Methotrexate | C9: =IF($B9="","",INDEX('Summary – Option 1'!$D$5:$D$337,$E$3+$A9-1)) -> Priority 1 | D9: =IF($B9="","",INDEX('Summary – Option 1'!$E$5:$E$337,$E$3+$A9-1)) -> High price · high volume | E9: =IF($B9="","",INDEX('Summary – Option 1'!$K$5:$K$337,$E$3+$A9-1)) -> 50.77 | F9: =IF($B9="","",INDEX('Summary – Option 1'!$L$5:$L$337,$E$3+$A9-1)) -> 996 | G9: =IF($B9="","",INDEX('Summary – Option 1'!$M$5:$M$337,$E$3+$A9-1)) -> 13045.6 | H9: =IF(OR($B9="",LEFT($C9,8)="Excluded",NOT(ISNUMBER($E9))),"",$B9&" (P"&RIGHT($C9,1)&")") -> Methotrexate (P1) | I9: =IF(OR($H9="",N($F9)<=0,$C9<>"Priority 1"),NA(),$E9) -> 50.77 | J9: =IF(OR($H9="",N($F9)<=0,$C9<>"Priority 1"),NA(),$F9) -> 996 | K9: =IF(OR($H9="",N($F9)<=0,$C9<>"Priority 1"),NA(),MAX($G9,1)) -> 13045.6 | L9: =IF(OR($H9="",N($F9)<=0,$C9<>"Priority 2"),NA(),$E9) -> #N/A | M9: =IF(OR($H9="",N($F9)<=0,$C9<>"Priority 2"),NA(),$F9) -> #N/A | N9: =IF(OR($H9="",N($F9)<=0,$C9<>"Priority 2"),NA(),MAX($G9,1)) -> #N/A | O9: =IF(OR($H9="",N($F9)<=0,$C9<>"Priority 3"),NA(),$E9) -> #N/A | P9: =IF(OR($H9="",N($F9)<=0,$C9<>"Priority 3"),NA(),$F9) -> #N/A | Q9: =IF(OR($H9="",N($F9)<=0,$C9<>"Priority 3"),NA(),MAX($G9,1)) -> #N/A
A10: 5 | B10: =IFERROR(IF(INDEX('Summary – Option 1'!$B$5:$B$337,$E$3+$A10-1)=$B$3,INDEX('Summary – Option 1'!$F$5:$F$337,$E$3+$A10-1),""),"") -> Fulvestrant | C10: =IF($B10="","",INDEX('Summary – Option 1'!$D$5:$D$337,$E$3+$A10-1)) -> Priority 1 | D10: =IF($B10="","",INDEX('Summary – Option 1'!$E$5:$E$337,$E$3+$A10-1)) -> High price · high volume | E10: =IF($B10="","",INDEX('Summary – Option 1'!$K$5:$K$337,$E$3+$A10-1)) -> 246.46 | F10: =IF($B10="","",INDEX('Summary – Option 1'!$L$5:$L$337,$E$3+$A10-1)) -> 146 | G10: =IF($B10="","",INDEX('Summary – Option 1'!$M$5:$M$337,$E$3+$A10-1)) -> 11366.1 | H10: =IF(OR($B10="",LEFT($C10,8)="Excluded",NOT(ISNUMBER($E10))),"",$B10&" (P"&RIGHT($C10,1)&")") -> Fulvestrant (P1) | I10: =IF(OR($H10="",N($F10)<=0,$C10<>"Priority 1"),NA(),$E10) -> 246.46 | J10: =IF(OR($H10="",N($F10)<=0,$C10<>"Priority 1"),NA(),$F10) -> 146 | K10: =IF(OR($H10="",N($F10)<=0,$C10<>"Priority 1"),NA(),MAX($G10,1)) -> 11366.1 | L10: =IF(OR($H10="",N($F10)<=0,$C10<>"Priority 2"),NA(),$E10) -> #N/A | M10: =IF(OR($H10="",N($F10)<=0,$C10<>"Priority 2"),NA(),$F10) -> #N/A | N10: =IF(OR($H10="",N($F10)<=0,$C10<>"Priority 2"),NA(),MAX($G10,1)) -> #N/A | O10: =IF(OR($H10="",N($F10)<=0,$C10<>"Priority 3"),NA(),$E10) -> #N/A | P10: =IF(OR($H10="",N($F10)<=0,$C10<>"Priority 3"),NA(),$F10) -> #N/A | Q10: =IF(OR($H10="",N($F10)<=0,$C10<>"Priority 3"),NA(),MAX($G10,1)) -> #N/A
A11: 6 | B11: =IFERROR(IF(INDEX('Summary – Option 1'!$B$5:$B$337,$E$3+$A11-1)=$B$3,INDEX('Summary – Option 1'!$F$5:$F$337,$E$3+$A11-1),""),"") -> Phenylephrine | C11: =IF($B11="","",INDEX('Summary – Option 1'!$D$5:$D$337,$E$3+$A11-1)) -> Priority 1 | D11: =IF($B11="","",INDEX('Summary – Option 1'!$E$5:$E$337,$E$3+$A11-1)) -> High price · high volume | E11: =IF($B11="","",INDEX('Summary – Option 1'!$K$5:$K$337,$E$3+$A11-1)) -> 32.6 | F11: =IF($B11="","",INDEX('Summary – Option 1'!$L$5:$L$337,$E$3+$A11-1)) -> 226 | G11: =IF($B11="","",INDEX('Summary – Option 1'!$M$5:$M$337,$E$3+$A11-1)) -> 5695.2 | H11: =IF(OR($B11="",LEFT($C11,8)="Excluded",NOT(ISNUMBER($E11))),"",$B11&" (P"&RIGHT($C11,1)&")") -> Phenylephrine (P1) | I11: =IF(OR($H11="",N($F11)<=0,$C11<>"Priority 1"),NA(),$E11) -> 32.6 | J11: =IF(OR($H11="",N($F11)<=0,$C11<>"Priority 1"),NA(),$F11) -> 226 | K11: =IF(OR($H11="",N($F11)<=0,$C11<>"Priority 1"),NA(),MAX($G11,1)) -> 5695.2 | L11: =IF(OR($H11="",N($F11)<=0,$C11<>"Priority 2"),NA(),$E11) -> #N/A | M11: =IF(OR($H11="",N($F11)<=0,$C11<>"Priority 2"),NA(),$F11) -> #N/A | N11: =IF(OR($H11="",N($F11)<=0,$C11<>"Priority 2"),NA(),MAX($G11,1)) -> #N/A | O11: =IF(OR($H11="",N($F11)<=0,$C11<>"Priority 3"),NA(),$E11) -> #N/A | P11: =IF(OR($H11="",N($F11)<=0,$C11<>"Priority 3"),NA(),$F11) -> #N/A | Q11: =IF(OR($H11="",N($F11)<=0,$C11<>"Priority 3"),NA(),MAX($G11,1)) -> #N/A
A12: 7 | B12: =IFERROR(IF(INDEX('Summary – Option 1'!$B$5:$B$337,$E$3+$A12-1)=$B$3,INDEX('Summary – Option 1'!$F$5:$F$337,$E$3+$A12-1),""),"") -> Epinephrine (Adrenaline) | C12: =IF($B12="","",INDEX('Summary – Option 1'!$D$5:$D$337,$E$3+$A12-1)) -> Priority 1 | D12: =IF($B12="","",INDEX('Summary – Option 1'!$E$5:$E$337,$E$3+$A12-1)) -> High price · high volume | E12: =IF($B12="","",INDEX('Summary – Option 1'!$K$5:$K$337,$E$3+$A12-1)) -> 28.67 | F12: =IF($B12="","",INDEX('Summary – Option 1'!$L$5:$L$337,$E$3+$A12-1)) -> 799 | G12: =IF($B12="","",INDEX('Summary – Option 1'!$M$5:$M$337,$E$3+$A12-1)) -> 4049.5 | H12: =IF(OR($B12="",LEFT($C12,8)="Excluded",NOT(ISNUMBER($E12))),"",$B12&" (P"&RIGHT($C12,1)&")") -> Epinephrine (Adrenaline) (P1) | I12: =IF(OR($H12="",N($F12)<=0,$C12<>"Priority 1"),NA(),$E12) -> 28.67 | J12: =IF(OR($H12="",N($F12)<=0,$C12<>"Priority 1"),NA(),$F12) -> 799 | K12: =IF(OR($H12="",N($F12)<=0,$C12<>"Priority 1"),NA(),MAX($G12,1)) -> 4049.5 | L12: =IF(OR($H12="",N($F12)<=0,$C12<>"Priority 2"),NA(),$E12) -> #N/A | M12: =IF(OR($H12="",N($F12)<=0,$C12<>"Priority 2"),NA(),$F12) -> #N/A | N12: =IF(OR($H12="",N($F12)<=0,$C12<>"Priority 2"),NA(),MAX($G12,1)) -> #N/A | O12: =IF(OR($H12="",N($F12)<=0,$C12<>"Priority 3"),NA(),$E12) -> #N/A | P12: =IF(OR($H12="",N($F12)<=0,$C12<>"Priority 3"),NA(),$F12) -> #N/A | Q12: =IF(OR($H12="",N($F12)<=0,$C12<>"Priority 3"),NA(),MAX($G12,1)) -> #N/A
A13: 8 | B13: =IFERROR(IF(INDEX('Summary – Option 1'!$B$5:$B$337,$E$3+$A13-1)=$B$3,INDEX('Summary – Option 1'!$F$5:$F$337,$E$3+$A13-1),""),"") -> Bleomycin | C13: =IF($B13="","",INDEX('Summary – Option 1'!$D$5:$D$337,$E$3+$A13-1)) -> Priority 1 | D13: =IF($B13="","",INDEX('Summary – Option 1'!$E$5:$E$337,$E$3+$A13-1)) -> High price · high volume | E13: =IF($B13="","",INDEX('Summary – Option 1'!$K$5:$K$337,$E$3+$A13-1)) -> 50.27 | F13: =IF($B13="","",INDEX('Summary – Option 1'!$L$5:$L$337,$E$3+$A13-1)) -> 441 | G13: =IF($B13="","",INDEX('Summary – Option 1'!$M$5:$M$337,$E$3+$A13-1)) -> 3973.7 | H13: =IF(OR($B13="",LEFT($C13,8)="Excluded",NOT(ISNUMBER($E13))),"",$B13&" (P"&RIGHT($C13,1)&")") -> Bleomycin (P1) | I13: =IF(OR($H13="",N($F13)<=0,$C13<>"Priority 1"),NA(),$E13) -> 50.27 | J13: =IF(OR($H13="",N($F13)<=0,$C13<>"Priority 1"),NA(),$F13) -> 441 | K13: =IF(OR($H13="",N($F13)<=0,$C13<>"Priority 1"),NA(),MAX($G13,1)) -> 3973.7 | L13: =IF(OR($H13="",N($F13)<=0,$C13<>"Priority 2"),NA(),$E13) -> #N/A | M13: =IF(OR($H13="",N($F13)<=0,$C13<>"Priority 2"),NA(),$F13) -> #N/A | N13: =IF(OR($H13="",N($F13)<=0,$C13<>"Priority 2"),NA(),MAX($G13,1)) -> #N/A | O13: =IF(OR($H13="",N($F13)<=0,$C13<>"Priority 3"),NA(),$E13) -> #N/A | P13: =IF(OR($H13="",N($F13)<=0,$C13<>"Priority 3"),NA(),$F13) -> #N/A | Q13: =IF(OR($H13="",N($F13)<=0,$C13<>"Priority 3"),NA(),MAX($G13,1)) -> #N/A
A14: 9 | B14: =IFERROR(IF(INDEX('Summary – Option 1'!$B$5:$B$337,$E$3+$A14-1)=$B$3,INDEX('Summary – Option 1'!$F$5:$F$337,$E$3+$A14-1),""),"") -> Denosumab | C14: =IF($B14="","",INDEX('Summary – Option 1'!$D$5:$D$337,$E$3+$A14-1)) -> Priority 1 | D14: =IF($B14="","",INDEX('Summary – Option 1'!$E$5:$E$337,$E$3+$A14-1)) -> High price · high volume | E14: =IF($B14="","",INDEX('Summary – Option 1'!$K$5:$K$337,$E$3+$A14-1)) -> 162.77 | F14: =IF($B14="","",INDEX('Summary – Option 1'!$L$5:$L$337,$E$3+$A14-1)) -> 314 | G14: =IF($B14="","",INDEX('Summary – Option 1'!$M$5:$M$337,$E$3+$A14-1)) -> 3429.5 | H14: =IF(OR($B14="",LEFT($C14,8)="Excluded",NOT(ISNUMBER($E14))),"",$B14&" (P"&RIGHT($C14,1)&")") -> Denosumab (P1) | I14: =IF(OR($H14="",N($F14)<=0,$C14<>"Priority 1"),NA(),$E14) -> 162.77 | J14: =IF(OR($H14="",N($F14)<=0,$C14<>"Priority 1"),NA(),$F14) -> 314 | K14: =IF(OR($H14="",N($F14)<=0,$C14<>"Priority 1"),NA(),MAX($G14,1)) -> 3429.5 | L14: =IF(OR($H14="",N($F14)<=0,$C14<>"Priority 2"),NA(),$E14) -> #N/A | M14: =IF(OR($H14="",N($F14)<=0,$C14<>"Priority 2"),NA(),$F14) -> #N/A | N14: =IF(OR($H14="",N($F14)<=0,$C14<>"Priority 2"),NA(),MAX($G14,1)) -> #N/A | O14: =IF(OR($H14="",N($F14)<=0,$C14<>"Priority 3"),NA(),$E14) -> #N/A | P14: =IF(OR($H14="",N($F14)<=0,$C14<>"Priority 3"),NA(),$F14) -> #N/A | Q14: =IF(OR($H14="",N($F14)<=0,$C14<>"Priority 3"),NA(),MAX($G14,1)) -> #N/A
A15: 10 | B15: =IFERROR(IF(INDEX('Summary – Option 1'!$B$5:$B$337,$E$3+$A15-1)=$B$3,INDEX('Summary – Option 1'!$F$5:$F$337,$E$3+$A15-1),""),"") -> Ceftriaxone | C15: =IF($B15="","",INDEX('Summary – Option 1'!$D$5:$D$337,$E$3+$A15-1)) -> Priority 2 | D15: =IF($B15="","",INDEX('Summary – Option 1'!$E$5:$E$337,$E$3+$A15-1)) -> Lower price · high volume | E15: =IF($B15="","",INDEX('Summary – Option 1'!$K$5:$K$337,$E$3+$A15-1)) -> 5.6 | F15: =IF($B15="","",INDEX('Summary – Option 1'!$L$5:$L$337,$E$3+$A15-1)) -> 3110 | G15: =IF($B15="","",INDEX('Summary – Option 1'!$M$5:$M$337,$E$3+$A15-1)) -> 93119.2 | H15: =IF(OR($B15="",LEFT($C15,8)="Excluded",NOT(ISNUMBER($E15))),"",$B15&" (P"&RIGHT($C15,1)&")") -> Ceftriaxone (P2) | I15: =IF(OR($H15="",N($F15)<=0,$C15<>"Priority 1"),NA(),$E15) -> #N/A | J15: =IF(OR($H15="",N($F15)<=0,$C15<>"Priority 1"),NA(),$F15) -> #N/A | K15: =IF(OR($H15="",N($F15)<=0,$C15<>"Priority 1"),NA(),MAX($G15,1)) -> #N/A | L15: =IF(OR($H15="",N($F15)<=0,$C15<>"Priority 2"),NA(),$E15) -> 5.6 | M15: =IF(OR($H15="",N($F15)<=0,$C15<>"Priority 2"),NA(),$F15) -> 3110 | N15: =IF(OR($H15="",N($F15)<=0,$C15<>"Priority 2"),NA(),MAX($G15,1)) -> 93119.2 | O15: =IF(OR($H15="",N($F15)<=0,$C15<>"Priority 3"),NA(),$E15) -> #N/A | P15: =IF(OR($H15="",N($F15)<=0,$C15<>"Priority 3"),NA(),$F15) -> #N/A | Q15: =IF(OR($H15="",N($F15)<=0,$C15<>"Priority 3"),NA(),MAX($G15,1)) -> #N/A
A16: 11 | B16: =IFERROR(IF(INDEX('Summary – Option 1'!$B$5:$B$337,$E$3+$A16-1)=$B$3,INDEX('Summary – Option 1'!$F$5:$F$337,$E$3+$A16-1),""),"") -> Ondansetron | C16: =IF($B16="","",INDEX('Summary – Option 1'!$D$5:$D$337,$E$3+$A16-1)) -> Priority 2 | D16: =IF($B16="","",INDEX('Summary – Option 1'!$E$5:$E$337,$E$3+$A16-1)) -> Lower price · high volume | E16: =IF($B16="","",INDEX('Summary – Option 1'!$K$5:$K$337,$E$3+$A16-1)) -> 24.05 | F16: =IF($B16="","",INDEX('Summary – Option 1'!$L$5:$L$337,$E$3+$A16-1)) -> 963 | G16: =IF($B16="","",INDEX('Summary – Option 1'!$M$5:$M$337,$E$3+$A16-1)) -> 17590.5 | H16: =IF(OR($B16="",LEFT($C16,8)="Excluded",NOT(ISNUMBER($E16))),"",$B16&" (P"&RIGHT($C16,1)&")") -> Ondansetron (P2) | I16: =IF(OR($H16="",N($F16)<=0,$C16<>"Priority 1"),NA(),$E16) -> #N/A | J16: =IF(OR($H16="",N($F16)<=0,$C16<>"Priority 1"),NA(),$F16) -> #N/A | K16: =IF(OR($H16="",N($F16)<=0,$C16<>"Priority 1"),NA(),MAX($G16,1)) -> #N/A | L16: =IF(OR($H16="",N($F16)<=0,$C16<>"Priority 2"),NA(),$E16) -> 24.05 | M16: =IF(OR($H16="",N($F16)<=0,$C16<>"Priority 2"),NA(),$F16) -> 963 | N16: =IF(OR($H16="",N($F16)<=0,$C16<>"Priority 2"),NA(),MAX($G16,1)) -> 17590.5 | O16: =IF(OR($H16="",N($F16)<=0,$C16<>"Priority 3"),NA(),$E16) -> #N/A | P16: =IF(OR($H16="",N($F16)<=0,$C16<>"Priority 3"),NA(),$F16) -> #N/A | Q16: =IF(OR($H16="",N($F16)<=0,$C16<>"Priority 3"),NA(),MAX($G16,1)) -> #N/A
A17: 12 | B17: =IFERROR(IF(INDEX('Summary – Option 1'!$B$5:$B$337,$E$3+$A17-1)=$B$3,INDEX('Summary – Option 1'!$F$5:$F$337,$E$3+$A17-1),""),"") -> Plerixafor | C17: =IF($B17="","",INDEX('Summary – Option 1'!$D$5:$D$337,$E$3+$A17-1)) -> Priority 2 | D17: =IF($B17="","",INDEX('Summary – Option 1'!$E$5:$E$337,$E$3+$A17-1)) -> High price · lower volume | E17: =IF($B17="","",INDEX('Summary – Option 1'!$K$5:$K$337,$E$3+$A17-1)) -> 4779 | F17: =IF($B17="","",INDEX('Summary – Option 1'!$L$5:$L$337,$E$3+$A17-1)) -> 47 | G17: =IF($B17="","",INDEX('Summary – Option 1'!$M$5:$M$337,$E$3+$A17-1)) -> 7904.7 | H17: =IF(OR($B17="",LEFT($C17,8)="Excluded",NOT(ISNUMBER($E17))),"",$B17&" (P"&RIGHT($C17,1)&")") -> Plerixafor (P2) | I17: =IF(OR($H17="",N($F17)<=0,$C17<>"Priority 1"),NA(),$E17) -> #N/A | J17: =IF(OR($H17="",N($F17)<=0,$C17<>"Priority 1"),NA(),$F17) -> #N/A | K17: =IF(OR($H17="",N($F17)<=0,$C17<>"Priority 1"),NA(),MAX($G17,1)) -> #N/A | L17: =IF(OR($H17="",N($F17)<=0,$C17<>"Priority 2"),NA(),$E17) -> 4779 | M17: =IF(OR($H17="",N($F17)<=0,$C17<>"Priority 2"),NA(),$F17) -> 47 | N17: =IF(OR($H17="",N($F17)<=0,$C17<>"Priority 2"),NA(),MAX($G17,1)) -> 7904.7 | O17: =IF(OR($H17="",N($F17)<=0,$C17<>"Priority 3"),NA(),$E17) -> #N/A | P17: =IF(OR($H17="",N($F17)<=0,$C17<>"Priority 3"),NA(),$F17) -> #N/A | Q17: =IF(OR($H17="",N($F17)<=0,$C17<>"Priority 3"),NA(),MAX($G17,1)) -> #N/A
... A35: 30 | B35: =IFERROR(IF(INDEX('Summary – Option 1'!$B$5:$B$337,$E$3+$A35-1)=$B$3,INDEX('Summary – Option 1'!$F$5:$F$337,$E$3+$A35-1),""),"") -> Phenytoin | C35: =IF($B35="","",INDEX('Summary – Option 1'!$D$5:$D$337,$E$3+$A35-1)) -> Excluded – price ≤ $5 | D35: =IF($B35="","",INDEX('Summary – Option 1'!$E$5:$E$337,$E$3+$A35-1)) | E35: =IF($B35="","",INDEX('Summary – Option 1'!$K$5:$K$337,$E$3+$A35-1)) -> 4.49 | F35: =IF($B35="","",INDEX('Summary – Option 1'!$L$5:$L$337,$E$3+$A35-1)) -> 208 | G35: =IF($B35="","",INDEX('Summary – Option 1'!$M$5:$M$337,$E$3+$A35-1)) -> 2009.5 | H35: =IF(OR($B35="",LEFT($C35,8)="Excluded",NOT(ISNUMBER($E35))),"",$B35&" (P"&RIGHT($C35,1)&")") | I35: =IF(OR($H35="",N($F35)<=0,$C35<>"Priority 1"),NA(),$E35) -> #N/A | J35: =IF(OR($H35="",N($F35)<=0,$C35<>"Priority 1"),NA(),$F35) -> #N/A | K35: =IF(OR($H35="",N($F35)<=0,$C35<>"Priority 1"),NA(),MAX($G35,1)) -> #N/A | L35: =IF(OR($H35="",N($F35)<=0,$C35<>"Priority 2"),NA(),$E35) -> #N/A | M35: =IF(OR($H35="",N($F35)<=0,$C35<>"Priority 2"),NA(),$F35) -> #N/A | N35: =IF(OR($H35="",N($F35)<=0,$C35<>"Priority 2"),NA(),MAX($G35,1)) -> #N/A | O35: =IF(OR($H35="",N($F35)<=0,$C35<>"Priority 3"),NA(),$E35) -> #N/A | P35: =IF(OR($H35="",N($F35)<=0,$C35<>"Priority 3"),NA(),$F35) -> #N/A | Q35: =IF(OR($H35="",N($F35)<=0,$C35<>"Priority 3"),NA(),MAX($G35,1)) -> #N/A
A37: Bubble colours: dark blue = Priority 1, light blue = Priority 2, grey = Priority 3. Hidden columns I–Q feed the chart (#N/A = no point to plot). Grey rows = Priority 1.

Sheet Summary – Option 2
A1: SurTrac co-packaging – priority companies and drugs (Option 2 – all shipments)
A2: 2x2: unit price (x) × shipments – all forms (#) (y); bubble = export – all forms ($'000). Priority 1 = high price AND high volume (top-right); Priority 2 = one of the two high; Priority 3 = both lower; cut-offs = median of eligible pairs (Scoring C3 / H3). Drugs with an ID / IM / SC route on a label in the 7 geographies only (IV-only drugs removed). Companies ranked by number of Priority 1 drugs, then opportunity of Priority 1 + 2; within a company, drugs by tier, then opportunity. Price ≤ $5 listed last as Excluded.
A3: Packaging: strength and fill per unit container (no carton sizes). Avg price: average per unit (per dose for multi-dose vaccine vials) of presentations priced > $5; Excluded rows: average of all priced presentations (all ≤ $5). Volume = India FY24 shipments of the molecule, all dosage forms (tablets, syrups etc. included – oral-heavy molecules look larger than their injectable market). Volume is molecule-level (same for every company). Markets: countries where the company (or its group entity) holds an authorisation – a proxy for where it is supplied. Filters, assumptions and limitations: see the tab of that name. Live – linked to Scoring; grey helper column O orders the list.
A4: Company rank | B4: Company | C4: Drug rank | D4: Priority tier | E4: 2x2 quadrant | F4: Drug (API) | G4: Product name | H4: Drug utility | I4: Presentation | J4: Packaging (per unit) | K4: Avg price (USD / unit) | L4: Shipments – all forms (#) | M4: Export – all forms ($'000) | N4: Markets where the company holds an authorisation | O4: Helper: sort key
A5: =IF($O5="","",INT($O5/1000)) -> 1 | B5: =IF($O5="","",INDEX(Scoring!$A$29:$A$361,MATCH($O5,Scoring!$AS$29:$AS$361,0))) -> Intas | C5: =IF($O5="","",IF(INDEX(Scoring!$AM$29:$AM$361,MATCH($O5,Scoring!$AS$29:$AS$361,0))="","–",INDEX(Scoring!$AM$29:$AM$361,MATCH($O5,Scoring!$AS$29:$AS$361,0)))) -> 1 | D5: =IF($O5="","",INDEX(Scoring!$AK$29:$AK$361,MATCH($O5,Scoring!$AS$29:$AS$361,0))) -> Priority 1 | E5: =IF($O5="","",INDEX(Scoring!$AL$29:$AL$361,MATCH($O5,Scoring!$AS$29:$AS$361,0))) -> High price · high volume | F5: =IF($O5="","",INDEX(Scoring!$B$29:$B$361,MATCH($O5,Scoring!$AS$29:$AS$361,0))) -> Azacitidine | G5: =IF($O5="","",INDEX(Scoring!$AG$29:$AG$361,MATCH($O5,Scoring!$AS$29:$AS$361,0))) -> Azacitidine Accord; Azaccord | H5: =IF($O5="","",INDEX(Scoring!$C$29:$C$361,MATCH($O5,Scoring!$AS$29:$AS$361,0))) -> Oncology: myelodysplastic syndromes, acute myeloid leukaemia | I5: =IF($O5="","",INDEX(Scoring!$I$29:$I$361,MATCH($O5,Scoring!$AS$29:$AS$361,0))) -> Vial | J5: =IF($O5="","",INDEX(Scoring!$Z$29:$Z$361,MATCH($O5,Scoring!$AS$29:$AS$361,0))) -> 25 mg/mL vial; 100 mg powder vial | K5: =IF($O5="","",IF(INDEX(Scoring!$D$29:$D$361,MATCH($O5,Scoring!$AS$29:$AS$361,0))="",INDEX(Scoring!$AF$29:$AF$361,MATCH($O5,Scoring!$AS$29:$AS$361,0)),INDEX(Scoring!$D$29:$D$361,MATCH($O5,Scoring!$AS$29:$AS$361,0)))) -> 256.12 | L5: =IF($O5="","",INDEX(Scoring!$L$29:$L$361,MATCH($O5,Scoring!$AS$29:$AS$361,0))) -> 762 | M5: =IF($O5="","",INDEX(Scoring!$N$29:$N$361,MATCH($O5,Scoring!$AS$29:$AS$361,0))) -> 50865.56 | N5: =IF($O5="","",INDEX(Scoring!$AI$29:$AI$361,MATCH($O5,Scoring!$AS$29:$AS$361,0))) -> UK, Australia | EU/EEA: all 30 countries | O5: =IFERROR(SMALL(Scoring!$AS$29:$AS$361,1),"") -> 1001
A6: =IF($O6="","",INT($O6/1000)) -> 1 | B6: =IF($O6="","",INDEX(Scoring!$A$29:$A$361,MATCH($O6,Scoring!$AS$29:$AS$361,0))) -> Intas | C6: =IF($O6="","",IF(INDEX(Scoring!$AM$29:$AM$361,MATCH($O6,Scoring!$AS$29:$AS$361,0))="","–",INDEX(Scoring!$AM$29:$AM$361,MATCH($O6,Scoring!$AS$29:$AS$361,0)))) -> 2 | D6: =IF($O6="","",INDEX(Scoring!$AK$29:$AK$361,MATCH($O6,Scoring!$AS$29:$AS$361,0))) -> Priority 1 | E6: =IF($O6="","",INDEX(Scoring!$AL$29:$AL$361,MATCH($O6,Scoring!$AS$29:$AS$361,0))) -> High price · high volume | F6: =IF($O6="","",INDEX(Scoring!$B$29:$B$361,MATCH($O6,Scoring!$AS$29:$AS$361,0))) -> Phenylephrine | G6: =IF($O6="","",INDEX(Scoring!$AG$29:$AG$361,MATCH($O6,Scoring!$AS$29:$AS$361,0))) -> Phenylephrine Accord; Phenylcord | H6: =IF($O6="","",INDEX(Scoring!$C$29:$C$361,MATCH($O6,Scoring!$AS$29:$AS$361,0))) -> Anaesthesia: low blood pressure during anaesthesia | I6: =IF($O6="","",INDEX(Scoring!$I$29:$I$361,MATCH($O6,Scoring!$AS$29:$AS$361,0))) -> Vial | J6: =IF($O6="","",INDEX(Scoring!$Z$29:$Z$361,MATCH($O6,Scoring!$AS$29:$AS$361,0))) -> 10 mg/1 mL vial; 100 mg/10 mL vial | K6: =IF($O6="","",IF(INDEX(Scoring!$D$29:$D$361,MATCH($O6,Scoring!$AS$29:$AS$361,0))="",INDEX(Scoring!$AF$29:$AF$361,MATCH($O6,Scoring!$AS$29:$AS$361,0)),INDEX(Scoring!$D$29:$D$361,MATCH($O6,Scoring!$AS$29:$AS$361,0)))) -> 32.6 | L6: =IF($O6="","",INDEX(Scoring!$L$29:$L$361,MATCH($O6,Scoring!$AS$29:$AS$361,0))) -> 1963 | M6: =IF($O6="","",INDEX(Scoring!$N$29:$N$361,MATCH($O6,Scoring!$AS$29:$AS$361,0))) -> 49365.77 | N6: =IF($O6="","",INDEX(Scoring!$AI$29:$AI$361,MATCH($O6,Scoring!$AS$29:$AS$361,0))) -> Australia, South Africa | O6: =IFERROR(SMALL(Scoring!$AS$29:$AS$361,2),"") -> 1002
A7: =IF($O7="","",INT($O7/1000)) -> 1 | B7: =IF($O7="","",INDEX(Scoring!$A$29:$A$361,MATCH($O7,Scoring!$AS$29:$AS$361,0))) -> Intas | C7: =IF($O7="","",IF(INDEX(Scoring!$AM$29:$AM$361,MATCH($O7,Scoring!$AS$29:$AS$361,0))="","–",INDEX(Scoring!$AM$29:$AM$361,MATCH($O7,Scoring!$AS$29:$AS$361,0)))) -> 3 | D7: =IF($O7="","",INDEX(Scoring!$AK$29:$AK$361,MATCH($O7,Scoring!$AS$29:$AS$361,0))) -> Priority 1 | E7: =IF($O7="","",INDEX(Scoring!$AL$29:$AL$361,MATCH($O7,Scoring!$AS$29:$AS$361,0))) -> High price · high volume | F7: =IF($O7="","",INDEX(Scoring!$B$29:$B$361,MATCH($O7,Scoring!$AS$29:$AS$361,0))) -> Bortezomib | G7: =IF($O7="","",INDEX(Scoring!$AG$29:$AG$361,MATCH($O7,Scoring!$AS$29:$AS$361,0))) -> Bortezomib; Bortezomib Accord; Bortezomib Intas (+1 more) | H7: =IF($O7="","",INDEX(Scoring!$C$29:$C$361,MATCH($O7,Scoring!$AS$29:$AS$361,0))) -> Oncology: multiple myeloma, mantle cell lymphoma | I7: =IF($O7="","",INDEX(Scoring!$I$29:$I$361,MATCH($O7,Scoring!$AS$29:$AS$361,0))) -> Vial, Prefilled syringe | J7: =IF($O7="","",INDEX(Scoring!$Z$29:$Z$361,MATCH($O7,Scoring!$AS$29:$AS$361,0))) -> 2 mg pre-filled syringe; 3.5 mg/1.4 mL vial; 2.5 mg/1 mL vial; 1 mg powder vial (+2 more) | K7: =IF($O7="","",IF(INDEX(Scoring!$D$29:$D$361,MATCH($O7,Scoring!$AS$29:$AS$361,0))="",INDEX(Scoring!$AF$29:$AF$361,MATCH($O7,Scoring!$AS$29:$AS$361,0)),INDEX(Scoring!$D$29:$D$361,MATCH($O7,Scoring!$AS$29:$AS$361,0)))) -> 569.27 | L7: =IF($O7="","",INDEX(Scoring!$L$29:$L$361,MATCH($O7,Scoring!$AS$29:$AS$361,0))) -> 905 | M7: =IF($O7="","",INDEX(Scoring!$N$29:$N$361,MATCH($O7,Scoring!$AS$29:$AS$361,0))) -> 28093.38 | N7: =IF($O7="","",INDEX(Scoring!$AI$29:$AI$361,MATCH($O7,Scoring!$AS$29:$AS$361,0))) -> UK, Australia, South Africa, UK-NI | EU/EEA: all 30 countries | O7: =IFERROR(SMALL(Scoring!$AS$29:$AS$361,3),"") -> 1003
A8: =IF($O8="","",INT($O8/1000)) -> 1 | B8: =IF($O8="","",INDEX(Scoring!$A$29:$A$361,MATCH($O8,Scoring!$AS$29:$AS$361,0))) -> Intas | C8: =IF($O8="","",IF(INDEX(Scoring!$AM$29:$AM$361,MATCH($O8,Scoring!$AS$29:$AS$361,0))="","–",INDEX(Scoring!$AM$29:$AM$361,MATCH($O8,Scoring!$AS$29:$AS$361,0)))) -> 4 | D8: =IF($O8="","",INDEX(Scoring!$AK$29:$AK$361,MATCH($O8,Scoring!$AS$29:$AS$361,0))) -> Priority 1 | E8: =IF($O8="","",INDEX(Scoring!$AL$29:$AL$361,MATCH($O8,Scoring!$AS$29:$AS$361,0))) -> High price · high volume | F8: =IF($O8="","",INDEX(Scoring!$B$29:$B$361,MATCH($O8,Scoring!$AS$29:$AS$361,0))) -> Methotrexate | G8: =IF($O8="","",INDEX(Scoring!$AG$29:$AG$361,MATCH($O8,Scoring!$AS$29:$AS$361,0))) -> Methotrexate; Methotrexate Subcutaneous; Methotrexate Intas | H8: =IF($O8="","",INDEX(Scoring!$C$29:$C$361,MATCH($O8,Scoring!$AS$29:$AS$361,0))) -> Oncology and immunology: leukaemia, lymphoma, bone cancer, rheumatoid arthritis, psoriasis | I8: =IF($O8="","",INDEX(Scoring!$I$29:$I$361,MATCH($O8,Scoring!$AS$29:$AS$361,0))) -> Vial, Prefilled syringe | J8: =IF($O8="","",INDEX(Scoring!$Z$29:$Z$361,MATCH($O8,Scoring!$AS$29:$AS$361,0))) -> 50 mg/2 mL vial; 500 mg/20 mL vial; 1000 mg/40 mL vial; 10 mg/0.2 mL pre-filled syringe (+2 more) | K8: =IF($O8="","",IF(INDEX(Scoring!$D$29:$D$361,MATCH($O8,Scoring!$AS$29:$AS$361,0))="",INDEX(Scoring!$AF$29:$AF$361,MATCH($O8,Scoring!$AS$29:$AS$361,0)),INDEX(Scoring!$D$29:$D$361,MATCH($O8,Scoring!$AS$29:$AS$361,0)))) -> 50.77 | L8: =IF($O8="","",INDEX(Scoring!$L$29:$L$361,MATCH($O8,Scoring!$AS$29:$AS$361,0))) -> 1282 | M8: =IF($O8="","",INDEX(Scoring!$N$29:$N$361,MATCH($O8,Scoring!$AS$29:$AS$361,0))) -> 16792.84 | N8: =IF($O8="","",INDEX(Scoring!$AI$29:$AI$361,MATCH($O8,Scoring!$AS$29:$AS$361,0))) -> UK, Canada, Australia, UK-NI | EU/EEA (25): Germany, France, Netherlands, Belgium + 21 more | O8: =IFERROR(SMALL(Scoring!$AS$29:$AS$361,4),"") -> 1004
A9: =IF($O9="","",INT($O9/1000)) -> 1 | B9: =IF($O9="","",INDEX(Scoring!$A$29:$A$361,MATCH($O9,Scoring!$AS$29:$AS$361,0))) -> Intas | C9: =IF($O9="","",IF(INDEX(Scoring!$AM$29:$AM$361,MATCH($O9,Scoring!$AS$29:$AS$361,0))="","–",INDEX(Scoring!$AM$29:$AM$361,MATCH($O9,Scoring!$AS$29:$AS$361,0)))) -> 5 | D9: =IF($O9="","",INDEX(Scoring!$AK$29:$AK$361,MATCH($O9,Scoring!$AS$29:$AS$361,0))) -> Priority 1 | E9: =IF($O9="","",INDEX(Scoring!$AL$29:$AL$361,MATCH($O9,Scoring!$AS$29:$AS$361,0))) -> High price · high volume | F9: =IF($O9="","",INDEX(Scoring!$B$29:$B$361,MATCH($O9,Scoring!$AS$29:$AS$361,0))) -> Epinephrine (Adrenaline) | G9: =IF($O9="","",INDEX(Scoring!$AG$29:$AG$361,MATCH($O9,Scoring!$AS$29:$AS$361,0))) -> Adrenaline Accord | H9: =IF($O9="","",INDEX(Scoring!$C$29:$C$361,MATCH($O9,Scoring!$AS$29:$AS$361,0))) -> Critical care: anaphylaxis, cardiac arrest, shock | I9: =IF($O9="","",INDEX(Scoring!$I$29:$I$361,MATCH($O9,Scoring!$AS$29:$AS$361,0))) -> Prefilled syringe | J9: =IF($O9="","",INDEX(Scoring!$Z$29:$Z$361,MATCH($O9,Scoring!$AS$29:$AS$361,0))) -> 1 mg/10 mL pre-filled syringe | K9: =IF($O9="","",IF(INDEX(Scoring!$D$29:$D$361,MATCH($O9,Scoring!$AS$29:$AS$361,0))="",INDEX(Scoring!$AF$29:$AF$361,MATCH($O9,Scoring!$AS$29:$AS$361,0)),INDEX(Scoring!$D$29:$D$361,MATCH($O9,Scoring!$AS$29:$AS$361,0)))) -> 28.67 | L9: =IF($O9="","",INDEX(Scoring!$L$29:$L$361,MATCH($O9,Scoring!$AS$29:$AS$361,0))) -> 912 | M9: =IF($O9="","",INDEX(Scoring!$N$29:$N$361,MATCH($O9,Scoring!$AS$29:$AS$361,0))) -> 4620.39 | N9: =IF($O9="","",INDEX(Scoring!$AI$29:$AI$361,MATCH($O9,Scoring!$AS$29:$AS$361,0))) -> EU/EEA (3): France, Netherlands, Portugal | O9: =IFERROR(SMALL(Scoring!$AS$29:$AS$361,5),"") -> 1005
